Workbook
Name Atividade_Administrativa: PARAMETROS!$AE$19:$AL$19
Name Banco_Questões: PARAMETROS!$AE$20:$AJ$20
Name Conselho_Editorial: PARAMETROS!$AE$15:$AL$15
Name Conselho_Profissional: PARAMETROS!$AE$24:$AI$24
Name CPA: PARAMETROS!$AE$25:$AI$25
Name Disciplinas_Digitais: PARAMETROS!$AE$28:$AJ$28
Name Elaborar_Extensão: PARAMETROS!$AE$13:$AR$13
Name Formação_Docente: PARAMETROS!$AE$21:$AM$21
Name NDE: PARAMETROS!$AE$26:$AG$26
Name Organização_ENADE: PARAMETROS!$AE$22:$AU$22
Name Organização_Eventos: PARAMETROS!$AE$23:$AM$23
Name Orientar_Estagio: PARAMETROS!$AE$6:$AL$6
Name Orientar_Extensão: PARAMETROS!$AE$14:$AL$14
Name Orientar_IC: PARAMETROS!$AE$16:$AI$16
Name Orientar_Monitoria: PARAMETROS!$AE$8:$AJ$8
Name Orientar_Preceptoria: PARAMETROS!$AE$7:$AJ$7
Name Orientar_TCC: PARAMETROS!$AE$9:$AL$9
Name Participação_Núcleo: PARAMETROS!$AE$27:$AI$27
Name Planejamento_Aula: PARAMETROS!$AE$4:$AH$4
Name Planejamento_Disciplina: PARAMETROS!$AE$5:$AL$5
Name Produção_Gravação: PARAMETROS!$AE$10:$AM$10
Name Produção_Livros: PARAMETROS!$AE$11:$AM$11
Name Produção_Roteiro_Video: PARAMETROS!$AE$12:$AM$12
Name Projeto_Inovação: PARAMETROS!$AE$17:$AM$17
Name Projeto_Pesquisa: PARAMETROS!$AE$18:$AM$18

Sheet PARAMETROS
A1: NOME | B1: CHAPA | C1: CH SEMANAL | D1: CH LETIVA | E1: CH NÃO-LETIVA | F1: EQUIPE (RH) | G1: CPF | H1: STATUS | I1: CARGO | K1: MÓDULO | L1: ORDEM | M1: DIA | N1: HORÁRIOS | U1: ID | V1: NATUREZA | W1: GRUPO ATIVIDADE | X1: ATOR | Y1: ATIVIDADE | Z1: CLASSE DE ANÁLISE | AA1: GLOSSÁRIO | AB1: TIPO ATIVIDADE | AC1: OBSERVAÇÃO | AD1: CHAVE | AE1: CH MIN VAL | AF1: CH MAX VAL
AY2: {=IFERROR( FILTRAR( PARAMETROS!$AE$4:$AR$99, (PARAMETROS!$Y$4:$Y$99='PREENCHIMENTO|NÃO-LETIVAS'!X4)* (PARAMETROS!$AE$4:$AR$99<>"") ), "")}
A3: ADRIANA DOS SANTOS SOUZA CREVELIN | B3: 012009006172 | C3: 12 | D3: =IF(I3="PROFESSOR REGENTE",IF(C3=40,C3*0.5,IF(C3>11,C3*0.75,C3)),IF(I3="PROFESSOR DE ENSINO SUPERIOR EAD",IF(C3=40,4,2),0)) -> 9 | E3: =IF(OR(I3="PROFESSOR REGENTE",I3="PROFESSOR DE ENSINO SUPERIOR PRESENCIAL"),C3-D3,IF(C3=40,12,6)) -> 3 | F3: JULIANA MORAES DA SILVA | G3: 29290419865 | H3: ATIVO | I3: PROFESSOR REGENTE | K3: 51|2026 | L3: 1 | M3: 2 - Segunda | N3: 19:00 às 20:30
A4: ADRIANO PARRAS MENEGATTI | B4: 012009004349 | C4: 20 | D4: =IF(I4="PROFESSOR REGENTE",IF(C4=40,C4*0.5,IF(C4>11,C4*0.75,C4)),IF(I4="PROFESSOR DE ENSINO SUPERIOR EAD",IF(C4=40,4,2),0)) -> 2 | E4: =IF(OR(I4="PROFESSOR REGENTE",I4="PROFESSOR DE ENSINO SUPERIOR PRESENCIAL"),C4-D4,IF(C4=40,12,6)) -> 6 | F4: JULIANA MORAES DA SILVA | G4: 08784034939 | H4: ATIVO | I4: PROFESSOR DE ENSINO SUPERIOR EAD | K4: 52|2026 | L4: 2 | M4: 3 - Terça | N4: 20:40 às 22:10 | U4: 1 | V4: Ensino | W4: Aulas | X4: Professor EAD, Professor Regente | Y4: Planejamento da Aula | Z4: Atividades de Ensino | AA4: Organizar os materiais e recursos didáticos para ministração da aula, bem como elaborar o portfólio da disciplina. | AB4: Horas não letivas | AC4: Deve ser feito registro por disciplina | AD4: Planejamento_Aula | AE4: 0 | AF4: 0.5 | AG4: =AF4+0.25 -> 0.75 | AH4: 1
A5: ADRIANO RUY MATSUO | B5: 012009003801 | C5: 40 | D5: =IF(I5="PROFESSOR REGENTE",IF(C5=40,C5*0.5,IF(C5>11,C5*0.75,C5)),IF(I5="PROFESSOR DE ENSINO SUPERIOR EAD",IF(C5=40,4,2),0)) -> 4 | E5: =IF(OR(I5="PROFESSOR REGENTE",I5="PROFESSOR DE ENSINO SUPERIOR PRESENCIAL"),C5-D5,IF(C5=40,12,6)) -> 12 | F5: JULIANA MORAES DA SILVA | G5: 05088387970 | H5: ATIVO | I5: PROFESSOR DE ENSINO SUPERIOR EAD | K5: 53|2026 | L5: ESTENDIDA | M5: 4 - Quarta | U5: 2 | V5: Ensino | W5: Aulas | X5: Professor EAD, Professor Regente | Y5: Planejamento da Disciplina | Z5: Atividades de Ensino | AA5: Atualizar ementa, bibliografia e plano de ensino, conforme deliberação do NDE. Elaborar o plano de ação da disciplina. Elaborar os slides padrão para a aula ao vivo. Realizar o apoio e orientação aos Tutores de Prática e aos Professores Mediadores vinculados às suas disciplinas. | AB5: Horas não letivas | AC5: Deve ser feito registro por disciplina | AD5: Planejamento_Disciplina | AE5: 0 | AF5: 0.5 | AG5: =AF5+0.25 -> 0.75 | AH5: 1 | AI5: 1.25 | AJ5: 1.5 | AK5: 1.75 | AL5: 2
A6: ADRIELE ANDRADE CEOLA | B6: 012009003713 | C6: 20 | D6: =IF(I6="PROFESSOR REGENTE",IF(C6=40,C6*0.5,IF(C6>11,C6*0.75,C6)),IF(I6="PROFESSOR DE ENSINO SUPERIOR EAD",IF(C6=40,4,2),0)) -> 2 | E6: =IF(OR(I6="PROFESSOR REGENTE",I6="PROFESSOR DE ENSINO SUPERIOR PRESENCIAL"),C6-D6,IF(C6=40,12,6)) -> 6 | F6: JULIANA MORAES DA SILVA | G6: 09015334919 | H6: ATIVO | I6: PROFESSOR DE ENSINO SUPERIOR EAD | K6: 54|2026 | M6: 5 - Quinta | U6: 3 | V6: Ensino | W6: Orientação | X6: Professor EAD, Professor Regente, Professor Mediador | Y6: Orientar Estágio Curricular (Obrigatório) | Z6: Estágio curricular | AA6: Orientar e acompanhar as atividades referentes ao Estágio Curricular junto aos estudantes e supervisores/preceptores. Realizar plantões mensais com os estudantes, gravar tutoriais, participação em seminário, elaborar e cadastrar propostas avaliativas. | AB6: Horas não letivas | AC6: Deve ser feito registro por disciplina e turma | AD6: Orientar_Estagio | AE6: 0 | AF6: 0.5 | AG6: =AF6+0.25 -> 0.75 | AH6: 1 | AI6: 1.25 | AJ6: 1.5 | AK6: 1.75 | AL6: 2
A7: ALEXANDRE LUIS PONCE MARTINS | B7: 012009004457 | C7: 20 | D7: =IF(I7="PROFESSOR REGENTE",IF(C7=40,C7*0.5,IF(C7>11,C7*0.75,C7)),IF(I7="PROFESSOR DE ENSINO SUPERIOR EAD",IF(C7=40,4,2),0)) -> 2 | E7: =IF(OR(I7="PROFESSOR REGENTE",I7="PROFESSOR DE ENSINO SUPERIOR PRESENCIAL"),C7-D7,IF(C7=40,12,6)) -> 6 | F7: JULIANA MORAES DA SILVA | G7: 06923731950 | H7: ATIVO | I7: PROFESSOR DE ENSINO SUPERIOR EAD | M7: 6 - Sexta | U7: 4 | V7: Ensino | W7: Orientação | X7: Professor EAD, Professor Regente, Professor Regente de Polo | Y7: Orientar Preceptoria e Supervisão (Saúde/Educação) | Z7: Estágio curricular | AA7: Preceptoria e supervisão em estágios curriculares obrigatórios. | AB7: Horas não letivas | AD7: Orientar_Preceptoria | AE7: 0 | AF7: 1 | AG7: =AF7+0.25 -> 1.25 | AH7: 1.5 | AI7: 1.75 | AJ7: 2
A8: ALINE DOS SANTOS PRETO DE SOUZA | B8: 012009005709 | C8: 20 | D8: =IF(I8="PROFESSOR REGENTE",IF(C8=40,C8*0.5,IF(C8>11,C8*0.75,C8)),IF(I8="PROFESSOR DE ENSINO SUPERIOR EAD",IF(C8=40,4,2),0)) -> 2 | E8: =IF(OR(I8="PROFESSOR REGENTE",I8="PROFESSOR DE ENSINO SUPERIOR PRESENCIAL"),C8-D8,IF(C8=40,12,6)) -> 6 | F8: JULIANA MORAES DA SILVA | G8: 00780598954 | H8: ATIVO | I8: PROFESSOR DE ENSINO SUPERIOR EAD | U8: 5 | V8: Ensino | W8: Orientação | X8: Professor EAD, Professor Regente, Professor Mediador | Y8: Orientar Projeto de Monitoria | Z8: Orient. Ensino - Demais | AA8: Orientar Projetos de Monitoria, a partir dos dados enviados pelo Núcleo de Monitoria. Produzir nivelamento, oficinas e projetos de ensino. | AB8: Horas não letivas | AD8: Orientar_Monitoria | AE8: 0 | AF8: 1 | AG8: =AF8+0.25 -> 1.25 | AH8: 1.5 | AI8: 1.75 | AJ8: 2
A9: AMANDA FERREIRA GUIMARAES | B9: 012009006176 | C9: 12 | D9: =IF(I9="PROFESSOR REGENTE",IF(C9=40,C9*0.5,IF(C9>11,C9*0.75,C9)),IF(I9="PROFESSOR DE ENSINO SUPERIOR EAD",IF(C9=40,4,2),0)) -> 9 | E9: =IF(OR(I9="PROFESSOR REGENTE",I9="PROFESSOR DE ENSINO SUPERIOR PRESENCIAL"),C9-D9,IF(C9=40,12,6)) -> 3 | F9: JULIANA MORAES DA SILVA | G9: 34572496870 | H9: ADMISSÃO PROX.MÊS | I9: PROFESSOR REGENTE | U9: 6 | V9: Ensino | W9: Orientação | X9: Professor EAD, Professor Regente, Professor Mediador | Y9: Orientar Trabalho de Conclusão de Curso (TCC) | Z9: TCC/Monografia | AA9: Orientar e acompanhar as atividades referentes ao TCC/Monografia junto aos estudantes. Realizar plantões periodicos e/ou bancas com os estudantes. | AB9: Horas não letivas | AC9: Deve ser feito registro por turma | AD9: Orientar_TCC | AE9: 0 | AF9: 0.5 | AG9: =AF9+0.25 -> 0.75 | AH9: 1 | AI9: 1.25 | AJ9: 1.5 | AK9: 1.75 | AL9: 2
A10: ANA CLAUDIA DE ABREU | B10: 012009004231 | C10: 20 | D10: =IF(I10="PROFESSOR REGENTE",IF(C10=40,C10*0.5,IF(C10>11,C10*0.75,C10)),IF(I10="PROFESSOR DE ENSINO SUPERIOR EAD",IF(C10=40,4,2),0)) -> 2 | E10: =IF(OR(I10="PROFESSOR REGENTE",I10="PROFESSOR DE ENSINO SUPERIOR PRESENCIAL"),C10-D10,IF(C10=40,12,6)) -> 6 | F10: JULIANA MORAES DA SILVA | G10: 07853006942 | H10: ATIVO | I10: PROFESSOR DE ENSINO SUPERIOR EAD | U10: 7 | V10: Ensino | W10: Produção de material didático | X10: Professor EAD, Professor Regente | Y10: Produção de material didático - Gravações | Z10: Gravações | AA10: Produzir materiais gravados para as disciplinas, tais como: gravação de aulas conceituais, gravação de aulas em pontes de feriados, gravação de autoatividades, gravação de podcasts, gravação de cápsulas de conhecimento, gravação de atividades práticas, entre outros. | AB10: Horas não letivas | AC10: Deve ser feito registro por disciplina | AD10: Produção_Gravação | AE10: 0 | AF10: 0.25 | AG10: =AF10+0.25 -> 0.5 | AH10: 0.75 | AI10: 1 | AJ10: 1.25 | AK10: 1.5 | AL10: 1.75 | AM10: 2
A11: ANA ELISA LAVEZO | B11: 012009003540 | C11: 40 | D11: =IF(I11="PROFESSOR REGENTE",IF(C11=40,C11*0.5,IF(C11>11,C11*0.75,C11)),IF(I11="PROFESSOR DE ENSINO SUPERIOR EAD",IF(C11=40,4,2),0)) -> 4 | E11: =IF(OR(I11="PROFESSOR REGENTE",I11="PROFESSOR DE ENSINO SUPERIOR PRESENCIAL"),C11-D11,IF(C11=40,12,6)) -> 12 | F11: JULIANA MORAES DA SILVA | G11: 02651880914 | H11: ATIVO | I11: PROFESSOR DE ENSINO SUPERIOR EAD | U11: 8 | V11: Ensino | W11: Produção de material didático | X11: Professor EAD, Professor Regente | Y11: Produção de material didático - Livros e Outros | Z11: Gestão da disciplina | AA11: Revisar livro da disciplina. Produzir, revisar e atualizar materiais didáticos, tais como: trilhas de aprendizagens, materiais complementares, diretrizes, e-books, manuais, objetos de aprendizagem, entre outros relativos às disciplinas. | AB11: Horas não letivas | AC11: Deve ser feito registro por disciplina | AD11: Produção_Livros | AE11: 0 | AF11: 0.25 | AG11: =AF11+0.25 -> 0.5 | AH11: 0.75 | AI11: 1 | AJ11: 1.25 | AK11: 1.5 | AL11: 1.75 | AM11: 2
A12: ANA LUCIA SALES DE LIMA | B12: 012009003558 | C12: 20 | D12: =IF(I12="PROFESSOR REGENTE",IF(C12=40,C12*0.5,IF(C12>11,C12*0.75,C12)),IF(I12="PROFESSOR DE ENSINO SUPERIOR EAD",IF(C12=40,4,2),0)) -> 2 | E12: =IF(OR(I12="PROFESSOR REGENTE",I12="PROFESSOR DE ENSINO SUPERIOR PRESENCIAL"),C12-D12,IF(C12=40,12,6)) -> 6 | F12: JULIANA MORAES DA SILVA | G12: 04130621980 | H12: ATIVO | I12: PROFESSOR DE ENSINO SUPERIOR EAD | U12: 9 | V12: Ensino | W12: Produção de material didático | X12: Professor EAD, Professor Regente | Y12: Produção de material didático - Roteiro de Vídeos | Z12: Elaboração de roteiros de vídeos | AA12: Elaborar roteiros/materiais de apoio para as gravações dos vídeos, tais como: aulas conceituais, aulas em pontes de feriados, autoatividades, podcasts, cápsulas de conhecimento, materiais para redes sociais, entre outros. | AB12: Horas não letivas | AC12: Deve ser feito registro por disciplina | AD12: Produção_Roteiro_Video | AE12: 0 | AF12: 0.25 | AG12: =AF12+0.25 -> 0.5 | AH12: 0.75 | AI12: 1 | AJ12: 1.25 | AK12: 1.5 | AL12: 1.75 | AM12: 2
A13: ANA PAULA CAVALCANTE LIMAO DA SILVA | B13: 012009004350 | C13: 20 | D13: =IF(I13="PROFESSOR REGENTE",IF(C13=40,C13*0.5,IF(C13>11,C13*0.75,C13)),IF(I13="PROFESSOR DE ENSINO SUPERIOR EAD",IF(C13=40,4,2),0)) -> 2 | E13: =IF(OR(I13="PROFESSOR REGENTE",I13="PROFESSOR DE ENSINO SUPERIOR PRESENCIAL"),C13-D13,IF(C13=40,12,6)) -> 6 | F13: JULIANA MORAES DA SILVA | G13: 00951182927 | H13: ATIVO | I13: PROFESSOR DE ENSINO SUPERIOR EAD | U13: 10 | V13: Extensão | W13: Organização e Acompanhamento | X13: Professor EAD, Professor Regente, Professor Mediador | Y13: Elaborar Projeto de Extensão | Z13: Extensão | AA13: Elaborar Projeto de Extensão de acordo com as premissas estabelecidas e mediante aprovações necessárias dentro da BU. | AB13: Horas não letivas | AC13: Deve ser feito registro por projeto | AD13: Elaborar_Extensão | AE13: 0 | AF13: 1 | AG13: =AF13+0.25 -> 1.25 | AH13: 1.5 | AI13: 1.75 | AJ13: 2 | AK13: 2.25 | AL13: 2.5 | AM13: 2.75 | AN13: 3 | AO13: 3.25 | AP13: 3.5 | AQ13: 3.75 | AR13: 4
A14: ANDERSON DOUGLAS DA SILVA | B14: 012009006177 | C14: 12 | D14: =IF(I14="PROFESSOR REGENTE",IF(C14=40,C14*0.5,IF(C14>11,C14*0.75,C14)),IF(I14="PROFESSOR DE ENSINO SUPERIOR EAD",IF(C14=40,4,2),0)) -> 9 | E14: =IF(OR(I14="PROFESSOR REGENTE",I14="PROFESSOR DE ENSINO SUPERIOR PRESENCIAL"),C14-D14,IF(C14=40,12,6)) -> 3 | F14: JULIANA MORAES DA SILVA | G14: 34254592876 | H14: ADMISSÃO PROX.MÊS | I14: PROFESSOR REGENTE | U14: 11 | V14: Extensão | W14: Organização e Acompanhamento | X14: Professor EAD, Professor Regente, Professor Mediador | Y14: Orientar Projeto de Extensão | Z14: Extensão | AA14: Orientar e acompanhar as atividades referentes à Extensão junto aos estudantes. Realizar plantões mensais com os estudantes. | AB14: Horas não letivas | AC14: Deve ser feito registro por projeto | AD14: Orientar_Extensão | AE14: 0 | AF14: 0.25 | AG14: =AF14+0.25 -> 0.5 | AH14: 0.75 | AI14: 1 | AJ14: 1.5 | AK14: 1.75 | AL14: 2
A15: ANDERSON KATSUMI MIYATAKE | B15: 012009003470 | C15: 40 | D15: =IF(I15="PROFESSOR REGENTE",IF(C15=40,C15*0.5,IF(C15>11,C15*0.75,C15)),IF(I15="PROFESSOR DE ENSINO SUPERIOR EAD",IF(C15=40,4,2),0)) -> 4 | E15: =IF(OR(I15="PROFESSOR REGENTE",I15="PROFESSOR DE ENSINO SUPERIOR PRESENCIAL"),C15-D15,IF(C15=40,12,6)) -> 12 | F15: JULIANA MORAES DA SILVA | G15: 34064839846 | H15: ATIVO | I15: PROFESSOR DE ENSINO SUPERIOR EAD | U15: 12 | V15: Pesquisa | W15: Orientação Pesquisa | X15: Professor EAD, Professor Regente, Professor Mediador | Y15: Conselho editorial | Z15: Orient.IC/TI | AA15: Compor e atuar junto ao conselho editorial das revistas institucionais. | AB15: Horas não letivas | AD15: Conselho_Editorial | AE15: 0 | AF15: 0.5 | AG15: =AF15+0.25 -> 0.75 | AH15: 1 | AI15: 1.25 | AJ15: 1.5 | AK15: 1.75 | AL15: 2
A16: ANDRESSA MARTINS DIAS FERREIRA | B16: 012009005339 | C16: 40 | D16: =IF(I16="PROFESSOR REGENTE",IF(C16=40,C16*0.5,IF(C16>11,C16*0.75,C16)),IF(I16="PROFESSOR DE ENSINO SUPERIOR EAD",IF(C16=40,4,2),0)) -> 4 | E16: =IF(OR(I16="PROFESSOR REGENTE",I16="PROFESSOR DE ENSINO SUPERIOR PRESENCIAL"),C16-D16,IF(C16=40,12,6)) -> 12 | F16: JULIANA MORAES DA SILVA | G16: 07256864990 | H16: ATIVO | I16: PROFESSOR DE ENSINO SUPERIOR EAD | U16: 13 | V16: Pesquisa | W16: Orientação Pesquisa | X16: Professor EAD, Professor Regente, Professor Mediador | Y16: Orientação de Iniciação Científica | Z16: Orient.IC/TI | AA16: Orientar estudantes de graduação em projetos de Iniciação Científica, promovendo a formação acadêmica por meio da participação em atividades investigativas, bem como orientar e organizar artigos para publicação em eventos e revistas. | AB16: Horas não letivas | AC16: Deve ser feito registro por estudante | AD16: Orientar_IC | AE16: 0 | AF16: 0.25 | AG16: =AF16+0.25 -> 0.5 | AH16: 0.75 | AI16: 1
A17: ANGELA FERREIRA DE LIMA PIZZAIA | B17: 012009004467 | C17: 40 | D17: =IF(I17="PROFESSOR REGENTE",IF(C17=40,C17*0.5,IF(C17>11,C17*0.75,C17)),IF(I17="PROFESSOR DE ENSINO SUPERIOR EAD",IF(C17=40,4,2),0)) -> 4 | E17: =IF(OR(I17="PROFESSOR REGENTE",I17="PROFESSOR DE ENSINO SUPERIOR PRESENCIAL"),C17-D17,IF(C17=40,12,6)) -> 12 | F17: JULIANA MORAES DA SILVA | G17: 93494599904 | H17: ATIVO | I17: PROFESSOR DE ENSINO SUPERIOR EAD | U17: 14 | V17: Pesquisa | W17: Orientação Pesquisa | X17: Coordenador de Curso, Professor EAD, Professor Regente, Professor Mediador | Y17: Projeto de Inovação | Z17: UA com Base Regulatória | AA17: Desenvolver ou participar de iniciativas voltadas à criação, testagem ou implementação de soluções inovadoras. | AB17: Horas não letivas | AC17: Deve ser feito registro por projeto | AD17: Projeto_Inovação | AE17: 0 | AF17: 0.25 | AG17: =AF17+0.25 -> 0.5 | AH17: 0.75 | AI17: 1 | AJ17: 1.25 | AK17: 1.5 | AL17: 1.75 | AM17: 2
A18: ANTONIO ALVES PEREIRA JUNIOR | B18: 012009006181 | C18: 12 | D18: =IF(I18="PROFESSOR REGENTE",IF(C18=40,C18*0.5,IF(C18>11,C18*0.75,C18)),IF(I18="PROFESSOR DE ENSINO SUPERIOR EAD",IF(C18=40,4,2),0)) -> 9 | E18: =IF(OR(I18="PROFESSOR REGENTE",I18="PROFESSOR DE ENSINO SUPERIOR PRESENCIAL"),C18-D18,IF(C18=40,12,6)) -> 3 | F18: JULIANA MORAES DA SILVA | G18: 06235685947 | H18: ADMISSÃO PROX.MÊS | I18: PROFESSOR REGENTE | U18: 15 | V18: Pesquisa | W18: Orientação Pesquisa | X18: Professor EAD, Professor Regente, Professor Mediador | Y18: Projeto de Pesquisa | Z18: UA com Base Regulatória | AA18: Participar ou coordenar projetos de pesquisa científica vinculados à instituição, com objetivos definidos, cronograma, metodologia e registro formal junto à área responsável. A atividade pode envolver coleta e análise de dados, elaboração de relatórios, artigos e participação em eventos científicos. | AB18: Horas não letivas | AC18: Deve ser feito registro por projeto | AD18: Projeto_Pesquisa | AE18: 0 | AF18: 0.25 | AG18: =AF18+0.25 -> 0.5 | AH18: 0.75 | AI18: 1 | AJ18: 1.25 | AK18: 1.5 | AL18: 1.75 | AM18: 2
A19: AUGUSTO JOAO STRICTAR MORETTO JUNIOR | B19: 012009003638 | C19: 20 | D19: =IF(I19="PROFESSOR REGENTE",IF(C19=40,C19*0.5,IF(C19>11,C19*0.75,C19)),IF(I19="PROFESSOR DE ENSINO SUPERIOR EAD",IF(C19=40,4,2),0)) -> 2 | E19: =IF(OR(I19="PROFESSOR REGENTE",I19="PROFESSOR DE ENSINO SUPERIOR PRESENCIAL"),C19-D19,IF(C19=40,12,6)) -> 6 | F19: JULIANA MORAES DA SILVA | G19: 07999576905 | H19: ATIVO | I19: PROFESSOR DE ENSINO SUPERIOR EAD | U19: 16 | V19: Planejamento | W19: Administrativas | X19: Professor EAD, Professor Regente, Professor Mediador | Y19: Atividades Administrativas/Gestão | Z19: Administrativas | AA19: Realizar atividades administrativas relacionadas ao curso, de acordo com orientação da coordenação. Por exemplo: ajustar e revisar atas, acompanhar e coletar assinaturas nas atas, acompanhar e elaborar portfólios de atividades do curso, participar de avaliações de MEC, entre outros. | AB19: Horas não letivas | AD19: Atividade_Administrativa | AE19: 0 | AF19: 0.5 | AG19: =AF19+0.25 -> 0.75 | AH19: 1 | AI19: 1.25 | AJ19: 1.5 | AK19: 1.75 | AL19: 2
A20: BARBARA LETICIA DA SILVA GUEDES DE MOURA | B20: 012009005453 | C20: 20 | D20: =IF(I20="PROFESSOR REGENTE",IF(C20=40,C20*0.5,IF(C20>11,C20*0.75,C20)),IF(I20="PROFESSOR DE ENSINO SUPERIOR EAD",IF(C20=40,4,2),0)) -> 2 | E20: =IF(OR(I20="PROFESSOR REGENTE",I20="PROFESSOR DE ENSINO SUPERIOR PRESENCIAL"),C20-D20,IF(C20=40,12,6)) -> 6 | F20: GISLAINE CARDOSO DE SOUZA FIAES | G20: 06229448947 | H20: ATIVO | I20: PROFESSOR DE ENSINO SUPERIOR EAD | U20: 17 | V20: Planejamento | W20: Gestão Acadêmica | X20: Professor EAD, Professor Regente, Professor Mediador | Y20: Banco de Questões | Z20: Gestão da disciplina | AA20: Elaborar, cadastrar, revisar e cancelar questões de acordo com as premissas estabelecidas para cada BU | AB20: Horas não letivas | AC20: Deve ser feito registro por disciplina | AD20: Banco_Questões | AE20: 0 | AF20: 1 | AG20: =AF20+0.25 -> 1.25 | AH20: 1.5 | AI20: 1.75 | AJ20: 2
A21: BIANCA PAIXAO IZALBERTI | B21: 012009004310 | C21: 40 | D21: =IF(I21="PROFESSOR REGENTE",IF(C21=40,C21*0.5,IF(C21>11,C21*0.75,C21)),IF(I21="PROFESSOR DE ENSINO SUPERIOR EAD",IF(C21=40,4,2),0)) -> 4 | E21: =IF(OR(I21="PROFESSOR REGENTE",I21="PROFESSOR DE ENSINO SUPERIOR PRESENCIAL"),C21-D21,IF(C21=40,12,6)) -> 12 | F21: JULIANA MORAES DA SILVA | G21: 06937762933 | H21: ATIVO | I21: PROFESSOR DE ENSINO SUPERIOR EAD | U21: 18 | V21: Planejamento | W21: Gestão Acadêmica | X21: Coordenador de Curso, Professor EAD, Professor Regente, Professor Mediador | Y21: Formação Docente | Z21: Formação continuada | AA21: Participar de programas, cursos, oficinas, reuniões, treinamentos ou eventos institucionais voltados ao desenvolvimento pedagógico, tecnológico ou científico, com o objetivo de aprimorar a atuação docente e alinhar práticas ao projeto educacional da instituição. | AB21: Horas não letivas | AD21: Formação_Docente | AE21: 0 | AF21: 0.25 | AG21: =AF21+0.25 -> 0.5 | AH21: 0.75 | AI21: 1 | AJ21: 1.25 | AK21: 1.5 | AL21: 1.75 | AM21: 2
A22: BRUNA MAYARA ROLDAO FERREIRA | B22: 012009005987 | C22: 20 | D22: =IF(I22="PROFESSOR REGENTE",IF(C22=40,C22*0.5,IF(C22>11,C22*0.75,C22)),IF(I22="PROFESSOR DE ENSINO SUPERIOR EAD",IF(C22=40,4,2),0)) -> 2 | E22: =IF(OR(I22="PROFESSOR REGENTE",I22="PROFESSOR DE ENSINO SUPERIOR PRESENCIAL"),C22-D22,IF(C22=40,12,6)) -> 6 | F22: JULIANA MORAES DA SILVA | G22: 06489968916 | H22: ATIVO | I22: PROFESSOR DE ENSINO SUPERIOR EAD | U22: 19 | V22: Planejamento | W22: Gestão Acadêmica | X22: Professor EAD, Professor Regente | Y22: Organização do ENADE | Z22: Gestão pedagógica | AA22: Atuar na organização de processos relativos ao ENADE. Preencher questionário de avaliação prática dos estudantes (licenciaturas). | AB22: Horas não letivas | AD22: Organização_ENADE | AE22: 0 | AF22: 0.25 | AG22: =AF22+0.25 -> 0.5 | AH22: 0.75 | AI22: 1 | AJ22: 1.25 | AK22: 1.5 | AL22: 1.75 | AM22: 2 | AN22: 2.25 | AO22: 2.5 | AP22: 2.75 | AQ22: 3 | AR22: 3.25 | AS22: 3.5 | AT22: 3.75 | AU22: 4
A23: CARINA SERON DA FONSECA | B23: 012009006205 | C23: 12 | D23: =IF(I23="PROFESSOR REGENTE",IF(C23=40,C23*0.5,IF(C23>11,C23*0.75,C23)),IF(I23="PROFESSOR DE ENSINO SUPERIOR EAD",IF(C23=40,4,2),0)) -> 9 | E23: =IF(OR(I23="PROFESSOR REGENTE",I23="PROFESSOR DE ENSINO SUPERIOR PRESENCIAL"),C23-D23,IF(C23=40,12,6)) -> 3 | F23: JULIANA MORAES DA SILVA | G23: 06982676994 | H23: ADMISSÃO PROX.MÊS | I23: PROFESSOR REGENTE | U23: 20 | V23: Planejamento | W23: Organização de Eventos Acadêmicos | X23: Professor EAD, Professor Regente, Professor Mediador | Y23: Organização de Eventos Acadêmicos | Z23: Eventos | AA23: Organizar e participar de eventos acadêmicos de interesse da BU. | AB23: Horas não letivas | AD23: Organização_Eventos | AE23: 0 | AF23: 0.25 | AG23: =AF23+0.25 -> 0.5 | AH23: 0.75 | AI23: 1 | AJ23: 1.25 | AK23: 1.5 | AL23: 1.75 | AM23: 2
A24: CARLA FABIANA DE ANDRADE GONCALVES IORI | B24: 012009003517 | C24: 40 | D24: =IF(I24="PROFESSOR REGENTE",IF(C24=40,C24*0.5,IF(C24>11,C24*0.75,C24)),IF(I24="PROFESSOR DE ENSINO SUPERIOR EAD",IF(C24=40,4,2),0)) -> 4 | E24: =IF(OR(I24="PROFESSOR REGENTE",I24="PROFESSOR DE ENSINO SUPERIOR PRESENCIAL"),C24-D24,IF(C24=40,12,6)) -> 12 | F24: JULIANA MORAES DA SILVA | G24: 03652555996 | H24: ATIVO | I24: PROFESSOR DE ENSINO SUPERIOR EAD | U24: 21 | V24: Planejamento | W24: Unidade Acadêmica Com Base Regulatória | X24: Coordenador de Curso, Professor EAD, Professor Regente, Professor Mediador | Y24: Conselho Profissional | Z24: UA com Base Regulatória | AA24: Participar da composição de conselho profissional (CAU, CREA, CRA, COREN, entre outros). | AB24: Horas não letivas | AC24: Deve ser feito registro por conselho | AD24: Conselho_Profissional | AE24: 0 | AF24: 0.25 | AG24: =AF24+0.25 -> 0.5 | AH24: 0.75 | AI24: 1
A25: CAROLINE PREVIATO SOUZA | B25: 012009004488 | C25: 40 | D25: =IF(I25="PROFESSOR REGENTE",IF(C25=40,C25*0.5,IF(C25>11,C25*0.75,C25)),IF(I25="PROFESSOR DE ENSINO SUPERIOR EAD",IF(C25=40,4,2),0)) -> 4 | E25: =IF(OR(I25="PROFESSOR REGENTE",I25="PROFESSOR DE ENSINO SUPERIOR PRESENCIAL"),C25-D25,IF(C25=40,12,6)) -> 12 | F25: JULIANA MORAES DA SILVA | G25: 06374431952 | H25: ATIVO | I25: PROFESSOR DE ENSINO SUPERIOR EAD | U25: 22 | V25: Planejamento | W25: Unidade Acadêmica Com Base Regulatória | X25: Coordenador de Curso, Professor EAD, Professor Regente, Professor Mediador | Y25: CPA - Comissão Própria de Avaliação | Z25: UA com Base Regulatória | AA25: Participar da Comissão Própria de Avaliação - CPA - de acordo com a Lei 10.861/2004 (SINAES). | AB25: Horas não letivas | AC25: Considera-se que CPA organiza reuniões de trabalho um vez ao mês com duração de uma ou duas horas no máximo | AD25: CPA | AE25: 0 | AF25: 0.25 | AG25: =AF25+0.25 -> 0.5 | AH25: 0.75 | AI25: 1
A26: CAROLINE WOLF TRENTINI SCHIPFER | B26: 012009006209 | C26: 12 | D26: =IF(I26="PROFESSOR REGENTE",IF(C26=40,C26*0.5,IF(C26>11,C26*0.75,C26)),IF(I26="PROFESSOR DE ENSINO SUPERIOR EAD",IF(C26=40,4,2),0)) -> 9 | E26: =IF(OR(I26="PROFESSOR REGENTE",I26="PROFESSOR DE ENSINO SUPERIOR PRESENCIAL"),C26-D26,IF(C26=40,12,6)) -> 3 | F26: JULIANA MORAES DA SILVA | G26: 05209839982 | H26: ADMISSÃO PROX.MÊS | I26: PROFESSOR REGENTE | U26: 23 | V26: Planejamento | W26: Unidade Acadêmica Com Base Regulatória | X26: Coordenador de Curso, Professor EAD, Professor Regente, Professor Mediador | Y26: NDE - Núcleo Docente Estruturante | Z26: UA com Base Regulatória | AA26: Compor o Núcleo Docente Estruturante (NDE) dos cursos de graduação. Estas atividades devem ser exercidas apenas por Professores TI ou TP. Atribuição deve ser encaminhada via ofício e aprovação da Pro-Reitoria da BU. | AB26: Horas não letivas | AC26: Considera-se um encontro mensal de uma hora ou duas no máximo para o NDE. Participar do NDE não consiste apenas em participar das reuniões. Há aprovações de materiais, ementas, entre outros. | AD26: NDE | AE26: 0 | AF26: 0.25 | AG26: =AF26+0.25 -> 0.5
A27: CLAUDETE CRISTINA IWATA | B27: 012009003393 | C27: 40 | D27: =IF(I27="PROFESSOR REGENTE",IF(C27=40,C27*0.5,IF(C27>11,C27*0.75,C27)),IF(I27="PROFESSOR DE ENSINO SUPERIOR EAD",IF(C27=40,4,2),0)) -> 4 | E27: =IF(OR(I27="PROFESSOR REGENTE",I27="PROFESSOR DE ENSINO SUPERIOR PRESENCIAL"),C27-D27,IF(C27=40,12,6)) -> 12 | F27: JULIANA MORAES DA SILVA | G27: 60216115949 | H27: ATIVO | I27: PROFESSOR DE ENSINO SUPERIOR EAD | U27: 24 | V27: Planejamento | W27: Unidade Acadêmica Com Base Regulatória | X27: Coordenador de Curso, Professor EAD, Professor Regente, Professor Mediador | Y27: Participação em Núcleo | Z27: UA com Base Regulatória | AA27: Atuar como membro de núcleos institucionais, contribuindo com análises, pareceres e propostas voltadas ao desenvolvimento pedagógico e à avaliação institucional, conforme as diretrizes da IES e legislação vigente. | AB27: Horas não letivas | AC27: Avaliar a periodicidade dessas atividades | AD27: Participação_Núcleo | AE27: 0 | AF27: 0.25 | AG27: =AF27+0.25 -> 0.5 | AH27: 0.75 | AI27: 1
A28: CLAUDIA CRISTINA BATISTELA FRANCISCO | B28: 012009003473 | C28: 40 | D28: =IF(I28="PROFESSOR REGENTE",IF(C28=40,C28*0.5,IF(C28>11,C28*0.75,C28)),IF(I28="PROFESSOR DE ENSINO SUPERIOR EAD",IF(C28=40,4,2),0)) -> 4 | E28: =IF(OR(I28="PROFESSOR REGENTE",I28="PROFESSOR DE ENSINO SUPERIOR PRESENCIAL"),C28-D28,IF(C28=40,12,6)) -> 12 | F28: JULIANA MORAES DA SILVA | G28: 03283083908 | H28: ATIVO | I28: PROFESSOR DE ENSINO SUPERIOR EAD | U28: 25 | V28: Ensino | W28: Orientação | X28: Professor EAD, Professor Regente | Y28: Disciplina EAD - Curso Presencial (Disciplinas On-line e Disciplinas Digitais) | Z28: Orient. Ensino - Demais | AA28: Cadastrar banco de questões. Realizar orientações aos estudantes, atendimento de protocolo e revisão de avaliação. | AB28: Horas não letivas | AC28: Deve ser feito registro por disciplina | AD28: Disciplinas_Digitais | AE28: 0 | AF28: 1 | AG28: =AF28+0.25 -> 1.25 | AH28: 1.5 | AI28: 1.75 | AJ28: 2
A29: CLEBER MENA LEAO JUNIOR | B29: 012009006141 | C29: 20 | D29: =IF(I29="PROFESSOR REGENTE",IF(C29=40,C29*0.5,IF(C29>11,C29*0.75,C29)),IF(I29="PROFESSOR DE ENSINO SUPERIOR EAD",IF(C29=40,4,2),0)) -> 2 | E29: =IF(OR(I29="PROFESSOR REGENTE",I29="PROFESSOR DE ENSINO SUPERIOR PRESENCIAL"),C29-D29,IF(C29=40,12,6)) -> 6 | F29: JULIANA MORAES DA SILVA | G29: 00517327007 | H29: ATIVO | I29: PROFESSOR DE ENSINO SUPERIOR EAD
A30: CRISTINA CEREZUELA | B30: 012009006182 | C30: 12 | D30: =IF(I30="PROFESSOR REGENTE",IF(C30=40,C30*0.5,IF(C30>11,C30*0.75,C30)),IF(I30="PROFESSOR DE ENSINO SUPERIOR EAD",IF(C30=40,4,2),0)) -> 9 | E30: =IF(OR(I30="PROFESSOR REGENTE",I30="PROFESSOR DE ENSINO SUPERIOR PRESENCIAL"),C30-D30,IF(C30=40,12,6)) -> 3 | F30: JULIANA MORAES DA SILVA | G30: 88380270991 | H30: ADMISSÃO PROX.MÊS | I30: PROFESSOR REGENTE
A31: CRISTINA KOZAN DE BRITO | B31: 012009006183 | C31: 12 | D31: =IF(I31="PROFESSOR REGENTE",IF(C31=40,C31*0.5,IF(C31>11,C31*0.75,C31)),IF(I31="PROFESSOR DE ENSINO SUPERIOR EAD",IF(C31=40,4,2),0)) -> 9 | E31: =IF(OR(I31="PROFESSOR REGENTE",I31="PROFESSOR DE ENSINO SUPERIOR PRESENCIAL"),C31-D31,IF(C31=40,12,6)) -> 3 | F31: JULIANA MORAES DA SILVA | G31: 04243159980 | H31: ADMISSÃO PROX.MÊS | I31: PROFESSOR REGENTE
A32: CYNTIA DANIELLE PINTO GOMES | B32: 012009006090 | C32: 20 | D32: =IF(I32="PROFESSOR REGENTE",IF(C32=40,C32*0.5,IF(C32>11,C32*0.75,C32)),IF(I32="PROFESSOR DE ENSINO SUPERIOR EAD",IF(C32=40,4,2),0)) -> 2 | E32: =IF(OR(I32="PROFESSOR REGENTE",I32="PROFESSOR DE ENSINO SUPERIOR PRESENCIAL"),C32-D32,IF(C32=40,12,6)) -> 6 | F32: JULIANA MORAES DA SILVA | G32: 03316790942 | H32: ATIVO | I32: PROFESSOR DE ENSINO SUPERIOR EAD
A33: DANIELA CARLA MONTEIRO | B33: 012009003455 | C33: 40 | D33: =IF(I33="PROFESSOR REGENTE",IF(C33=40,C33*0.5,IF(C33>11,C33*0.75,C33)),IF(I33="PROFESSOR DE ENSINO SUPERIOR EAD",IF(C33=40,4,2),0)) -> 4 | E33: =IF(OR(I33="PROFESSOR REGENTE",I33="PROFESSOR DE ENSINO SUPERIOR PRESENCIAL"),C33-D33,IF(C33=40,12,6)) -> 12 | F33: JULIANA MORAES DA SILVA | G33: 01922159905 | H33: ATIVO | I33: PROFESSOR DE ENSINO SUPERIOR EAD
A34: DANIELA FAGUNDES CARNELOS NUNES | B34: 012009006206 | C34: 12 | D34: =IF(I34="PROFESSOR REGENTE",IF(C34=40,C34*0.5,IF(C34>11,C34*0.75,C34)),IF(I34="PROFESSOR DE ENSINO SUPERIOR EAD",IF(C34=40,4,2),0)) -> 9 | E34: =IF(OR(I34="PROFESSOR REGENTE",I34="PROFESSOR DE ENSINO SUPERIOR PRESENCIAL"),C34-D34,IF(C34=40,12,6)) -> 3 | F34: JULIANA MORAES DA SILVA | G34: 07641785980 | H34: ADMISSÃO PROX.MÊS | I34: PROFESSOR REGENTE
A35: DANIELA SIKORSKI | B35: 012009003544 | C35: 20 | D35: =IF(I35="PROFESSOR REGENTE",IF(C35=40,C35*0.5,IF(C35>11,C35*0.75,C35)),IF(I35="PROFESSOR DE ENSINO SUPERIOR EAD",IF(C35=40,4,2),0)) -> 2 | E35: =IF(OR(I35="PROFESSOR REGENTE",I35="PROFESSOR DE ENSINO SUPERIOR PRESENCIAL"),C35-D35,IF(C35=40,12,6)) -> 6 | F35: JULIANA MORAES DA SILVA | G35: 02913298966 | H35: ATIVO | I35: PROFESSOR DE ENSINO SUPERIOR EAD
A36: DIOGO BOCHNIA ZULIANI | B36: 012009003457 | C36: 20 | D36: =IF(I36="PROFESSOR REGENTE",IF(C36=40,C36*0.5,IF(C36>11,C36*0.75,C36)),IF(I36="PROFESSOR DE ENSINO SUPERIOR EAD",IF(C36=40,4,2),0)) -> 2 | E36: =IF(OR(I36="PROFESSOR REGENTE",I36="PROFESSOR DE ENSINO SUPERIOR PRESENCIAL"),C36-D36,IF(C36=40,12,6)) -> 6 | F36: JULIANA MORAES DA SILVA | G36: 03872419900 | H36: ATIVO | I36: PROFESSOR DE ENSINO SUPERIOR EAD
A37: EDMILSON DE LIMA LESSA | B37: 012009005549 | C37: 20 | D37: =IF(I37="PROFESSOR REGENTE",IF(C37=40,C37*0.5,IF(C37>11,C37*0.75,C37)),IF(I37="PROFESSOR DE ENSINO SUPERIOR EAD",IF(C37=40,4,2),0)) -> 2 | E37: =IF(OR(I37="PROFESSOR REGENTE",I37="PROFESSOR DE ENSINO SUPERIOR PRESENCIAL"),C37-D37,IF(C37=40,12,6)) -> 6 | F37: GISLAINE CARDOSO DE SOUZA FIAES | G37: 08384214743 | H37: ATIVO | I37: PROFESSOR DE ENSINO SUPERIOR EAD
A38: EDSON RIBEIRO DE BRITTO DE ALMEIDA JUNIOR | B38: 012009005037 | C38: 40 | D38: =IF(I38="PROFESSOR REGENTE",IF(C38=40,C38*0.5,IF(C38>11,C38*0.75,C38)),IF(I38="PROFESSOR DE ENSINO SUPERIOR EAD",IF(C38=40,4,2),0)) -> 4 | E38: =IF(OR(I38="PROFESSOR REGENTE",I38="PROFESSOR DE ENSINO SUPERIOR PRESENCIAL"),C38-D38,IF(C38=40,12,6)) -> 12 | F38: JULIANA MORAES DA SILVA | G38: 09307081999 | H38: ATIVO | I38: PROFESSOR DE ENSINO SUPERIOR EAD
A39: EDUARDO SALES DE LIMA | B39: 012009003704 | C39: 20 | D39: =IF(I39="PROFESSOR REGENTE",IF(C39=40,C39*0.5,IF(C39>11,C39*0.75,C39)),IF(I39="PROFESSOR DE ENSINO SUPERIOR EAD",IF(C39=40,4,2),0)) -> 2 | E39: =IF(OR(I39="PROFESSOR REGENTE",I39="PROFESSOR DE ENSINO SUPERIOR PRESENCIAL"),C39-D39,IF(C39=40,12,6)) -> 6 | F39: JULIANA MORAES DA SILVA | G39: 26631459800 | H39: ATIVO | I39: PROFESSOR DE ENSINO SUPERIOR EAD
A40: ELIEL NERIS JOAQUIM | B40: 012009006198 | C40: 12 | D40: =IF(I40="PROFESSOR REGENTE",IF(C40=40,C40*0.5,IF(C40>11,C40*0.75,C40)),IF(I40="PROFESSOR DE ENSINO SUPERIOR EAD",IF(C40=40,4,2),0)) -> 9 | E40: =IF(OR(I40="PROFESSOR REGENTE",I40="PROFESSOR DE ENSINO SUPERIOR PRESENCIAL"),C40-D40,IF(C40=40,12,6)) -> 3 | F40: JULIANA MORAES DA SILVA | G40: 04759793976 | H40: ADMISSÃO PROX.MÊS | I40: PROFESSOR REGENTE
... A135: LUCAS MEN BENATTI | B135: 012009006258 | C135: 12 | D135: =IF(I135="PROFESSOR REGENTE",IF(C135=40,C135*0.5,IF(C135>11,C135*0.75,C135)),IF(I135="PROFESSOR DE ENSINO SUPERIOR EAD",IF(C135=40,4,2),0)) -> 9 | E135: =IF(OR(I135="PROFESSOR REGENTE",I135="PROFESSOR DE ENSINO SUPERIOR PRESENCIAL"),C135-D135,IF(C135=40,12,6)) -> 3 | F135: JULIANA MORAES DA SILVA | G135: 09773753905 | H135: ATIVO | I135: PROFESSOR REGENTE
A136: GUILHERME HERREIRA ALVES | B136: 012009006260 | C136: 12 | D136: =IF(I136="PROFESSOR REGENTE",IF(C136=40,C136*0.5,IF(C136>11,C136*0.75,C136)),IF(I136="PROFESSOR DE ENSINO SUPERIOR EAD",IF(C136=40,4,2),0)) -> 9 | E136: =IF(OR(I136="PROFESSOR REGENTE",I136="PROFESSOR DE ENSINO SUPERIOR PRESENCIAL"),C136-D136,IF(C136=40,12,6)) -> 3 | F136: JULIANA MORAES DA SILVA | G136: 42451307846 | H136: ATIVO | I136: PROFESSOR REGENTE
A137: NATHALIA MARIA VALERIO | B137: 012009006244 | C137: 12 | D137: =IF(I137="PROFESSOR REGENTE",IF(C137=40,C137*0.5,IF(C137>11,C137*0.75,C137)),IF(I137="PROFESSOR DE ENSINO SUPERIOR EAD",IF(C137=40,4,2),0)) -> 9 | E137: =IF(OR(I137="PROFESSOR REGENTE",I137="PROFESSOR DE ENSINO SUPERIOR PRESENCIAL"),C137-D137,IF(C137=40,12,6)) -> 3 | F137: JULIANA MORAES DA SILVA | G137: 10252115961 | H137: ATIVO | I137: PROFESSOR REGENTE
A138: JOANA BALTER MARTINS DA SILVA | B138: 012009006246 | C138: 12 | D138: =IF(I138="PROFESSOR REGENTE",IF(C138=40,C138*0.5,IF(C138>11,C138*0.75,C138)),IF(I138="PROFESSOR DE ENSINO SUPERIOR EAD",IF(C138=40,4,2),0)) -> 9 | E138: =IF(OR(I138="PROFESSOR REGENTE",I138="PROFESSOR DE ENSINO SUPERIOR PRESENCIAL"),C138-D138,IF(C138=40,12,6)) -> 3 | F138: JULIANA MORAES DA SILVA | G138: 07939731718 | H138: ATIVO | I138: PROFESSOR REGENTE
A139: WELLEM APARECIDA DE FREITAS SEMCZUK | B139: 012009006250 | C139: 12 | D139: =IF(I139="PROFESSOR REGENTE",IF(C139=40,C139*0.5,IF(C139>11,C139*0.75,C139)),IF(I139="PROFESSOR DE ENSINO SUPERIOR EAD",IF(C139=40,4,2),0)) -> 9 | E139: =IF(OR(I139="PROFESSOR REGENTE",I139="PROFESSOR DE ENSINO SUPERIOR PRESENCIAL"),C139-D139,IF(C139=40,12,6)) -> 3 | F139: JULIANA MORAES DA SILVA | G139: 05805624923 | H139: ATIVO | I139: PROFESSOR REGENTE
A140: INDIANARA PAULA PINHEIRO FERMINO | B140: 012009006257 | C140: 12 | D140: =IF(I140="PROFESSOR REGENTE",IF(C140=40,C140*0.5,IF(C140>11,C140*0.75,C140)),IF(I140="PROFESSOR DE ENSINO SUPERIOR EAD",IF(C140=40,4,2),0)) -> 9 | E140: =IF(OR(I140="PROFESSOR REGENTE",I140="PROFESSOR DE ENSINO SUPERIOR PRESENCIAL"),C140-D140,IF(C140=40,12,6)) -> 3 | F140: JULIANA MORAES DA SILVA | G140: 05592355939 | H140: ATIVO | I140: PROFESSOR REGENTE
A141: JEFERSON CAMARGO FUKUSHIMA | B141: 012009006263 | C141: 12 | D141: =IF(I141="PROFESSOR REGENTE",IF(C141=40,C141*0.5,IF(C141>11,C141*0.75,C141)),IF(I141="PROFESSOR DE ENSINO SUPERIOR EAD",IF(C141=40,4,2),0)) -> 9 | E141: =IF(OR(I141="PROFESSOR REGENTE",I141="PROFESSOR DE ENSINO SUPERIOR PRESENCIAL"),C141-D141,IF(C141=40,12,6)) -> 3 | F141: JULIANA MORAES DA SILVA | G141: 31705859836 | H141: ATIVO | I141: PROFESSOR REGENTE
A142: EMILY FERNANDES | B142: 012009006261 | C142: 12 | D142: =IF(I142="PROFESSOR REGENTE",IF(C142=40,C142*0.5,IF(C142>11,C142*0.75,C142)),IF(I142="PROFESSOR DE ENSINO SUPERIOR EAD",IF(C142=40,4,2),0)) -> 9 | E142: =IF(OR(I142="PROFESSOR REGENTE",I142="PROFESSOR DE ENSINO SUPERIOR PRESENCIAL"),C142-D142,IF(C142=40,12,6)) -> 3 | F142: JULIANA MORAES DA SILVA | G142: 01754828450 | H142: ATIVO | I142: PROFESSOR REGENTE
A143: IGOR SILVA DE SA | B143: 012009006248 | C143: 12 | D143: =IF(I143="PROFESSOR REGENTE",IF(C143=40,C143*0.5,IF(C143>11,C143*0.75,C143)),IF(I143="PROFESSOR DE ENSINO SUPERIOR EAD",IF(C143=40,4,2),0)) -> 9 | E143: =IF(OR(I143="PROFESSOR REGENTE",I143="PROFESSOR DE ENSINO SUPERIOR PRESENCIAL"),C143-D143,IF(C143=40,12,6)) -> 3 | F143: JULIANA MORAES DA SILVA | G143: 04821566192 | H143: ATIVO | I143: PROFESSOR REGENTE
A144: ROBERTA DA FONSECA COUTINHO PONTES | B144: 012009006249 | C144: 12 | D144: =IF(I144="PROFESSOR REGENTE",IF(C144=40,C144*0.5,IF(C144>11,C144*0.75,C144)),IF(I144="PROFESSOR DE ENSINO SUPERIOR EAD",IF(C144=40,4,2),0)) -> 9 | E144: =IF(OR(I144="PROFESSOR REGENTE",I144="PROFESSOR DE ENSINO SUPERIOR PRESENCIAL"),C144-D144,IF(C144=40,12,6)) -> 3 | F144: JULIANA MORAES DA SILVA | G144: 16043449706 | H144: ATIVO | I144: PROFESSOR REGENTE
A145: LUIS FERNANDO MOREIRA DA SILVA | B145: 012009006245 | C145: 12 | D145: =IF(I145="PROFESSOR REGENTE",IF(C145=40,C145*0.5,IF(C145>11,C145*0.75,C145)),IF(I145="PROFESSOR DE ENSINO SUPERIOR EAD",IF(C145=40,4,2),0)) -> 9 | E145: =IF(OR(I145="PROFESSOR REGENTE",I145="PROFESSOR DE ENSINO SUPERIOR PRESENCIAL"),C145-D145,IF(C145=40,12,6)) -> 3 | F145: JULIANA MORAES DA SILVA | G145: 35493802830 | H145: ATIVO | I145: PROFESSOR REGENTE
A146: TATIANE CRISTINA ALBUQUERQUE ALVES | B146: 012009006247 | C146: 12 | D146: =IF(I146="PROFESSOR REGENTE",IF(C146=40,C146*0.5,IF(C146>11,C146*0.75,C146)),IF(I146="PROFESSOR DE ENSINO SUPERIOR EAD",IF(C146=40,4,2),0)) -> 9 | E146: =IF(OR(I146="PROFESSOR REGENTE",I146="PROFESSOR DE ENSINO SUPERIOR PRESENCIAL"),C146-D146,IF(C146=40,12,6)) -> 3 | F146: JULIANA MORAES DA SILVA | G146: 04688559984 | H146: ATIVO | I146: PROFESSOR REGENTE
A147: ARTHUR DA SILVA GOMES | B147: 012009006305 | C147: 12 | D147: =IF(I147="PROFESSOR REGENTE",IF(C147=40,C147*0.5,IF(C147>11,C147*0.75,C147)),IF(I147="PROFESSOR DE ENSINO SUPERIOR EAD",IF(C147=40,4,2),0)) -> 9 | E147: =IF(OR(I147="PROFESSOR REGENTE",I147="PROFESSOR DE ENSINO SUPERIOR PRESENCIAL"),C147-D147,IF(C147=40,12,6)) -> 3 | F147: JULIANA MORAES DA SILVA | G147: 08917110665 | H147: ATIVO | I147: PROFESSOR REGENTE
A148: BRUNA EDUARDA KUBLISKI FOLMER ROMAN | B148: 012009006311 | C148: 12 | D148: =IF(I148="PROFESSOR REGENTE",IF(C148=40,C148*0.5,IF(C148>11,C148*0.75,C148)),IF(I148="PROFESSOR DE ENSINO SUPERIOR EAD",IF(C148=40,4,2),0)) -> 9 | E148: =IF(OR(I148="PROFESSOR REGENTE",I148="PROFESSOR DE ENSINO SUPERIOR PRESENCIAL"),C148-D148,IF(C148=40,12,6)) -> 3 | F148: JULIANA MORAES DA SILVA | G148: 07445248900 | H148: ATIVO | I148: PROFESSOR REGENTE
A149: BRUNO DA SILVA BORGES | B149: 012009006309 | C149: 12 | D149: =IF(I149="PROFESSOR REGENTE",IF(C149=40,C149*0.5,IF(C149>11,C149*0.75,C149)),IF(I149="PROFESSOR DE ENSINO SUPERIOR EAD",IF(C149=40,4,2),0)) -> 9 | E149: =IF(OR(I149="PROFESSOR REGENTE",I149="PROFESSOR DE ENSINO SUPERIOR PRESENCIAL"),C149-D149,IF(C149=40,12,6)) -> 3 | F149: JULIANA MORAES DA SILVA | G149: 03203790009 | H149: ATIVO | I149: PROFESSOR REGENTE
A150: ELISANGELA GISELE DO CARMO | B150: 012009006304 | C150: 12 | D150: =IF(I150="PROFESSOR REGENTE",IF(C150=40,C150*0.5,IF(C150>11,C150*0.75,C150)),IF(I150="PROFESSOR DE ENSINO SUPERIOR EAD",IF(C150=40,4,2),0)) -> 9 | E150: =IF(OR(I150="PROFESSOR REGENTE",I150="PROFESSOR DE ENSINO SUPERIOR PRESENCIAL"),C150-D150,IF(C150=40,12,6)) -> 3 | F150: JULIANA MORAES DA SILVA | G150: 09557701730 | H150: ATIVO | I150: PROFESSOR REGENTE
A151: FABIO LUIS HEGETO | B151: 012009006316 | C151: 12 | D151: =IF(I151="PROFESSOR REGENTE",IF(C151=40,C151*0.5,IF(C151>11,C151*0.75,C151)),IF(I151="PROFESSOR DE ENSINO SUPERIOR EAD",IF(C151=40,4,2),0)) -> 9 | E151: =IF(OR(I151="PROFESSOR REGENTE",I151="PROFESSOR DE ENSINO SUPERIOR PRESENCIAL"),C151-D151,IF(C151=40,12,6)) -> 3 | F151: JULIANA MORAES DA SILVA | G151: 03764711906 | H151: ATIVO | I151: PROFESSOR REGENTE
A152: GUARACY CARLOS DA SILVEIRA | B152: 012009006310 | C152: 12 | D152: =IF(I152="PROFESSOR REGENTE",IF(C152=40,C152*0.5,IF(C152>11,C152*0.75,C152)),IF(I152="PROFESSOR DE ENSINO SUPERIOR EAD",IF(C152=40,4,2),0)) -> 9 | E152: =IF(OR(I152="PROFESSOR REGENTE",I152="PROFESSOR DE ENSINO SUPERIOR PRESENCIAL"),C152-D152,IF(C152=40,12,6)) -> 3 | F152: JULIANA MORAES DA SILVA | G152: 26858645802 | H152: ATIVO | I152: PROFESSOR REGENTE
A153: ISADORA GABRIELLA SILVA PALMIERI | B153: 012009006312 | C153: 12 | D153: =IF(I153="PROFESSOR REGENTE",IF(C153=40,C153*0.5,IF(C153>11,C153*0.75,C153)),IF(I153="PROFESSOR DE ENSINO SUPERIOR EAD",IF(C153=40,4,2),0)) -> 9 | E153: =IF(OR(I153="PROFESSOR REGENTE",I153="PROFESSOR DE ENSINO SUPERIOR PRESENCIAL"),C153-D153,IF(C153=40,12,6)) -> 3 | F153: JULIANA MORAES DA SILVA | G153: 08580763908 | H153: ATIVO | I153: PROFESSOR REGENTE
A154: JOSE DE SOUSA MAGALHAES | B154: 012009006308 | C154: 12 | D154: =IF(I154="PROFESSOR REGENTE",IF(C154=40,C154*0.5,IF(C154>11,C154*0.75,C154)),IF(I154="PROFESSOR DE ENSINO SUPERIOR EAD",IF(C154=40,4,2),0)) -> 9 | E154: =IF(OR(I154="PROFESSOR REGENTE",I154="PROFESSOR DE ENSINO SUPERIOR PRESENCIAL"),C154-D154,IF(C154=40,12,6)) -> 3 | F154: JULIANA MORAES DA SILVA | G154: 05133032358 | H154: ATIVO | I154: PROFESSOR REGENTE
A155: LARISSA DE MENEZES ALVANHAN | B155: 012009006314 | C155: 12 | D155: =IF(I155="PROFESSOR REGENTE",IF(C155=40,C155*0.5,IF(C155>11,C155*0.75,C155)),IF(I155="PROFESSOR DE ENSINO SUPERIOR EAD",IF(C155=40,4,2),0)) -> 9 | E155: =IF(OR(I155="PROFESSOR REGENTE",I155="PROFESSOR DE ENSINO SUPERIOR PRESENCIAL"),C155-D155,IF(C155=40,12,6)) -> 3 | F155: JULIANA MORAES DA SILVA | G155: 05201189954 | H155: ATIVO | I155: PROFESSOR REGENTE
A156: MELISSA CAROLINA DE MOURA | B156: 012009006307 | C156: 12 | D156: =IF(I156="PROFESSOR REGENTE",IF(C156=40,C156*0.5,IF(C156>11,C156*0.75,C156)),IF(I156="PROFESSOR DE ENSINO SUPERIOR EAD",IF(C156=40,4,2),0)) -> 9 | E156: =IF(OR(I156="PROFESSOR REGENTE",I156="PROFESSOR DE ENSINO SUPERIOR PRESENCIAL"),C156-D156,IF(C156=40,12,6)) -> 3 | F156: JULIANA MORAES DA SILVA | G156: 27068944825 | H156: ATIVO | I156: PROFESSOR REGENTE
A157: TALITA MEIRELES FLORES | B157: 012009006315 | C157: 12 | D157: =IF(I157="PROFESSOR REGENTE",IF(C157=40,C157*0.5,IF(C157>11,C157*0.75,C157)),IF(I157="PROFESSOR DE ENSINO SUPERIOR EAD",IF(C157=40,4,2),0)) -> 9 | E157: =IF(OR(I157="PROFESSOR REGENTE",I157="PROFESSOR DE ENSINO SUPERIOR PRESENCIAL"),C157-D157,IF(C157=40,12,6)) -> 3 | F157: JULIANA MORAES DA SILVA | G157: 01716039150 | H157: ATIVO | I157: PROFESSOR REGENTE
... A232: VANDER LUIZ DA SILVA | B232: 012009007778 | C232: 12 | D232: =IF(I232="PROFESSOR REGENTE",IF(C232=40,C232*0.5,IF(C232>11,C232*0.75,C232)),IF(I232="PROFESSOR DE ENSINO SUPERIOR EAD",IF(C232=40,4,2),0)) -> 9 | E232: =IF(OR(I232="PROFESSOR REGENTE",I232="PROFESSOR DE ENSINO SUPERIOR PRESENCIAL"),C232-D232,IF(C232=40,12,6)) -> 3 | F232: CRISLAINE RODRIGUES GALAN | G232: 08428218994 | H232: ATIVO | I232: PROFESSOR REGENTE
A233: PROFESSOR RPA | B233: 000000000000 | C233: 0 | D233: 0 | E233: 0 | G233: 00000000000 | I233: RPA

Sheet PREENCHIMENTO|LETIVAS
A1: Devem ser inseridas: - Disciplinas com aulas transmitidas ao vivo; - Disciplinas com aulas que tenham sido gravadas especificamente para serem usadas ao vivo neste módulo; Não devem ser inseridas: - Disciplinas com aulas reaproveitadas de anos anteriores; - Disciplinas sem aulas ao vivo;
A8: LISTAS SUSPENSAS (Apenas Seleção) | J8: DIGITÁVEIS
A9: PROFESSOR(A) | B9: CHAPA | C9: CH SEMANAL | D9: CH LETIVA | E9: CARGO | F9: MÓDULO | G9: ORDEM | H9: DIA DA TRANSMISSÃO | I9: HORÁRIO | J9: DISCIPLINA (NOME) | K9: OBSERVAÇÃO | L9: R$ (RPA)
A10: AMANDA FERREIRA GUIMARAES | B10: =IF(_xlfn.XLOOKUP(A10,PARAMETROS!A:A,PARAMETROS!B:B)=0,"",_xlfn.XLOOKUP(A10,PARAMETROS!A:A,PARAMETROS!B:B)) -> 012009006176 | C10: =IF(_xlfn.XLOOKUP(A10,PARAMETROS!A:A,PARAMETROS!C:C)=0,"",_xlfn.XLOOKUP(A10,PARAMETROS!A:A,PARAMETROS!C:C)) -> 12 | D10: =IF(_xlfn.XLOOKUP(A10,PARAMETROS!A:A,PARAMETROS!D:D)=0,"",_xlfn.XLOOKUP(A10,PARAMETROS!A:A,PARAMETROS!D:D)) -> 9 | E10: =IF(_xlfn.XLOOKUP('PREENCHIMENTO|LETIVAS'!A10,PARAMETROS!A:A,PARAMETROS!I:I)=0,"",_xlfn.XLOOKUP('PREENCHIMENTO|LETIVAS'!A10,PARAMETROS!A:A,PARAMETROS!I:I)) -> PROFESSOR REGENTE | F10: 51|2026 | G10: 1 | H10: 4 - Quarta | I10: 20:40 às 22:10 | J10: GESTÃO DE PESSOAS E DESENVOLVIMENTO DE EQUIPES | W10: =IF(I10<>"",2,0) -> 2
A11: IZABELLA DURANTE TEMPORINI FURTADO | B11: =IF(_xlfn.XLOOKUP(A11,PARAMETROS!A:A,PARAMETROS!B:B)=0,"",_xlfn.XLOOKUP(A11,PARAMETROS!A:A,PARAMETROS!B:B)) -> 012009006192 | C11: =IF(_xlfn.XLOOKUP(A11,PARAMETROS!A:A,PARAMETROS!C:C)=0,"",_xlfn.XLOOKUP(A11,PARAMETROS!A:A,PARAMETROS!C:C)) -> 12 | D11: =IF(_xlfn.XLOOKUP(A11,PARAMETROS!A:A,PARAMETROS!D:D)=0,"",_xlfn.XLOOKUP(A11,PARAMETROS!A:A,PARAMETROS!D:D)) -> 9 | E11: =IF(_xlfn.XLOOKUP('PREENCHIMENTO|LETIVAS'!A11,PARAMETROS!A:A,PARAMETROS!I:I)=0,"",_xlfn.XLOOKUP('PREENCHIMENTO|LETIVAS'!A11,PARAMETROS!A:A,PARAMETROS!I:I)) -> PROFESSOR REGENTE | F11: 51|2026 | G11: 2 | H11: 4 - Quarta | I11: 19:00 às 20:30 | J11: ESTATÍSTICA | W11: =IF(I11<>"",2,0) -> 2
A12: IZABELLA DURANTE TEMPORINI FURTADO | B12: =IF(_xlfn.XLOOKUP(A12,PARAMETROS!A:A,PARAMETROS!B:B)=0,"",_xlfn.XLOOKUP(A12,PARAMETROS!A:A,PARAMETROS!B:B)) -> 012009006192 | C12: =IF(_xlfn.XLOOKUP(A12,PARAMETROS!A:A,PARAMETROS!C:C)=0,"",_xlfn.XLOOKUP(A12,PARAMETROS!A:A,PARAMETROS!C:C)) -> 12 | D12: =IF(_xlfn.XLOOKUP(A12,PARAMETROS!A:A,PARAMETROS!D:D)=0,"",_xlfn.XLOOKUP(A12,PARAMETROS!A:A,PARAMETROS!D:D)) -> 9 | E12: =IF(_xlfn.XLOOKUP('PREENCHIMENTO|LETIVAS'!A12,PARAMETROS!A:A,PARAMETROS!I:I)=0,"",_xlfn.XLOOKUP('PREENCHIMENTO|LETIVAS'!A12,PARAMETROS!A:A,PARAMETROS!I:I)) -> PROFESSOR REGENTE | F12: 51|2026 | G12: 1 | H12: 5 - Quinta | I12: 19:00 às 20:30 | J12: GEOMETRIA ANALÍTICA E ÁLGEBRA LINEAR | W12: =IF(I12<>"",2,0) -> 2
A13: IZABELLA DURANTE TEMPORINI FURTADO | B13: =IF(_xlfn.XLOOKUP(A13,PARAMETROS!A:A,PARAMETROS!B:B)=0,"",_xlfn.XLOOKUP(A13,PARAMETROS!A:A,PARAMETROS!B:B)) -> 012009006192 | C13: =IF(_xlfn.XLOOKUP(A13,PARAMETROS!A:A,PARAMETROS!C:C)=0,"",_xlfn.XLOOKUP(A13,PARAMETROS!A:A,PARAMETROS!C:C)) -> 12 | D13: =IF(_xlfn.XLOOKUP(A13,PARAMETROS!A:A,PARAMETROS!D:D)=0,"",_xlfn.XLOOKUP(A13,PARAMETROS!A:A,PARAMETROS!D:D)) -> 9 | E13: =IF(_xlfn.XLOOKUP('PREENCHIMENTO|LETIVAS'!A13,PARAMETROS!A:A,PARAMETROS!I:I)=0,"",_xlfn.XLOOKUP('PREENCHIMENTO|LETIVAS'!A13,PARAMETROS!A:A,PARAMETROS!I:I)) -> PROFESSOR REGENTE | F13: 51|2026 | G13: 2 | H13: 4 - Quarta | I13: 20:40 às 22:10 | J13: PROBABILIDADE E ESTATÍSTICA PARA ANÁLISE DE DADOS | W13: =IF(I13<>"",2,0) -> 2
A14: IZABELLA DURANTE TEMPORINI FURTADO | B14: =IF(_xlfn.XLOOKUP(A14,PARAMETROS!A:A,PARAMETROS!B:B)=0,"",_xlfn.XLOOKUP(A14,PARAMETROS!A:A,PARAMETROS!B:B)) -> 012009006192 | C14: =IF(_xlfn.XLOOKUP(A14,PARAMETROS!A:A,PARAMETROS!C:C)=0,"",_xlfn.XLOOKUP(A14,PARAMETROS!A:A,PARAMETROS!C:C)) -> 12 | D14: =IF(_xlfn.XLOOKUP(A14,PARAMETROS!A:A,PARAMETROS!D:D)=0,"",_xlfn.XLOOKUP(A14,PARAMETROS!A:A,PARAMETROS!D:D)) -> 9 | E14: =IF(_xlfn.XLOOKUP('PREENCHIMENTO|LETIVAS'!A14,PARAMETROS!A:A,PARAMETROS!I:I)=0,"",_xlfn.XLOOKUP('PREENCHIMENTO|LETIVAS'!A14,PARAMETROS!A:A,PARAMETROS!I:I)) -> PROFESSOR REGENTE | F14: 51|2026 | G14: 2 | H14: 5 - Quinta | I14: 19:00 às 20:30 | J14: CÁLCULO APLICADO À QUÍMICA | W14: =IF(I14<>"",2,0) -> 2
A15: ADRIANO APARECIDO DE OLIVEIRA | B15: =IF(_xlfn.XLOOKUP(A15,PARAMETROS!A:A,PARAMETROS!B:B)=0,"",_xlfn.XLOOKUP(A15,PARAMETROS!A:A,PARAMETROS!B:B)) -> 012009003424 | C15: =IF(_xlfn.XLOOKUP(A15,PARAMETROS!A:A,PARAMETROS!C:C)=0,"",_xlfn.XLOOKUP(A15,PARAMETROS!A:A,PARAMETROS!C:C)) -> 40 | D15: =IF(_xlfn.XLOOKUP(A15,PARAMETROS!A:A,PARAMETROS!D:D)=0,"",_xlfn.XLOOKUP(A15,PARAMETROS!A:A,PARAMETROS!D:D)) -> 20 | E15: =IF(_xlfn.XLOOKUP('PREENCHIMENTO|LETIVAS'!A15,PARAMETROS!A:A,PARAMETROS!I:I)=0,"",_xlfn.XLOOKUP('PREENCHIMENTO|LETIVAS'!A15,PARAMETROS!A:A,PARAMETROS!I:I)) -> PROFESSOR REGENTE | F15: 51|2026 | G15: 1 | H15: 2 - Segunda | I15: 20:40 às 22:10 | J15: MENTALIDADE CRIATIVA E EMPREENDEDORA | W15: =IF(I15<>"",2,0) -> 2
A16: ADRIANO APARECIDO DE OLIVEIRA | B16: =IF(_xlfn.XLOOKUP(A16,PARAMETROS!A:A,PARAMETROS!B:B)=0,"",_xlfn.XLOOKUP(A16,PARAMETROS!A:A,PARAMETROS!B:B)) -> 012009003424 | C16: =IF(_xlfn.XLOOKUP(A16,PARAMETROS!A:A,PARAMETROS!C:C)=0,"",_xlfn.XLOOKUP(A16,PARAMETROS!A:A,PARAMETROS!C:C)) -> 40 | D16: =IF(_xlfn.XLOOKUP(A16,PARAMETROS!A:A,PARAMETROS!D:D)=0,"",_xlfn.XLOOKUP(A16,PARAMETROS!A:A,PARAMETROS!D:D)) -> 20 | E16: =IF(_xlfn.XLOOKUP('PREENCHIMENTO|LETIVAS'!A16,PARAMETROS!A:A,PARAMETROS!I:I)=0,"",_xlfn.XLOOKUP('PREENCHIMENTO|LETIVAS'!A16,PARAMETROS!A:A,PARAMETROS!I:I)) -> PROFESSOR REGENTE | F16: 51|2026 | G16: 1 | H16: 3 - Terça | I16: 20:40 às 22:10 | J16: MENTALIDADE CRIATIVA E EMPREENDEDORA | W16: =IF(I16<>"",2,0) -> 2
A17: ADRIANO APARECIDO DE OLIVEIRA | B17: =IF(_xlfn.XLOOKUP(A17,PARAMETROS!A:A,PARAMETROS!B:B)=0,"",_xlfn.XLOOKUP(A17,PARAMETROS!A:A,PARAMETROS!B:B)) -> 012009003424 | C17: =IF(_xlfn.XLOOKUP(A17,PARAMETROS!A:A,PARAMETROS!C:C)=0,"",_xlfn.XLOOKUP(A17,PARAMETROS!A:A,PARAMETROS!C:C)) -> 40 | D17: =IF(_xlfn.XLOOKUP(A17,PARAMETROS!A:A,PARAMETROS!D:D)=0,"",_xlfn.XLOOKUP(A17,PARAMETROS!A:A,PARAMETROS!D:D)) -> 20 | E17: =IF(_xlfn.XLOOKUP('PREENCHIMENTO|LETIVAS'!A17,PARAMETROS!A:A,PARAMETROS!I:I)=0,"",_xlfn.XLOOKUP('PREENCHIMENTO|LETIVAS'!A17,PARAMETROS!A:A,PARAMETROS!I:I)) -> PROFESSOR REGENTE | F17: 51|2026 | G17: 1 | H17: 4 - Quarta | I17: 20:40 às 22:10 | J17: MENTALIDADE CRIATIVA E EMPREENDEDORA | W17: =IF(I17<>"",2,0) -> 2
A18: ADRIANO APARECIDO DE OLIVEIRA | B18: =IF(_xlfn.XLOOKUP(A18,PARAMETROS!A:A,PARAMETROS!B:B)=0,"",_xlfn.XLOOKUP(A18,PARAMETROS!A:A,PARAMETROS!B:B)) -> 012009003424 | C18: =IF(_xlfn.XLOOKUP(A18,PARAMETROS!A:A,PARAMETROS!C:C)=0,"",_xlfn.XLOOKUP(A18,PARAMETROS!A:A,PARAMETROS!C:C)) -> 40 | D18: =IF(_xlfn.XLOOKUP(A18,PARAMETROS!A:A,PARAMETROS!D:D)=0,"",_xlfn.XLOOKUP(A18,PARAMETROS!A:A,PARAMETROS!D:D)) -> 20 | E18: =IF(_xlfn.XLOOKUP('PREENCHIMENTO|LETIVAS'!A18,PARAMETROS!A:A,PARAMETROS!I:I)=0,"",_xlfn.XLOOKUP('PREENCHIMENTO|LETIVAS'!A18,PARAMETROS!A:A,PARAMETROS!I:I)) -> PROFESSOR REGENTE | F18: 51|2026 | G18: 1 | H18: 5 - Quinta | I18: 20:40 às 22:10 | J18: MENTALIDADE CRIATIVA E EMPREENDEDORA | W18: =IF(I18<>"",2,0) -> 2
A19: LUIS FERNANDO MOREIRA DA SILVA | B19: =IF(_xlfn.XLOOKUP(A19,PARAMETROS!A:A,PARAMETROS!B:B)=0,"",_xlfn.XLOOKUP(A19,PARAMETROS!A:A,PARAMETROS!B:B)) -> 012009006245 | C19: =IF(_xlfn.XLOOKUP(A19,PARAMETROS!A:A,PARAMETROS!C:C)=0,"",_xlfn.XLOOKUP(A19,PARAMETROS!A:A,PARAMETROS!C:C)) -> 12 | D19: =IF(_xlfn.XLOOKUP(A19,PARAMETROS!A:A,PARAMETROS!D:D)=0,"",_xlfn.XLOOKUP(A19,PARAMETROS!A:A,PARAMETROS!D:D)) -> 9 | E19: =IF(_xlfn.XLOOKUP('PREENCHIMENTO|LETIVAS'!A19,PARAMETROS!A:A,PARAMETROS!I:I)=0,"",_xlfn.XLOOKUP('PREENCHIMENTO|LETIVAS'!A19,PARAMETROS!A:A,PARAMETROS!I:I)) -> PROFESSOR REGENTE | F19: 51|2026 | G19: ESTENDIDA | H19: 2 - Segunda | I19: 20:40 às 22:10 | J19: CONCEITOS DA ADMINISTRAÇÃO E ÉTICA EMPRESARIAL | W19: =IF(I19<>"",2,0) -> 2
A20: LUIS FERNANDO MOREIRA DA SILVA | B20: =IF(_xlfn.XLOOKUP(A20,PARAMETROS!A:A,PARAMETROS!B:B)=0,"",_xlfn.XLOOKUP(A20,PARAMETROS!A:A,PARAMETROS!B:B)) -> 012009006245 | C20: =IF(_xlfn.XLOOKUP(A20,PARAMETROS!A:A,PARAMETROS!C:C)=0,"",_xlfn.XLOOKUP(A20,PARAMETROS!A:A,PARAMETROS!C:C)) -> 12 | D20: =IF(_xlfn.XLOOKUP(A20,PARAMETROS!A:A,PARAMETROS!D:D)=0,"",_xlfn.XLOOKUP(A20,PARAMETROS!A:A,PARAMETROS!D:D)) -> 9 | E20: =IF(_xlfn.XLOOKUP('PREENCHIMENTO|LETIVAS'!A20,PARAMETROS!A:A,PARAMETROS!I:I)=0,"",_xlfn.XLOOKUP('PREENCHIMENTO|LETIVAS'!A20,PARAMETROS!A:A,PARAMETROS!I:I)) -> PROFESSOR REGENTE | F20: 51|2026 | G20: 1 | H20: 2 - Segunda | I20: 19:00 às 20:30 | J20: TEORIAS DA ADMINISTRAÇÃO | W20: =IF(I20<>"",2,0) -> 2
A21: LUIS FERNANDO MOREIRA DA SILVA | B21: =IF(_xlfn.XLOOKUP(A21,PARAMETROS!A:A,PARAMETROS!B:B)=0,"",_xlfn.XLOOKUP(A21,PARAMETROS!A:A,PARAMETROS!B:B)) -> 012009006245 | C21: =IF(_xlfn.XLOOKUP(A21,PARAMETROS!A:A,PARAMETROS!C:C)=0,"",_xlfn.XLOOKUP(A21,PARAMETROS!A:A,PARAMETROS!C:C)) -> 12 | D21: =IF(_xlfn.XLOOKUP(A21,PARAMETROS!A:A,PARAMETROS!D:D)=0,"",_xlfn.XLOOKUP(A21,PARAMETROS!A:A,PARAMETROS!D:D)) -> 9 | E21: =IF(_xlfn.XLOOKUP('PREENCHIMENTO|LETIVAS'!A21,PARAMETROS!A:A,PARAMETROS!I:I)=0,"",_xlfn.XLOOKUP('PREENCHIMENTO|LETIVAS'!A21,PARAMETROS!A:A,PARAMETROS!I:I)) -> PROFESSOR REGENTE | F21: 51|2026 | G21: 2 | H21: 3 - Terça | I21: 19:00 às 20:30 | J21: PESQUISA DE OPINIÃO PÚBLICA | W21: =IF(I21<>"",2,0) -> 2
A22: ELAINE SANTOS | B22: =IF(_xlfn.XLOOKUP(A22,PARAMETROS!A:A,PARAMETROS!B:B)=0,"",_xlfn.XLOOKUP(A22,PARAMETROS!A:A,PARAMETROS!B:B)) -> 012009006265 | C22: =IF(_xlfn.XLOOKUP(A22,PARAMETROS!A:A,PARAMETROS!C:C)=0,"",_xlfn.XLOOKUP(A22,PARAMETROS!A:A,PARAMETROS!C:C)) -> 12 | D22: =IF(_xlfn.XLOOKUP(A22,PARAMETROS!A:A,PARAMETROS!D:D)=0,"",_xlfn.XLOOKUP(A22,PARAMETROS!A:A,PARAMETROS!D:D)) -> 9 | E22: =IF(_xlfn.XLOOKUP('PREENCHIMENTO|LETIVAS'!A22,PARAMETROS!A:A,PARAMETROS!I:I)=0,"",_xlfn.XLOOKUP('PREENCHIMENTO|LETIVAS'!A22,PARAMETROS!A:A,PARAMETROS!I:I)) -> PROFESSOR REGENTE | F22: 51|2026 | G22: ESTENDIDA | H22: 2 - Segunda | I22: 20:40 às 22:10 | J22: PROGRAMAÇÃO E CÁLCULO NUMÉRICO | W22: =IF(I22<>"",2,0) -> 2
A23: ELAINE SANTOS | B23: =IF(_xlfn.XLOOKUP(A23,PARAMETROS!A:A,PARAMETROS!B:B)=0,"",_xlfn.XLOOKUP(A23,PARAMETROS!A:A,PARAMETROS!B:B)) -> 012009006265 | C23: =IF(_xlfn.XLOOKUP(A23,PARAMETROS!A:A,PARAMETROS!C:C)=0,"",_xlfn.XLOOKUP(A23,PARAMETROS!A:A,PARAMETROS!C:C)) -> 12 | D23: =IF(_xlfn.XLOOKUP(A23,PARAMETROS!A:A,PARAMETROS!D:D)=0,"",_xlfn.XLOOKUP(A23,PARAMETROS!A:A,PARAMETROS!D:D)) -> 9 | E23: =IF(_xlfn.XLOOKUP('PREENCHIMENTO|LETIVAS'!A23,PARAMETROS!A:A,PARAMETROS!I:I)=0,"",_xlfn.XLOOKUP('PREENCHIMENTO|LETIVAS'!A23,PARAMETROS!A:A,PARAMETROS!I:I)) -> PROFESSOR REGENTE | F23: 51|2026 | G23: ESTENDIDA | H23: 2 - Segunda | I23: 19:00 às 20:30 | J23: SISTEMAS DE ENERGIA SOLAR TÉRMICA E FOTOVOLTAICA | W23: =IF(I23<>"",2,0) -> 2
A24: GUSTAVO GONCALVES KREPSKI | B24: =IF(_xlfn.XLOOKUP(A24,PARAMETROS!A:A,PARAMETROS!B:B)=0,"",_xlfn.XLOOKUP(A24,PARAMETROS!A:A,PARAMETROS!B:B)) -> 012009004339 | C24: =IF(_xlfn.XLOOKUP(A24,PARAMETROS!A:A,PARAMETROS!C:C)=0,"",_xlfn.XLOOKUP(A24,PARAMETROS!A:A,PARAMETROS!C:C)) -> 40 | D24: =IF(_xlfn.XLOOKUP(A24,PARAMETROS!A:A,PARAMETROS!D:D)=0,"",_xlfn.XLOOKUP(A24,PARAMETROS!A:A,PARAMETROS!D:D)) -> 20 | E24: =IF(_xlfn.XLOOKUP('PREENCHIMENTO|LETIVAS'!A24,PARAMETROS!A:A,PARAMETROS!I:I)=0,"",_xlfn.XLOOKUP('PREENCHIMENTO|LETIVAS'!A24,PARAMETROS!A:A,PARAMETROS!I:I)) -> PROFESSOR REGENTE | F24: 51|2026 | G24: ESTENDIDA | H24: 2 - Segunda | I24: 19:00 às 20:30 | J24: ELETRÔNICA ANALÓGICA | W24: =IF(I24<>"",2,0) -> 2
A25: GUSTAVO GONCALVES KREPSKI | B25: =IF(_xlfn.XLOOKUP(A25,PARAMETROS!A:A,PARAMETROS!B:B)=0,"",_xlfn.XLOOKUP(A25,PARAMETROS!A:A,PARAMETROS!B:B)) -> 012009004339 | C25: =IF(_xlfn.XLOOKUP(A25,PARAMETROS!A:A,PARAMETROS!C:C)=0,"",_xlfn.XLOOKUP(A25,PARAMETROS!A:A,PARAMETROS!C:C)) -> 40 | D25: =IF(_xlfn.XLOOKUP(A25,PARAMETROS!A:A,PARAMETROS!D:D)=0,"",_xlfn.XLOOKUP(A25,PARAMETROS!A:A,PARAMETROS!D:D)) -> 20 | E25: =IF(_xlfn.XLOOKUP('PREENCHIMENTO|LETIVAS'!A25,PARAMETROS!A:A,PARAMETROS!I:I)=0,"",_xlfn.XLOOKUP('PREENCHIMENTO|LETIVAS'!A25,PARAMETROS!A:A,PARAMETROS!I:I)) -> PROFESSOR REGENTE | F25: 51|2026 | G25: ESTENDIDA | H25: 2 - Segunda | I25: 20:40 às 22:10 | J25: SINAIS E SISTEMAS LINEARES | W25: =IF(I25<>"",2,0) -> 2
A26: UGO ANDREATA GALIMBERTTI | B26: =IF(_xlfn.XLOOKUP(A26,PARAMETROS!A:A,PARAMETROS!B:B)=0,"",_xlfn.XLOOKUP(A26,PARAMETROS!A:A,PARAMETROS!B:B)) -> 012009006226 | C26: =IF(_xlfn.XLOOKUP(A26,PARAMETROS!A:A,PARAMETROS!C:C)=0,"",_xlfn.XLOOKUP(A26,PARAMETROS!A:A,PARAMETROS!C:C)) -> 40 | D26: =IF(_xlfn.XLOOKUP(A26,PARAMETROS!A:A,PARAMETROS!D:D)=0,"",_xlfn.XLOOKUP(A26,PARAMETROS!A:A,PARAMETROS!D:D)) -> 20 | E26: =IF(_xlfn.XLOOKUP('PREENCHIMENTO|LETIVAS'!A26,PARAMETROS!A:A,PARAMETROS!I:I)=0,"",_xlfn.XLOOKUP('PREENCHIMENTO|LETIVAS'!A26,PARAMETROS!A:A,PARAMETROS!I:I)) -> PROFESSOR REGENTE | F26: 51|2026 | G26: ESTENDIDA | H26: 3 - Terça | I26: 19:00 às 20:30 | J26: ATELIÊ DE ARQUITETURA: EDIFÍCIOS VERTICAIS | W26: =IF(I26<>"",2,0) -> 2
A27: UGO ANDREATA GALIMBERTTI | B27: =IF(_xlfn.XLOOKUP(A27,PARAMETROS!A:A,PARAMETROS!B:B)=0,"",_xlfn.XLOOKUP(A27,PARAMETROS!A:A,PARAMETROS!B:B)) -> 012009006226 | C27: =IF(_xlfn.XLOOKUP(A27,PARAMETROS!A:A,PARAMETROS!C:C)=0,"",_xlfn.XLOOKUP(A27,PARAMETROS!A:A,PARAMETROS!C:C)) -> 40 | D27: =IF(_xlfn.XLOOKUP(A27,PARAMETROS!A:A,PARAMETROS!D:D)=0,"",_xlfn.XLOOKUP(A27,PARAMETROS!A:A,PARAMETROS!D:D)) -> 20 | E27: =IF(_xlfn.XLOOKUP('PREENCHIMENTO|LETIVAS'!A27,PARAMETROS!A:A,PARAMETROS!I:I)=0,"",_xlfn.XLOOKUP('PREENCHIMENTO|LETIVAS'!A27,PARAMETROS!A:A,PARAMETROS!I:I)) -> PROFESSOR REGENTE | F27: 51|2026 | G27: ESTENDIDA | H27: 3 - Terça | I27: 19:00 às 20:30 | J27: ATELIÊ DE PROJETO DE ARQUITETURA: EDIFÍCIOS VERTICAIS | W27: =IF(I27<>"",2,0) -> 2
A28: UGO ANDREATA GALIMBERTTI | B28: =IF(_xlfn.XLOOKUP(A28,PARAMETROS!A:A,PARAMETROS!B:B)=0,"",_xlfn.XLOOKUP(A28,PARAMETROS!A:A,PARAMETROS!B:B)) -> 012009006226 | C28: =IF(_xlfn.XLOOKUP(A28,PARAMETROS!A:A,PARAMETROS!C:C)=0,"",_xlfn.XLOOKUP(A28,PARAMETROS!A:A,PARAMETROS!C:C)) -> 40 | D28: =IF(_xlfn.XLOOKUP(A28,PARAMETROS!A:A,PARAMETROS!D:D)=0,"",_xlfn.XLOOKUP(A28,PARAMETROS!A:A,PARAMETROS!D:D)) -> 20 | E28: =IF(_xlfn.XLOOKUP('PREENCHIMENTO|LETIVAS'!A28,PARAMETROS!A:A,PARAMETROS!I:I)=0,"",_xlfn.XLOOKUP('PREENCHIMENTO|LETIVAS'!A28,PARAMETROS!A:A,PARAMETROS!I:I)) -> PROFESSOR REGENTE | F28: 51|2026 | G28: ESTENDIDA | H28: 4 - Quarta | I28: 19:00 às 20:30 | J28: DESENHO ARQUITETÔNICO AUXILIADO POR COMPUTADOR | W28: =IF(I28<>"",2,0) -> 2
A29: UGO ANDREATA GALIMBERTTI | B29: =IF(_xlfn.XLOOKUP(A29,PARAMETROS!A:A,PARAMETROS!B:B)=0,"",_xlfn.XLOOKUP(A29,PARAMETROS!A:A,PARAMETROS!B:B)) -> 012009006226 | C29: =IF(_xlfn.XLOOKUP(A29,PARAMETROS!A:A,PARAMETROS!C:C)=0,"",_xlfn.XLOOKUP(A29,PARAMETROS!A:A,PARAMETROS!C:C)) -> 40 | D29: =IF(_xlfn.XLOOKUP(A29,PARAMETROS!A:A,PARAMETROS!D:D)=0,"",_xlfn.XLOOKUP(A29,PARAMETROS!A:A,PARAMETROS!D:D)) -> 20 | E29: =IF(_xlfn.XLOOKUP('PREENCHIMENTO|LETIVAS'!A29,PARAMETROS!A:A,PARAMETROS!I:I)=0,"",_xlfn.XLOOKUP('PREENCHIMENTO|LETIVAS'!A29,PARAMETROS!A:A,PARAMETROS!I:I)) -> PROFESSOR REGENTE | F29: 51|2026 | G29: ESTENDIDA | H29: 4 - Quarta | I29: 20:40 às 22:10 | J29: DESENHO UNIVERSAL | W29: =IF(I29<>"",2,0) -> 2
A30: UGO ANDREATA GALIMBERTTI | B30: =IF(_xlfn.XLOOKUP(A30,PARAMETROS!A:A,PARAMETROS!B:B)=0,"",_xlfn.XLOOKUP(A30,PARAMETROS!A:A,PARAMETROS!B:B)) -> 012009006226 | C30: =IF(_xlfn.XLOOKUP(A30,PARAMETROS!A:A,PARAMETROS!C:C)=0,"",_xlfn.XLOOKUP(A30,PARAMETROS!A:A,PARAMETROS!C:C)) -> 40 | D30: =IF(_xlfn.XLOOKUP(A30,PARAMETROS!A:A,PARAMETROS!D:D)=0,"",_xlfn.XLOOKUP(A30,PARAMETROS!A:A,PARAMETROS!D:D)) -> 20 | E30: =IF(_xlfn.XLOOKUP('PREENCHIMENTO|LETIVAS'!A30,PARAMETROS!A:A,PARAMETROS!I:I)=0,"",_xlfn.XLOOKUP('PREENCHIMENTO|LETIVAS'!A30,PARAMETROS!A:A,PARAMETROS!I:I)) -> PROFESSOR REGENTE | F30: 51|2026 | G30: ESTENDIDA | H30: 2 - Segunda | I30: 19:00 às 20:30 | J30: DESENHO TÉCNICO | W30: =IF(I30<>"",2,0) -> 2
A31: BRUNA EDUARDA KUBLISKI FOLMER ROMAN | B31: =IF(_xlfn.XLOOKUP(A31,PARAMETROS!A:A,PARAMETROS!B:B)=0,"",_xlfn.XLOOKUP(A31,PARAMETROS!A:A,PARAMETROS!B:B)) -> 012009006311 | C31: =IF(_xlfn.XLOOKUP(A31,PARAMETROS!A:A,PARAMETROS!C:C)=0,"",_xlfn.XLOOKUP(A31,PARAMETROS!A:A,PARAMETROS!C:C)) -> 12 | D31: =IF(_xlfn.XLOOKUP(A31,PARAMETROS!A:A,PARAMETROS!D:D)=0,"",_xlfn.XLOOKUP(A31,PARAMETROS!A:A,PARAMETROS!D:D)) -> 9 | E31: =IF(_xlfn.XLOOKUP('PREENCHIMENTO|LETIVAS'!A31,PARAMETROS!A:A,PARAMETROS!I:I)=0,"",_xlfn.XLOOKUP('PREENCHIMENTO|LETIVAS'!A31,PARAMETROS!A:A,PARAMETROS!I:I)) -> PROFESSOR REGENTE | F31: 51|2026 | G31: ESTENDIDA | H31: 4 - Quarta | I31: 19:00 às 20:30 | J31: ATELIÊ DE PROJETO DE ARQUITETURA: RESIDENCIAL | W31: =IF(I31<>"",2,0) -> 2
A32: BRUNA EDUARDA KUBLISKI FOLMER ROMAN | B32: =IF(_xlfn.XLOOKUP(A32,PARAMETROS!A:A,PARAMETROS!B:B)=0,"",_xlfn.XLOOKUP(A32,PARAMETROS!A:A,PARAMETROS!B:B)) -> 012009006311 | C32: =IF(_xlfn.XLOOKUP(A32,PARAMETROS!A:A,PARAMETROS!C:C)=0,"",_xlfn.XLOOKUP(A32,PARAMETROS!A:A,PARAMETROS!C:C)) -> 12 | D32: =IF(_xlfn.XLOOKUP(A32,PARAMETROS!A:A,PARAMETROS!D:D)=0,"",_xlfn.XLOOKUP(A32,PARAMETROS!A:A,PARAMETROS!D:D)) -> 9 | E32: =IF(_xlfn.XLOOKUP('PREENCHIMENTO|LETIVAS'!A32,PARAMETROS!A:A,PARAMETROS!I:I)=0,"",_xlfn.XLOOKUP('PREENCHIMENTO|LETIVAS'!A32,PARAMETROS!A:A,PARAMETROS!I:I)) -> PROFESSOR REGENTE | F32: 51|2026 | G32: ESTENDIDA | H32: 4 - Quarta | I32: 20:40 às 22:10 | J32: TEORIA DA ARQUITETURA E URBANISMO | W32: =IF(I32<>"",2,0) -> 2
A33: LUCAS MEN BENATTI | B33: =IF(_xlfn.XLOOKUP(A33,PARAMETROS!A:A,PARAMETROS!B:B)=0,"",_xlfn.XLOOKUP(A33,PARAMETROS!A:A,PARAMETROS!B:B)) -> 012009006258 | C33: =IF(_xlfn.XLOOKUP(A33,PARAMETROS!A:A,PARAMETROS!C:C)=0,"",_xlfn.XLOOKUP(A33,PARAMETROS!A:A,PARAMETROS!C:C)) -> 12 | D33: =IF(_xlfn.XLOOKUP(A33,PARAMETROS!A:A,PARAMETROS!D:D)=0,"",_xlfn.XLOOKUP(A33,PARAMETROS!A:A,PARAMETROS!D:D)) -> 9 | E33: =IF(_xlfn.XLOOKUP('PREENCHIMENTO|LETIVAS'!A33,PARAMETROS!A:A,PARAMETROS!I:I)=0,"",_xlfn.XLOOKUP('PREENCHIMENTO|LETIVAS'!A33,PARAMETROS!A:A,PARAMETROS!I:I)) -> PROFESSOR REGENTE | F33: 51|2026 | G33: ESTENDIDA | H33: 4 - Quarta | I33: 19:00 às 20:30 | J33: ESTÉTICA E HISTÓRIA DA ARTE | W33: =IF(I33<>"",2,0) -> 2
A34: LUCAS MEN BENATTI | B34: =IF(_xlfn.XLOOKUP(A34,PARAMETROS!A:A,PARAMETROS!B:B)=0,"",_xlfn.XLOOKUP(A34,PARAMETROS!A:A,PARAMETROS!B:B)) -> 012009006258 | C34: =IF(_xlfn.XLOOKUP(A34,PARAMETROS!A:A,PARAMETROS!C:C)=0,"",_xlfn.XLOOKUP(A34,PARAMETROS!A:A,PARAMETROS!C:C)) -> 12 | D34: =IF(_xlfn.XLOOKUP(A34,PARAMETROS!A:A,PARAMETROS!D:D)=0,"",_xlfn.XLOOKUP(A34,PARAMETROS!A:A,PARAMETROS!D:D)) -> 9 | E34: =IF(_xlfn.XLOOKUP('PREENCHIMENTO|LETIVAS'!A34,PARAMETROS!A:A,PARAMETROS!I:I)=0,"",_xlfn.XLOOKUP('PREENCHIMENTO|LETIVAS'!A34,PARAMETROS!A:A,PARAMETROS!I:I)) -> PROFESSOR REGENTE | F34: 51|2026 | G34: 2 | H34: 5 - Quinta | I34: 19:00 às 20:30 | J34: ARTE CONTEMPORÂNEA | W34: =IF(I34<>"",2,0) -> 2
A35: LEONARDO DA SILVA FERREIRA | B35: =IF(_xlfn.XLOOKUP(A35,PARAMETROS!A:A,PARAMETROS!B:B)=0,"",_xlfn.XLOOKUP(A35,PARAMETROS!A:A,PARAMETROS!B:B)) -> 012009006237 | C35: =IF(_xlfn.XLOOKUP(A35,PARAMETROS!A:A,PARAMETROS!C:C)=0,"",_xlfn.XLOOKUP(A35,PARAMETROS!A:A,PARAMETROS!C:C)) -> 12 | D35: =IF(_xlfn.XLOOKUP(A35,PARAMETROS!A:A,PARAMETROS!D:D)=0,"",_xlfn.XLOOKUP(A35,PARAMETROS!A:A,PARAMETROS!D:D)) -> 9 | E35: =IF(_xlfn.XLOOKUP('PREENCHIMENTO|LETIVAS'!A35,PARAMETROS!A:A,PARAMETROS!I:I)=0,"",_xlfn.XLOOKUP('PREENCHIMENTO|LETIVAS'!A35,PARAMETROS!A:A,PARAMETROS!I:I)) -> PROFESSOR REGENTE | F35: 51|2026 | G35: ESTENDIDA | H35: 3 - Terça | I35: 20:40 às 22:10 | J35: TEORIA DO URBANISMO | W35: =IF(I35<>"",2,0) -> 2
A36: LEONARDO DA SILVA FERREIRA | B36: =IF(_xlfn.XLOOKUP(A36,PARAMETROS!A:A,PARAMETROS!B:B)=0,"",_xlfn.XLOOKUP(A36,PARAMETROS!A:A,PARAMETROS!B:B)) -> 012009006237 | C36: =IF(_xlfn.XLOOKUP(A36,PARAMETROS!A:A,PARAMETROS!C:C)=0,"",_xlfn.XLOOKUP(A36,PARAMETROS!A:A,PARAMETROS!C:C)) -> 12 | D36: =IF(_xlfn.XLOOKUP(A36,PARAMETROS!A:A,PARAMETROS!D:D)=0,"",_xlfn.XLOOKUP(A36,PARAMETROS!A:A,PARAMETROS!D:D)) -> 9 | E36: =IF(_xlfn.XLOOKUP('PREENCHIMENTO|LETIVAS'!A36,PARAMETROS!A:A,PARAMETROS!I:I)=0,"",_xlfn.XLOOKUP('PREENCHIMENTO|LETIVAS'!A36,PARAMETROS!A:A,PARAMETROS!I:I)) -> PROFESSOR REGENTE | F36: 51|2026 | G36: ESTENDIDA | H36: 3 - Terça | I36: 19:00 às 20:30 | J36: TEORIA E HISTÓRIA DA ARQUITETURA, DO URBANISMO E DO PAISAGISMO | W36: =IF(I36<>"",2,0) -> 2
A37: LEONARDO DA SILVA FERREIRA | B37: =IF(_xlfn.XLOOKUP(A37,PARAMETROS!A:A,PARAMETROS!B:B)=0,"",_xlfn.XLOOKUP(A37,PARAMETROS!A:A,PARAMETROS!B:B)) -> 012009006237 | C37: =IF(_xlfn.XLOOKUP(A37,PARAMETROS!A:A,PARAMETROS!C:C)=0,"",_xlfn.XLOOKUP(A37,PARAMETROS!A:A,PARAMETROS!C:C)) -> 12 | D37: =IF(_xlfn.XLOOKUP(A37,PARAMETROS!A:A,PARAMETROS!D:D)=0,"",_xlfn.XLOOKUP(A37,PARAMETROS!A:A,PARAMETROS!D:D)) -> 9 | E37: =IF(_xlfn.XLOOKUP('PREENCHIMENTO|LETIVAS'!A37,PARAMETROS!A:A,PARAMETROS!I:I)=0,"",_xlfn.XLOOKUP('PREENCHIMENTO|LETIVAS'!A37,PARAMETROS!A:A,PARAMETROS!I:I)) -> PROFESSOR REGENTE | F37: 51|2026 | G37: 2 | H37: 4 - Quarta | I37: 20:40 às 22:10 | J37: PLANEJAMENTO E DESENVOLVIMENTO URBANO | W37: =IF(I37<>"",2,0) -> 2
A38: RAONY ROBSON RUIZ | B38: =IF(_xlfn.XLOOKUP(A38,PARAMETROS!A:A,PARAMETROS!B:B)=0,"",_xlfn.XLOOKUP(A38,PARAMETROS!A:A,PARAMETROS!B:B)) -> 012009006222 | C38: =IF(_xlfn.XLOOKUP(A38,PARAMETROS!A:A,PARAMETROS!C:C)=0,"",_xlfn.XLOOKUP(A38,PARAMETROS!A:A,PARAMETROS!C:C)) -> 12 | D38: =IF(_xlfn.XLOOKUP(A38,PARAMETROS!A:A,PARAMETROS!D:D)=0,"",_xlfn.XLOOKUP(A38,PARAMETROS!A:A,PARAMETROS!D:D)) -> 9 | E38: =IF(_xlfn.XLOOKUP('PREENCHIMENTO|LETIVAS'!A38,PARAMETROS!A:A,PARAMETROS!I:I)=0,"",_xlfn.XLOOKUP('PREENCHIMENTO|LETIVAS'!A38,PARAMETROS!A:A,PARAMETROS!I:I)) -> PROFESSOR REGENTE | F38: 51|2026 | G38: 1 | H38: 5 - Quinta | I38: 19:00 às 20:30 | J38: ARTE DIGITAL | W38: =IF(I38<>"",2,0) -> 2
A39: RAONY ROBSON RUIZ | B39: =IF(_xlfn.XLOOKUP(A39,PARAMETROS!A:A,PARAMETROS!B:B)=0,"",_xlfn.XLOOKUP(A39,PARAMETROS!A:A,PARAMETROS!B:B)) -> 012009006222 | C39: =IF(_xlfn.XLOOKUP(A39,PARAMETROS!A:A,PARAMETROS!C:C)=0,"",_xlfn.XLOOKUP(A39,PARAMETROS!A:A,PARAMETROS!C:C)) -> 12 | D39: =IF(_xlfn.XLOOKUP(A39,PARAMETROS!A:A,PARAMETROS!D:D)=0,"",_xlfn.XLOOKUP(A39,PARAMETROS!A:A,PARAMETROS!D:D)) -> 9 | E39: =IF(_xlfn.XLOOKUP('PREENCHIMENTO|LETIVAS'!A39,PARAMETROS!A:A,PARAMETROS!I:I)=0,"",_xlfn.XLOOKUP('PREENCHIMENTO|LETIVAS'!A39,PARAMETROS!A:A,PARAMETROS!I:I)) -> PROFESSOR REGENTE | F39: 51|2026 | G39: 2 | H39: 5 - Quinta | I39: 19:00 às 20:30 | J39: FUNDAMENTOS DA LINGUAGEM VISUAL | W39: =IF(I39<>"",2,0) -> 2
A40: TAYENE ELIZE MACAO | B40: =IF(_xlfn.XLOOKUP(A40,PARAMETROS!A:A,PARAMETROS!B:B)=0,"",_xlfn.XLOOKUP(A40,PARAMETROS!A:A,PARAMETROS!B:B)) -> 012009006225 | C40: =IF(_xlfn.XLOOKUP(A40,PARAMETROS!A:A,PARAMETROS!C:C)=0,"",_xlfn.XLOOKUP(A40,PARAMETROS!A:A,PARAMETROS!C:C)) -> 12 | D40: =IF(_xlfn.XLOOKUP(A40,PARAMETROS!A:A,PARAMETROS!D:D)=0,"",_xlfn.XLOOKUP(A40,PARAMETROS!A:A,PARAMETROS!D:D)) -> 9 | E40: =IF(_xlfn.XLOOKUP('PREENCHIMENTO|LETIVAS'!A40,PARAMETROS!A:A,PARAMETROS!I:I)=0,"",_xlfn.XLOOKUP('PREENCHIMENTO|LETIVAS'!A40,PARAMETROS!A:A,PARAMETROS!I:I)) -> PROFESSOR REGENTE | F40: 51|2026 | G40: 2 | H40: 5 - Quinta | I40: 20:40 às 22:10 | J40: LINGUAGEM POÉTICA DAS ARTES CÊNICAS | W40: =IF(I40<>"",2,0) -> 2
A41: TAYENE ELIZE MACAO | B41: =IF(_xlfn.XLOOKUP(A41,PARAMETROS!A:A,PARAMETROS!B:B)=0,"",_xlfn.XLOOKUP(A41,PARAMETROS!A:A,PARAMETROS!B:B)) -> 012009006225 | C41: =IF(_xlfn.XLOOKUP(A41,PARAMETROS!A:A,PARAMETROS!C:C)=0,"",_xlfn.XLOOKUP(A41,PARAMETROS!A:A,PARAMETROS!C:C)) -> 12 | D41: =IF(_xlfn.XLOOKUP(A41,PARAMETROS!A:A,PARAMETROS!D:D)=0,"",_xlfn.XLOOKUP(A41,PARAMETROS!A:A,PARAMETROS!D:D)) -> 9 | E41: =IF(_xlfn.XLOOKUP('PREENCHIMENTO|LETIVAS'!A41,PARAMETROS!A:A,PARAMETROS!I:I)=0,"",_xlfn.XLOOKUP('PREENCHIMENTO|LETIVAS'!A41,PARAMETROS!A:A,PARAMETROS!I:I)) -> PROFESSOR REGENTE | F41: 51|2026 | G41: 2 | H41: 5 - Quinta | I41: 19:00 às 20:30 | J41: CONTEXTO HISTÓRICO DO TEATRO | W41: =IF(I41<>"",2,0) -> 2
A42: TEREZA CRISTINA DE CARVALHO | B42: =IF(_xlfn.XLOOKUP(A42,PARAMETROS!A:A,PARAMETROS!B:B)=0,"",_xlfn.XLOOKUP(A42,PARAMETROS!A:A,PARAMETROS!B:B)) -> 012009003575 | C42: =IF(_xlfn.XLOOKUP(A42,PARAMETROS!A:A,PARAMETROS!C:C)=0,"",_xlfn.XLOOKUP(A42,PARAMETROS!A:A,PARAMETROS!C:C)) -> 20 | D42: =IF(_xlfn.XLOOKUP(A42,PARAMETROS!A:A,PARAMETROS!D:D)=0,"",_xlfn.XLOOKUP(A42,PARAMETROS!A:A,PARAMETROS!D:D)) -> 2 | E42: =IF(_xlfn.XLOOKUP('PREENCHIMENTO|LETIVAS'!A42,PARAMETROS!A:A,PARAMETROS!I:I)=0,"",_xlfn.XLOOKUP('PREENCHIMENTO|LETIVAS'!A42,PARAMETROS!A:A,PARAMETROS!I:I)) -> PROFESSOR DE ENSINO SUPERIOR EAD | F42: 51|2026 | G42: 2 | H42: 5 - Quinta | I42: 20:40 às 22:10 | J42: POLÍTICAS EDUCACIONAIS E ORGANIZAÇÃO DA EDUCAÇÃO BÁSICA | W42: =IF(I42<>"",2,0) -> 2
A43: RAQUEL DE ARAUJO BOMFIM GARCIA | B43: =IF(_xlfn.XLOOKUP(A43,PARAMETROS!A:A,PARAMETROS!B:B)=0,"",_xlfn.XLOOKUP(A43,PARAMETROS!A:A,PARAMETROS!B:B)) -> 012009003803 | C43: =IF(_xlfn.XLOOKUP(A43,PARAMETROS!A:A,PARAMETROS!C:C)=0,"",_xlfn.XLOOKUP(A43,PARAMETROS!A:A,PARAMETROS!C:C)) -> 20 | D43: =IF(_xlfn.XLOOKUP(A43,PARAMETROS!A:A,PARAMETROS!D:D)=0,"",_xlfn.XLOOKUP(A43,PARAMETROS!A:A,PARAMETROS!D:D)) -> 2 | E43: =IF(_xlfn.XLOOKUP('PREENCHIMENTO|LETIVAS'!A43,PARAMETROS!A:A,PARAMETROS!I:I)=0,"",_xlfn.XLOOKUP('PREENCHIMENTO|LETIVAS'!A43,PARAMETROS!A:A,PARAMETROS!I:I)) -> PROFESSOR DE ENSINO SUPERIOR EAD | F43: 51|2026 | G43: 2 | H43: 3 - Terça | I43: 19:00 às 20:30 | J43: PENSAMENTO CLÍNICO E POSTURA TERAPÊUTICA | W43: =IF(I43<>"",2,0) -> 2
A44: MARIANA ARDENGUE | B44: =IF(_xlfn.XLOOKUP(A44,PARAMETROS!A:A,PARAMETROS!B:B)=0,"",_xlfn.XLOOKUP(A44,PARAMETROS!A:A,PARAMETROS!B:B)) -> 012009004121 | C44: =IF(_xlfn.XLOOKUP(A44,PARAMETROS!A:A,PARAMETROS!C:C)=0,"",_xlfn.XLOOKUP(A44,PARAMETROS!A:A,PARAMETROS!C:C)) -> 20 | D44: =IF(_xlfn.XLOOKUP(A44,PARAMETROS!A:A,PARAMETROS!D:D)=0,"",_xlfn.XLOOKUP(A44,PARAMETROS!A:A,PARAMETROS!D:D)) -> 2 | E44: =IF(_xlfn.XLOOKUP('PREENCHIMENTO|LETIVAS'!A44,PARAMETROS!A:A,PARAMETROS!I:I)=0,"",_xlfn.XLOOKUP('PREENCHIMENTO|LETIVAS'!A44,PARAMETROS!A:A,PARAMETROS!I:I)) -> PROFESSOR DE ENSINO SUPERIOR EAD | F44: 51|2026 | G44: 1 | H44: 3 - Terça | I44: 19:00 às 20:30 | J44: ATIVIDADE FÍSICA E QUALIDADE DE VIDA | W44: =IF(I44<>"",2,0) -> 2
A45: ADRIANO RUY MATSUO | B45: =IF(_xlfn.XLOOKUP(A45,PARAMETROS!A:A,PARAMETROS!B:B)=0,"",_xlfn.XLOOKUP(A45,PARAMETROS!A:A,PARAMETROS!B:B)) -> 012009003801 | C45: =IF(_xlfn.XLOOKUP(A45,PARAMETROS!A:A,PARAMETROS!C:C)=0,"",_xlfn.XLOOKUP(A45,PARAMETROS!A:A,PARAMETROS!C:C)) -> 40 | D45: =IF(_xlfn.XLOOKUP(A45,PARAMETROS!A:A,PARAMETROS!D:D)=0,"",_xlfn.XLOOKUP(A45,PARAMETROS!A:A,PARAMETROS!D:D)) -> 4 | E45: =IF(_xlfn.XLOOKUP('PREENCHIMENTO|LETIVAS'!A45,PARAMETROS!A:A,PARAMETROS!I:I)=0,"",_xlfn.XLOOKUP('PREENCHIMENTO|LETIVAS'!A45,PARAMETROS!A:A,PARAMETROS!I:I)) -> PROFESSOR DE ENSINO SUPERIOR EAD | F45: 51|2026 | G45: 2 | H45: 3 - Terça | I45: 19:00 às 20:30 | J45: ATLETISMO | W45: =IF(I45<>"",2,0) -> 2
A46: ADRIANO RUY MATSUO | B46: =IF(_xlfn.XLOOKUP(A46,PARAMETROS!A:A,PARAMETROS!B:B)=0,"",_xlfn.XLOOKUP(A46,PARAMETROS!A:A,PARAMETROS!B:B)) -> 012009003801 | C46: =IF(_xlfn.XLOOKUP(A46,PARAMETROS!A:A,PARAMETROS!C:C)=0,"",_xlfn.XLOOKUP(A46,PARAMETROS!A:A,PARAMETROS!C:C)) -> 40 | D46: =IF(_xlfn.XLOOKUP(A46,PARAMETROS!A:A,PARAMETROS!D:D)=0,"",_xlfn.XLOOKUP(A46,PARAMETROS!A:A,PARAMETROS!D:D)) -> 4 | E46: =IF(_xlfn.XLOOKUP('PREENCHIMENTO|LETIVAS'!A46,PARAMETROS!A:A,PARAMETROS!I:I)=0,"",_xlfn.XLOOKUP('PREENCHIMENTO|LETIVAS'!A46,PARAMETROS!A:A,PARAMETROS!I:I)) -> PROFESSOR DE ENSINO SUPERIOR EAD | F46: 51|2026 | G46: 2 | H46: 3 - Terça | I46: 20:40 às 22:10 | J46: MUSCULAÇÃO E EXERCÍCIOS RESISTIDOS | W46: =IF(I46<>"",2,0) -> 2
A47: CLEBER MENA LEAO JUNIOR | B47: =IF(_xlfn.XLOOKUP(A47,PARAMETROS!A:A,PARAMETROS!B:B)=0,"",_xlfn.XLOOKUP(A47,PARAMETROS!A:A,PARAMETROS!B:B)) -> 012009006141 | C47: =IF(_xlfn.XLOOKUP(A47,PARAMETROS!A:A,PARAMETROS!C:C)=0,"",_xlfn.XLOOKUP(A47,PARAMETROS!A:A,PARAMETROS!C:C)) -> 20 | D47: =IF(_xlfn.XLOOKUP(A47,PARAMETROS!A:A,PARAMETROS!D:D)=0,"",_xlfn.XLOOKUP(A47,PARAMETROS!A:A,PARAMETROS!D:D)) -> 2 | E47: =IF(_xlfn.XLOOKUP('PREENCHIMENTO|LETIVAS'!A47,PARAMETROS!A:A,PARAMETROS!I:I)=0,"",_xlfn.XLOOKUP('PREENCHIMENTO|LETIVAS'!A47,PARAMETROS!A:A,PARAMETROS!I:I)) -> PROFESSOR DE ENSINO SUPERIOR EAD | F47: 51|2026 | G47: 2 | H47: 3 - Terça | I47: 20:40 às 22:10 | J47: LUTAS | W47: =IF(I47<>"",2,0) -> 2
A48: JULIANA FRANCO AFONSO | B48: =IF(_xlfn.XLOOKUP(A48,PARAMETROS!A:A,PARAMETROS!B:B)=0,"",_xlfn.XLOOKUP(A48,PARAMETROS!A:A,PARAMETROS!B:B)) -> 012009003454 | C48: =IF(_xlfn.XLOOKUP(A48,PARAMETROS!A:A,PARAMETROS!C:C)=0,"",_xlfn.XLOOKUP(A48,PARAMETROS!A:A,PARAMETROS!C:C)) -> 40 | D48: =IF(_xlfn.XLOOKUP(A48,PARAMETROS!A:A,PARAMETROS!D:D)=0,"",_xlfn.XLOOKUP(A48,PARAMETROS!A:A,PARAMETROS!D:D)) -> 4 | E48: =IF(_xlfn.XLOOKUP('PREENCHIMENTO|LETIVAS'!A48,PARAMETROS!A:A,PARAMETROS!I:I)=0,"",_xlfn.XLOOKUP('PREENCHIMENTO|LETIVAS'!A48,PARAMETROS!A:A,PARAMETROS!I:I)) -> PROFESSOR DE ENSINO SUPERIOR EAD | F48: 51|2026 | G48: 2 | H48: 3 - Terça | I48: 19:00 às 20:30 | J48: CENÁRIOS ECONÔMICOS | W48: =IF(I48<>"",2,0) -> 2
... A67: RAUL GRECO JUNIOR | B67: =IF(_xlfn.XLOOKUP(A67,PARAMETROS!A:A,PARAMETROS!B:B)=0,"",_xlfn.XLOOKUP(A67,PARAMETROS!A:A,PARAMETROS!B:B)) -> 012009005662 | C67: =IF(_xlfn.XLOOKUP(A67,PARAMETROS!A:A,PARAMETROS!C:C)=0,"",_xlfn.XLOOKUP(A67,PARAMETROS!A:A,PARAMETROS!C:C)) -> 40 | D67: =IF(_xlfn.XLOOKUP(A67,PARAMETROS!A:A,PARAMETROS!D:D)=0,"",_xlfn.XLOOKUP(A67,PARAMETROS!A:A,PARAMETROS!D:D)) -> 4 | E67: =IF(_xlfn.XLOOKUP('PREENCHIMENTO|LETIVAS'!A67,PARAMETROS!A:A,PARAMETROS!I:I)=0,"",_xlfn.XLOOKUP('PREENCHIMENTO|LETIVAS'!A67,PARAMETROS!A:A,PARAMETROS!I:I)) -> PROFESSOR DE ENSINO SUPERIOR EAD | F67: 51|2026 | G67: 2 | H67: 3 - Terça | I67: 19:00 às 20:30 | J67: CLOUD COMPUTING | W67: =IF(I67<>"",2,0) -> 2
A68: VICTOR DE MARQUI PEDROSO | B68: =IF(_xlfn.XLOOKUP(A68,PARAMETROS!A:A,PARAMETROS!B:B)=0,"",_xlfn.XLOOKUP(A68,PARAMETROS!A:A,PARAMETROS!B:B)) -> 012009003435 | C68: =IF(_xlfn.XLOOKUP(A68,PARAMETROS!A:A,PARAMETROS!C:C)=0,"",_xlfn.XLOOKUP(A68,PARAMETROS!A:A,PARAMETROS!C:C)) -> 40 | D68: =IF(_xlfn.XLOOKUP(A68,PARAMETROS!A:A,PARAMETROS!D:D)=0,"",_xlfn.XLOOKUP(A68,PARAMETROS!A:A,PARAMETROS!D:D)) -> 4 | E68: =IF(_xlfn.XLOOKUP('PREENCHIMENTO|LETIVAS'!A68,PARAMETROS!A:A,PARAMETROS!I:I)=0,"",_xlfn.XLOOKUP('PREENCHIMENTO|LETIVAS'!A68,PARAMETROS!A:A,PARAMETROS!I:I)) -> PROFESSOR DE ENSINO SUPERIOR EAD | F68: 51|2026 | G68: ESTENDIDA | H68: 3 - Terça | I68: 19:00 às 20:30 | J68: IMERSÃO PROFISSIONAL: PROJETO DE INTERFACE | W68: =IF(I68<>"",2,0) -> 2
A69: VICTOR DE MARQUI PEDROSO | B69: =IF(_xlfn.XLOOKUP(A69,PARAMETROS!A:A,PARAMETROS!B:B)=0,"",_xlfn.XLOOKUP(A69,PARAMETROS!A:A,PARAMETROS!B:B)) -> 012009003435 | C69: =IF(_xlfn.XLOOKUP(A69,PARAMETROS!A:A,PARAMETROS!C:C)=0,"",_xlfn.XLOOKUP(A69,PARAMETROS!A:A,PARAMETROS!C:C)) -> 40 | D69: =IF(_xlfn.XLOOKUP(A69,PARAMETROS!A:A,PARAMETROS!D:D)=0,"",_xlfn.XLOOKUP(A69,PARAMETROS!A:A,PARAMETROS!D:D)) -> 4 | E69: =IF(_xlfn.XLOOKUP('PREENCHIMENTO|LETIVAS'!A69,PARAMETROS!A:A,PARAMETROS!I:I)=0,"",_xlfn.XLOOKUP('PREENCHIMENTO|LETIVAS'!A69,PARAMETROS!A:A,PARAMETROS!I:I)) -> PROFESSOR DE ENSINO SUPERIOR EAD | F69: 51|2026 | G69: 2 | H69: 3 - Terça | I69: 19:00 às 20:30 | J69: INTERFACE HUMANO-COMPUTADOR | W69: =IF(I69<>"",2,0) -> 2
A70: HELOUISE HELLEN DE GODOI VIOLA | B70: =IF(_xlfn.XLOOKUP(A70,PARAMETROS!A:A,PARAMETROS!B:B)=0,"",_xlfn.XLOOKUP(A70,PARAMETROS!A:A,PARAMETROS!B:B)) -> 012009005858 | C70: =IF(_xlfn.XLOOKUP(A70,PARAMETROS!A:A,PARAMETROS!C:C)=0,"",_xlfn.XLOOKUP(A70,PARAMETROS!A:A,PARAMETROS!C:C)) -> 40 | D70: =IF(_xlfn.XLOOKUP(A70,PARAMETROS!A:A,PARAMETROS!D:D)=0,"",_xlfn.XLOOKUP(A70,PARAMETROS!A:A,PARAMETROS!D:D)) -> 4 | E70: =IF(_xlfn.XLOOKUP('PREENCHIMENTO|LETIVAS'!A70,PARAMETROS!A:A,PARAMETROS!I:I)=0,"",_xlfn.XLOOKUP('PREENCHIMENTO|LETIVAS'!A70,PARAMETROS!A:A,PARAMETROS!I:I)) -> PROFESSOR DE ENSINO SUPERIOR EAD | F70: 51|2026 | G70: 1 | H70: 3 - Terça | I70: 19:00 às 20:30 | J70: GESTÃO DE BIBLIOTECAS | W70: =IF(I70<>"",2,0) -> 2
A71: JULLY OYAMA TAKIZAWA | B71: =IF(_xlfn.XLOOKUP(A71,PARAMETROS!A:A,PARAMETROS!B:B)=0,"",_xlfn.XLOOKUP(A71,PARAMETROS!A:A,PARAMETROS!B:B)) -> 012009005223 | C71: =IF(_xlfn.XLOOKUP(A71,PARAMETROS!A:A,PARAMETROS!C:C)=0,"",_xlfn.XLOOKUP(A71,PARAMETROS!A:A,PARAMETROS!C:C)) -> 20 | D71: =IF(_xlfn.XLOOKUP(A71,PARAMETROS!A:A,PARAMETROS!D:D)=0,"",_xlfn.XLOOKUP(A71,PARAMETROS!A:A,PARAMETROS!D:D)) -> 2 | E71: =IF(_xlfn.XLOOKUP('PREENCHIMENTO|LETIVAS'!A71,PARAMETROS!A:A,PARAMETROS!I:I)=0,"",_xlfn.XLOOKUP('PREENCHIMENTO|LETIVAS'!A71,PARAMETROS!A:A,PARAMETROS!I:I)) -> PROFESSOR DE ENSINO SUPERIOR EAD | F71: 51|2026 | G71: ESTENDIDA | H71: 5 - Quinta | I71: 19:00 às 20:30 | J71: BIOLOGIA MOLECULAR E FORENSE​ | W71: =IF(I71<>"",2,0) -> 2
A72: BARBARA LETICIA DA SILVA GUEDES DE MOURA | B72: =IF(_xlfn.XLOOKUP(A72,PARAMETROS!A:A,PARAMETROS!B:B)=0,"",_xlfn.XLOOKUP(A72,PARAMETROS!A:A,PARAMETROS!B:B)) -> 012009005453 | C72: =IF(_xlfn.XLOOKUP(A72,PARAMETROS!A:A,PARAMETROS!C:C)=0,"",_xlfn.XLOOKUP(A72,PARAMETROS!A:A,PARAMETROS!C:C)) -> 20 | D72: =IF(_xlfn.XLOOKUP(A72,PARAMETROS!A:A,PARAMETROS!D:D)=0,"",_xlfn.XLOOKUP(A72,PARAMETROS!A:A,PARAMETROS!D:D)) -> 2 | E72: =IF(_xlfn.XLOOKUP('PREENCHIMENTO|LETIVAS'!A72,PARAMETROS!A:A,PARAMETROS!I:I)=0,"",_xlfn.XLOOKUP('PREENCHIMENTO|LETIVAS'!A72,PARAMETROS!A:A,PARAMETROS!I:I)) -> PROFESSOR DE ENSINO SUPERIOR EAD | F72: 51|2026 | G72: ESTENDIDA | H72: 4 - Quarta | I72: 19:00 às 20:30 | J72: BIOQUÍMICA CLÍNICA | W72: =IF(I72<>"",2,0) -> 2
A73: CYNTIA DANIELLE PINTO GOMES | B73: =IF(_xlfn.XLOOKUP(A73,PARAMETROS!A:A,PARAMETROS!B:B)=0,"",_xlfn.XLOOKUP(A73,PARAMETROS!A:A,PARAMETROS!B:B)) -> 012009006090 | C73: =IF(_xlfn.XLOOKUP(A73,PARAMETROS!A:A,PARAMETROS!C:C)=0,"",_xlfn.XLOOKUP(A73,PARAMETROS!A:A,PARAMETROS!C:C)) -> 20 | D73: =IF(_xlfn.XLOOKUP(A73,PARAMETROS!A:A,PARAMETROS!D:D)=0,"",_xlfn.XLOOKUP(A73,PARAMETROS!A:A,PARAMETROS!D:D)) -> 2 | E73: =IF(_xlfn.XLOOKUP('PREENCHIMENTO|LETIVAS'!A73,PARAMETROS!A:A,PARAMETROS!I:I)=0,"",_xlfn.XLOOKUP('PREENCHIMENTO|LETIVAS'!A73,PARAMETROS!A:A,PARAMETROS!I:I)) -> PROFESSOR DE ENSINO SUPERIOR EAD | F73: 51|2026 | G73: 1 | H73: 5 - Quinta | I73: 19:00 às 20:30 | J73: DIDÁTICA | W73: =IF(I73<>"",2,0) -> 2
A74: SAMUEL RENAN BORGES BELINATO | B74: =IF(_xlfn.XLOOKUP(A74,PARAMETROS!A:A,PARAMETROS!B:B)=0,"",_xlfn.XLOOKUP(A74,PARAMETROS!A:A,PARAMETROS!B:B)) -> 012009005492 | C74: =IF(_xlfn.XLOOKUP(A74,PARAMETROS!A:A,PARAMETROS!C:C)=0,"",_xlfn.XLOOKUP(A74,PARAMETROS!A:A,PARAMETROS!C:C)) -> 20 | D74: =IF(_xlfn.XLOOKUP(A74,PARAMETROS!A:A,PARAMETROS!D:D)=0,"",_xlfn.XLOOKUP(A74,PARAMETROS!A:A,PARAMETROS!D:D)) -> 2 | E74: =IF(_xlfn.XLOOKUP('PREENCHIMENTO|LETIVAS'!A74,PARAMETROS!A:A,PARAMETROS!I:I)=0,"",_xlfn.XLOOKUP('PREENCHIMENTO|LETIVAS'!A74,PARAMETROS!A:A,PARAMETROS!I:I)) -> PROFESSOR DE ENSINO SUPERIOR EAD | F74: 51|2026 | G74: 1 | H74: 2 - Segunda | I74: 20:40 às 22:10 | J74: CONTABILIDADE AVANÇADA | W74: =IF(I74<>"",2,0) -> 2
A75: ROSANGELA DE OLIVEIRA | B75: =IF(_xlfn.XLOOKUP(A75,PARAMETROS!A:A,PARAMETROS!B:B)=0,"",_xlfn.XLOOKUP(A75,PARAMETROS!A:A,PARAMETROS!B:B)) -> 012009003748 | C75: =IF(_xlfn.XLOOKUP(A75,PARAMETROS!A:A,PARAMETROS!C:C)=0,"",_xlfn.XLOOKUP(A75,PARAMETROS!A:A,PARAMETROS!C:C)) -> 20 | D75: =IF(_xlfn.XLOOKUP(A75,PARAMETROS!A:A,PARAMETROS!D:D)=0,"",_xlfn.XLOOKUP(A75,PARAMETROS!A:A,PARAMETROS!D:D)) -> 2 | E75: =IF(_xlfn.XLOOKUP('PREENCHIMENTO|LETIVAS'!A75,PARAMETROS!A:A,PARAMETROS!I:I)=0,"",_xlfn.XLOOKUP('PREENCHIMENTO|LETIVAS'!A75,PARAMETROS!A:A,PARAMETROS!I:I)) -> PROFESSOR DE ENSINO SUPERIOR EAD | F75: 51|2026 | G75: 2 | H75: 2 - Segunda | I75: 20:40 às 22:10 | J75: CONTABILIDADE INTRODUTÓRIA | W75: =IF(I75<>"",2,0) -> 2
A76: CRISTINA KOZAN DE BRITO | B76: =IF(_xlfn.XLOOKUP(A76,PARAMETROS!A:A,PARAMETROS!B:B)=0,"",_xlfn.XLOOKUP(A76,PARAMETROS!A:A,PARAMETROS!B:B)) -> 012009006183 | C76: =IF(_xlfn.XLOOKUP(A76,PARAMETROS!A:A,PARAMETROS!C:C)=0,"",_xlfn.XLOOKUP(A76,PARAMETROS!A:A,PARAMETROS!C:C)) -> 12 | D76: =IF(_xlfn.XLOOKUP(A76,PARAMETROS!A:A,PARAMETROS!D:D)=0,"",_xlfn.XLOOKUP(A76,PARAMETROS!A:A,PARAMETROS!D:D)) -> 9 | E76: =IF(_xlfn.XLOOKUP('PREENCHIMENTO|LETIVAS'!A76,PARAMETROS!A:A,PARAMETROS!I:I)=0,"",_xlfn.XLOOKUP('PREENCHIMENTO|LETIVAS'!A76,PARAMETROS!A:A,PARAMETROS!I:I)) -> PROFESSOR REGENTE | F76: 51|2026 | G76: 2 | H76: 2 - Segunda | I76: 19:00 às 20:30 | J76: ESTATÍSTICA | W76: =IF(I76<>"",2,0) -> 2
A77: CRISTINA KOZAN DE BRITO | B77: =IF(_xlfn.XLOOKUP(A77,PARAMETROS!A:A,PARAMETROS!B:B)=0,"",_xlfn.XLOOKUP(A77,PARAMETROS!A:A,PARAMETROS!B:B)) -> 012009006183 | C77: =IF(_xlfn.XLOOKUP(A77,PARAMETROS!A:A,PARAMETROS!C:C)=0,"",_xlfn.XLOOKUP(A77,PARAMETROS!A:A,PARAMETROS!C:C)) -> 12 | D77: =IF(_xlfn.XLOOKUP(A77,PARAMETROS!A:A,PARAMETROS!D:D)=0,"",_xlfn.XLOOKUP(A77,PARAMETROS!A:A,PARAMETROS!D:D)) -> 9 | E77: =IF(_xlfn.XLOOKUP('PREENCHIMENTO|LETIVAS'!A77,PARAMETROS!A:A,PARAMETROS!I:I)=0,"",_xlfn.XLOOKUP('PREENCHIMENTO|LETIVAS'!A77,PARAMETROS!A:A,PARAMETROS!I:I)) -> PROFESSOR REGENTE | F77: 51|2026 | G77: 2 | H77: 5 - Quinta | I77: 20:40 às 22:10 | J77: ETNOMATEMÁTICA E HISTÓRIA DA MATEMÁTICA | W77: =IF(I77<>"",2,0) -> 2
A78: CRISTINA KOZAN DE BRITO | B78: =IF(_xlfn.XLOOKUP(A78,PARAMETROS!A:A,PARAMETROS!B:B)=0,"",_xlfn.XLOOKUP(A78,PARAMETROS!A:A,PARAMETROS!B:B)) -> 012009006183 | C78: =IF(_xlfn.XLOOKUP(A78,PARAMETROS!A:A,PARAMETROS!C:C)=0,"",_xlfn.XLOOKUP(A78,PARAMETROS!A:A,PARAMETROS!C:C)) -> 12 | D78: =IF(_xlfn.XLOOKUP(A78,PARAMETROS!A:A,PARAMETROS!D:D)=0,"",_xlfn.XLOOKUP(A78,PARAMETROS!A:A,PARAMETROS!D:D)) -> 9 | E78: =IF(_xlfn.XLOOKUP('PREENCHIMENTO|LETIVAS'!A78,PARAMETROS!A:A,PARAMETROS!I:I)=0,"",_xlfn.XLOOKUP('PREENCHIMENTO|LETIVAS'!A78,PARAMETROS!A:A,PARAMETROS!I:I)) -> PROFESSOR REGENTE | F78: 51|2026 | G78: ESTENDIDA | H78: 5 - Quinta | I78: 20:40 às 22:10 | J78: PRÁTICA DE ENSINO: ETNOMATEMÁTICA E HISTÓRIA DA MATEMÁTICA | W78: =IF(I78<>"",2,0) -> 2
A79: SUZANA MOREIRA FERREIRA | B79: =IF(_xlfn.XLOOKUP(A79,PARAMETROS!A:A,PARAMETROS!B:B)=0,"",_xlfn.XLOOKUP(A79,PARAMETROS!A:A,PARAMETROS!B:B)) -> 012009003709 | C79: =IF(_xlfn.XLOOKUP(A79,PARAMETROS!A:A,PARAMETROS!C:C)=0,"",_xlfn.XLOOKUP(A79,PARAMETROS!A:A,PARAMETROS!C:C)) -> 20 | D79: =IF(_xlfn.XLOOKUP(A79,PARAMETROS!A:A,PARAMETROS!D:D)=0,"",_xlfn.XLOOKUP(A79,PARAMETROS!A:A,PARAMETROS!D:D)) -> 2 | E79: =IF(_xlfn.XLOOKUP('PREENCHIMENTO|LETIVAS'!A79,PARAMETROS!A:A,PARAMETROS!I:I)=0,"",_xlfn.XLOOKUP('PREENCHIMENTO|LETIVAS'!A79,PARAMETROS!A:A,PARAMETROS!I:I)) -> PROFESSOR DE ENSINO SUPERIOR EAD | F79: 51|2026 | G79: 2 | H79: 2 - Segunda | I79: 20:40 às 22:10 | J79: PERÍCIA, ARBITRAGEM E ATUÁRIA | W79: =IF(I79<>"",2,0) -> 2
A80: DANIELA FAGUNDES CARNELOS NUNES | B80: =IF(_xlfn.XLOOKUP(A80,PARAMETROS!A:A,PARAMETROS!B:B)=0,"",_xlfn.XLOOKUP(A80,PARAMETROS!A:A,PARAMETROS!B:B)) -> 012009006206 | C80: =IF(_xlfn.XLOOKUP(A80,PARAMETROS!A:A,PARAMETROS!C:C)=0,"",_xlfn.XLOOKUP(A80,PARAMETROS!A:A,PARAMETROS!C:C)) -> 12 | D80: =IF(_xlfn.XLOOKUP(A80,PARAMETROS!A:A,PARAMETROS!D:D)=0,"",_xlfn.XLOOKUP(A80,PARAMETROS!A:A,PARAMETROS!D:D)) -> 9 | E80: =IF(_xlfn.XLOOKUP('PREENCHIMENTO|LETIVAS'!A80,PARAMETROS!A:A,PARAMETROS!I:I)=0,"",_xlfn.XLOOKUP('PREENCHIMENTO|LETIVAS'!A80,PARAMETROS!A:A,PARAMETROS!I:I)) -> PROFESSOR REGENTE | F80: 51|2026 | G80: 1 | H80: 2 - Segunda | I80: 19:00 às 20:30 | J80: PLANEJAMENTO E GESTÃO DE NEGÓCIOS | W80: =IF(I80<>"",2,0) -> 2
A81: CLAUDIA CRISTINA BATISTELA FRANCISCO | B81: =IF(_xlfn.XLOOKUP(A81,PARAMETROS!A:A,PARAMETROS!B:B)=0,"",_xlfn.XLOOKUP(A81,PARAMETROS!A:A,PARAMETROS!B:B)) -> 012009003473 | C81: =IF(_xlfn.XLOOKUP(A81,PARAMETROS!A:A,PARAMETROS!C:C)=0,"",_xlfn.XLOOKUP(A81,PARAMETROS!A:A,PARAMETROS!C:C)) -> 40 | D81: =IF(_xlfn.XLOOKUP(A81,PARAMETROS!A:A,PARAMETROS!D:D)=0,"",_xlfn.XLOOKUP(A81,PARAMETROS!A:A,PARAMETROS!D:D)) -> 4 | E81: =IF(_xlfn.XLOOKUP('PREENCHIMENTO|LETIVAS'!A81,PARAMETROS!A:A,PARAMETROS!I:I)=0,"",_xlfn.XLOOKUP('PREENCHIMENTO|LETIVAS'!A81,PARAMETROS!A:A,PARAMETROS!I:I)) -> PROFESSOR DE ENSINO SUPERIOR EAD | F81: 51|2026 | G81: 1 | H81: 4 - Quarta | I81: 19:00 às 20:30 | J81: COMPORTAMENTO DO CONSUMIDOR | W81: =IF(I81<>"",2,0) -> 2
A82: CLAUDIA CRISTINA BATISTELA FRANCISCO | B82: =IF(_xlfn.XLOOKUP(A82,PARAMETROS!A:A,PARAMETROS!B:B)=0,"",_xlfn.XLOOKUP(A82,PARAMETROS!A:A,PARAMETROS!B:B)) -> 012009003473 | C82: =IF(_xlfn.XLOOKUP(A82,PARAMETROS!A:A,PARAMETROS!C:C)=0,"",_xlfn.XLOOKUP(A82,PARAMETROS!A:A,PARAMETROS!C:C)) -> 40 | D82: =IF(_xlfn.XLOOKUP(A82,PARAMETROS!A:A,PARAMETROS!D:D)=0,"",_xlfn.XLOOKUP(A82,PARAMETROS!A:A,PARAMETROS!D:D)) -> 4 | E82: =IF(_xlfn.XLOOKUP('PREENCHIMENTO|LETIVAS'!A82,PARAMETROS!A:A,PARAMETROS!I:I)=0,"",_xlfn.XLOOKUP('PREENCHIMENTO|LETIVAS'!A82,PARAMETROS!A:A,PARAMETROS!I:I)) -> PROFESSOR DE ENSINO SUPERIOR EAD | F82: 51|2026 | G82: 1 | H82: 3 - Terça | I82: 19:00 às 20:30 | J82: COMPORTAMENTO DO CONSUMIDOR | W82: =IF(I82<>"",2,0) -> 2
A83: CLAUDIA CRISTINA BATISTELA FRANCISCO | B83: =IF(_xlfn.XLOOKUP(A83,PARAMETROS!A:A,PARAMETROS!B:B)=0,"",_xlfn.XLOOKUP(A83,PARAMETROS!A:A,PARAMETROS!B:B)) -> 012009003473 | C83: =IF(_xlfn.XLOOKUP(A83,PARAMETROS!A:A,PARAMETROS!C:C)=0,"",_xlfn.XLOOKUP(A83,PARAMETROS!A:A,PARAMETROS!C:C)) -> 40 | D83: =IF(_xlfn.XLOOKUP(A83,PARAMETROS!A:A,PARAMETROS!D:D)=0,"",_xlfn.XLOOKUP(A83,PARAMETROS!A:A,PARAMETROS!D:D)) -> 4 | E83: =IF(_xlfn.XLOOKUP('PREENCHIMENTO|LETIVAS'!A83,PARAMETROS!A:A,PARAMETROS!I:I)=0,"",_xlfn.XLOOKUP('PREENCHIMENTO|LETIVAS'!A83,PARAMETROS!A:A,PARAMETROS!I:I)) -> PROFESSOR DE ENSINO SUPERIOR EAD | F83: 51|2026 | G83: 1 | H83: 4 - Quarta | I83: 19:00 às 20:30 | J83: COMPORTAMENTO DO CONSUMIDOR | W83: =IF(I83<>"",2,0) -> 2
A84: CLAUDIA CRISTINA BATISTELA FRANCISCO | B84: =IF(_xlfn.XLOOKUP(A84,PARAMETROS!A:A,PARAMETROS!B:B)=0,"",_xlfn.XLOOKUP(A84,PARAMETROS!A:A,PARAMETROS!B:B)) -> 012009003473 | C84: =IF(_xlfn.XLOOKUP(A84,PARAMETROS!A:A,PARAMETROS!C:C)=0,"",_xlfn.XLOOKUP(A84,PARAMETROS!A:A,PARAMETROS!C:C)) -> 40 | D84: =IF(_xlfn.XLOOKUP(A84,PARAMETROS!A:A,PARAMETROS!D:D)=0,"",_xlfn.XLOOKUP(A84,PARAMETROS!A:A,PARAMETROS!D:D)) -> 4 | E84: =IF(_xlfn.XLOOKUP('PREENCHIMENTO|LETIVAS'!A84,PARAMETROS!A:A,PARAMETROS!I:I)=0,"",_xlfn.XLOOKUP('PREENCHIMENTO|LETIVAS'!A84,PARAMETROS!A:A,PARAMETROS!I:I)) -> PROFESSOR DE ENSINO SUPERIOR EAD | F84: 51|2026 | G84: 2 | H84: 4 - Quarta | I84: 20:40 às 22:10 | J84: MARKETING VERDE E SOCIAL | W84: =IF(I84<>"",2,0) -> 2
A85: MAYCON VINICIUS DE SENNA RIBEIRO | B85: =IF(_xlfn.XLOOKUP(A85,PARAMETROS!A:A,PARAMETROS!B:B)=0,"",_xlfn.XLOOKUP(A85,PARAMETROS!A:A,PARAMETROS!B:B)) -> 012009003848 | C85: =IF(_xlfn.XLOOKUP(A85,PARAMETROS!A:A,PARAMETROS!C:C)=0,"",_xlfn.XLOOKUP(A85,PARAMETROS!A:A,PARAMETROS!C:C)) -> 40 | D85: =IF(_xlfn.XLOOKUP(A85,PARAMETROS!A:A,PARAMETROS!D:D)=0,"",_xlfn.XLOOKUP(A85,PARAMETROS!A:A,PARAMETROS!D:D)) -> 4 | E85: =IF(_xlfn.XLOOKUP('PREENCHIMENTO|LETIVAS'!A85,PARAMETROS!A:A,PARAMETROS!I:I)=0,"",_xlfn.XLOOKUP('PREENCHIMENTO|LETIVAS'!A85,PARAMETROS!A:A,PARAMETROS!I:I)) -> PROFESSOR DE ENSINO SUPERIOR EAD | F85: 51|2026 | G85: ESTENDIDA | H85: 4 - Quarta | J85: QUÍMICA E ANÁLISES QUÍMICAS EM ALIMENTOS | K85: Horário não informado ainda no mapa pedagógico. | W85: =IF(I85<>"",2,0) -> 0
A86: MYLLENA MARCELA GANZERT FERNANDES | B86: =IF(_xlfn.XLOOKUP(A86,PARAMETROS!A:A,PARAMETROS!B:B)=0,"",_xlfn.XLOOKUP(A86,PARAMETROS!A:A,PARAMETROS!B:B)) -> 012009006279 | C86: =IF(_xlfn.XLOOKUP(A86,PARAMETROS!A:A,PARAMETROS!C:C)=0,"",_xlfn.XLOOKUP(A86,PARAMETROS!A:A,PARAMETROS!C:C)) -> 40 | D86: =IF(_xlfn.XLOOKUP(A86,PARAMETROS!A:A,PARAMETROS!D:D)=0,"",_xlfn.XLOOKUP(A86,PARAMETROS!A:A,PARAMETROS!D:D)) -> 20 | E86: =IF(_xlfn.XLOOKUP('PREENCHIMENTO|LETIVAS'!A86,PARAMETROS!A:A,PARAMETROS!I:I)=0,"",_xlfn.XLOOKUP('PREENCHIMENTO|LETIVAS'!A86,PARAMETROS!A:A,PARAMETROS!I:I)) -> PROFESSOR REGENTE | F86: 51|2026 | G86: 2 | H86: 3 - Terça | I86: 20:40 às 22:10 | J86: NEUROCIÊNCIA DA FELICIDADE E INTUIÇÃO | W86: =IF(I86<>"",2,0) -> 2
A87: MYLLENA MARCELA GANZERT FERNANDES | B87: =IF(_xlfn.XLOOKUP(A87,PARAMETROS!A:A,PARAMETROS!B:B)=0,"",_xlfn.XLOOKUP(A87,PARAMETROS!A:A,PARAMETROS!B:B)) -> 012009006279 | C87: =IF(_xlfn.XLOOKUP(A87,PARAMETROS!A:A,PARAMETROS!C:C)=0,"",_xlfn.XLOOKUP(A87,PARAMETROS!A:A,PARAMETROS!C:C)) -> 40 | D87: =IF(_xlfn.XLOOKUP(A87,PARAMETROS!A:A,PARAMETROS!D:D)=0,"",_xlfn.XLOOKUP(A87,PARAMETROS!A:A,PARAMETROS!D:D)) -> 20 | E87: =IF(_xlfn.XLOOKUP('PREENCHIMENTO|LETIVAS'!A87,PARAMETROS!A:A,PARAMETROS!I:I)=0,"",_xlfn.XLOOKUP('PREENCHIMENTO|LETIVAS'!A87,PARAMETROS!A:A,PARAMETROS!I:I)) -> PROFESSOR REGENTE | F87: 51|2026 | G87: 2 | H87: 3 - Terça | I87: 19:00 às 20:30 | J87: SAÚDE INTEGRATIVA | W87: =IF(I87<>"",2,0) -> 2
A88: MYLLENA MARCELA GANZERT FERNANDES | B88: =IF(_xlfn.XLOOKUP(A88,PARAMETROS!A:A,PARAMETROS!B:B)=0,"",_xlfn.XLOOKUP(A88,PARAMETROS!A:A,PARAMETROS!B:B)) -> 012009006279 | C88: =IF(_xlfn.XLOOKUP(A88,PARAMETROS!A:A,PARAMETROS!C:C)=0,"",_xlfn.XLOOKUP(A88,PARAMETROS!A:A,PARAMETROS!C:C)) -> 40 | D88: =IF(_xlfn.XLOOKUP(A88,PARAMETROS!A:A,PARAMETROS!D:D)=0,"",_xlfn.XLOOKUP(A88,PARAMETROS!A:A,PARAMETROS!D:D)) -> 20 | E88: =IF(_xlfn.XLOOKUP('PREENCHIMENTO|LETIVAS'!A88,PARAMETROS!A:A,PARAMETROS!I:I)=0,"",_xlfn.XLOOKUP('PREENCHIMENTO|LETIVAS'!A88,PARAMETROS!A:A,PARAMETROS!I:I)) -> PROFESSOR REGENTE | F88: 51|2026 | G88: ESTENDIDA | H88: 4 - Quarta | I88: 20:40 às 22:10 | J88: AVALIAÇÃO, DIAGNÓSTICO E TERAPÊUTICA | W88: =IF(I88<>"",2,0) -> 2
A89: MYLLENA MARCELA GANZERT FERNANDES | B89: =IF(_xlfn.XLOOKUP(A89,PARAMETROS!A:A,PARAMETROS!B:B)=0,"",_xlfn.XLOOKUP(A89,PARAMETROS!A:A,PARAMETROS!B:B)) -> 012009006279 | C89: =IF(_xlfn.XLOOKUP(A89,PARAMETROS!A:A,PARAMETROS!C:C)=0,"",_xlfn.XLOOKUP(A89,PARAMETROS!A:A,PARAMETROS!C:C)) -> 40 | D89: =IF(_xlfn.XLOOKUP(A89,PARAMETROS!A:A,PARAMETROS!D:D)=0,"",_xlfn.XLOOKUP(A89,PARAMETROS!A:A,PARAMETROS!D:D)) -> 20 | E89: =IF(_xlfn.XLOOKUP('PREENCHIMENTO|LETIVAS'!A89,PARAMETROS!A:A,PARAMETROS!I:I)=0,"",_xlfn.XLOOKUP('PREENCHIMENTO|LETIVAS'!A89,PARAMETROS!A:A,PARAMETROS!I:I)) -> PROFESSOR REGENTE | F89: 51|2026 | G89: ESTENDIDA | H89: 4 - Quarta | I89: 19:00 às 20:30 | J89: INTRODUÇÃO A TERAPIA OCUPACIONAL E BIOÉTICA | W89: =IF(I89<>"",2,0) -> 2
A90: MURILO DE OLIVEIRA LAZARIN | B90: =IF(_xlfn.XLOOKUP(A90,PARAMETROS!A:A,PARAMETROS!B:B)=0,"",_xlfn.XLOOKUP(A90,PARAMETROS!A:A,PARAMETROS!B:B)) -> 012009006217 | C90: =IF(_xlfn.XLOOKUP(A90,PARAMETROS!A:A,PARAMETROS!C:C)=0,"",_xlfn.XLOOKUP(A90,PARAMETROS!A:A,PARAMETROS!C:C)) -> 12 | D90: =IF(_xlfn.XLOOKUP(A90,PARAMETROS!A:A,PARAMETROS!D:D)=0,"",_xlfn.XLOOKUP(A90,PARAMETROS!A:A,PARAMETROS!D:D)) -> 9 | E90: =IF(_xlfn.XLOOKUP('PREENCHIMENTO|LETIVAS'!A90,PARAMETROS!A:A,PARAMETROS!I:I)=0,"",_xlfn.XLOOKUP('PREENCHIMENTO|LETIVAS'!A90,PARAMETROS!A:A,PARAMETROS!I:I)) -> PROFESSOR REGENTE | F90: 51|2026 | G90: 1 | H90: 5 - Quinta | I90: 19:00 às 20:30 | J90: CINEMA CONTEMPORÂNEO | W90: =IF(I90<>"",2,0) -> 2
A91: FERNANDA LEANDRO DOMANSKI | B91: =IF(_xlfn.XLOOKUP(A91,PARAMETROS!A:A,PARAMETROS!B:B)=0,"",_xlfn.XLOOKUP(A91,PARAMETROS!A:A,PARAMETROS!B:B)) -> 012009006187 | C91: =IF(_xlfn.XLOOKUP(A91,PARAMETROS!A:A,PARAMETROS!C:C)=0,"",_xlfn.XLOOKUP(A91,PARAMETROS!A:A,PARAMETROS!C:C)) -> 12 | D91: =IF(_xlfn.XLOOKUP(A91,PARAMETROS!A:A,PARAMETROS!D:D)=0,"",_xlfn.XLOOKUP(A91,PARAMETROS!A:A,PARAMETROS!D:D)) -> 9 | E91: =IF(_xlfn.XLOOKUP('PREENCHIMENTO|LETIVAS'!A91,PARAMETROS!A:A,PARAMETROS!I:I)=0,"",_xlfn.XLOOKUP('PREENCHIMENTO|LETIVAS'!A91,PARAMETROS!A:A,PARAMETROS!I:I)) -> PROFESSOR REGENTE | F91: 51|2026 | G91: 2 | H91: 4 - Quarta | I91: 20:40 às 22:10 | J91: PRÁTICAS CAMBIAIS E FINANCEIRAS INTERNACIONAIS | W91: =IF(I91<>"",2,0) -> 2
A92: MARTA CIRERA | B92: =IF(_xlfn.XLOOKUP(A92,PARAMETROS!A:A,PARAMETROS!B:B)=0,"",_xlfn.XLOOKUP(A92,PARAMETROS!A:A,PARAMETROS!B:B)) -> 012009005581 | C92: =IF(_xlfn.XLOOKUP(A92,PARAMETROS!A:A,PARAMETROS!C:C)=0,"",_xlfn.XLOOKUP(A92,PARAMETROS!A:A,PARAMETROS!C:C)) -> 40 | D92: =IF(_xlfn.XLOOKUP(A92,PARAMETROS!A:A,PARAMETROS!D:D)=0,"",_xlfn.XLOOKUP(A92,PARAMETROS!A:A,PARAMETROS!D:D)) -> 4 | E92: =IF(_xlfn.XLOOKUP('PREENCHIMENTO|LETIVAS'!A92,PARAMETROS!A:A,PARAMETROS!I:I)=0,"",_xlfn.XLOOKUP('PREENCHIMENTO|LETIVAS'!A92,PARAMETROS!A:A,PARAMETROS!I:I)) -> PROFESSOR DE ENSINO SUPERIOR EAD | F92: 51|2026 | G92: 1 | H92: 3 - Terça | I92: 19:00 às 20:30 | J92: EDUCAÇÃO, DIREITOS HUMANOS E CIDADANIA | W92: =IF(I92<>"",2,0) -> 2
A93: MARTA CIRERA | B93: =IF(_xlfn.XLOOKUP(A93,PARAMETROS!A:A,PARAMETROS!B:B)=0,"",_xlfn.XLOOKUP(A93,PARAMETROS!A:A,PARAMETROS!B:B)) -> 012009005581 | C93: =IF(_xlfn.XLOOKUP(A93,PARAMETROS!A:A,PARAMETROS!C:C)=0,"",_xlfn.XLOOKUP(A93,PARAMETROS!A:A,PARAMETROS!C:C)) -> 40 | D93: =IF(_xlfn.XLOOKUP(A93,PARAMETROS!A:A,PARAMETROS!D:D)=0,"",_xlfn.XLOOKUP(A93,PARAMETROS!A:A,PARAMETROS!D:D)) -> 4 | E93: =IF(_xlfn.XLOOKUP('PREENCHIMENTO|LETIVAS'!A93,PARAMETROS!A:A,PARAMETROS!I:I)=0,"",_xlfn.XLOOKUP('PREENCHIMENTO|LETIVAS'!A93,PARAMETROS!A:A,PARAMETROS!I:I)) -> PROFESSOR DE ENSINO SUPERIOR EAD | F93: 51|2026 | G93: 2 | H93: 3 - Terça | I93: 20:40 às 22:10 | J93: GESTÃO EM PROGRAMAS E PROJETOS SOCIAIS | W93: =IF(I93<>"",2,0) -> 2
A94: CAROLINE PREVIATO SOUZA | B94: =IF(_xlfn.XLOOKUP(A94,PARAMETROS!A:A,PARAMETROS!B:B)=0,"",_xlfn.XLOOKUP(A94,PARAMETROS!A:A,PARAMETROS!B:B)) -> 012009004488 | C94: =IF(_xlfn.XLOOKUP(A94,PARAMETROS!A:A,PARAMETROS!C:C)=0,"",_xlfn.XLOOKUP(A94,PARAMETROS!A:A,PARAMETROS!C:C)) -> 40 | D94: =IF(_xlfn.XLOOKUP(A94,PARAMETROS!A:A,PARAMETROS!D:D)=0,"",_xlfn.XLOOKUP(A94,PARAMETROS!A:A,PARAMETROS!D:D)) -> 4 | E94: =IF(_xlfn.XLOOKUP('PREENCHIMENTO|LETIVAS'!A94,PARAMETROS!A:A,PARAMETROS!I:I)=0,"",_xlfn.XLOOKUP('PREENCHIMENTO|LETIVAS'!A94,PARAMETROS!A:A,PARAMETROS!I:I)) -> PROFESSOR DE ENSINO SUPERIOR EAD | F94: 51|2026 | G94: 2 | H94: 3 - Terça | I94: 19:00 às 20:30 | J94: ESTADO E PROTEÇÃO SOCIAL | W94: =IF(I94<>"",2,0) -> 2
A95: HILKA PELIZZA VIER MACHADO | B95: =IF(_xlfn.XLOOKUP(A95,PARAMETROS!A:A,PARAMETROS!B:B)=0,"",_xlfn.XLOOKUP(A95,PARAMETROS!A:A,PARAMETROS!B:B)) -> 012009003546 | C95: =IF(_xlfn.XLOOKUP(A95,PARAMETROS!A:A,PARAMETROS!C:C)=0,"",_xlfn.XLOOKUP(A95,PARAMETROS!A:A,PARAMETROS!C:C)) | D95: =IF(_xlfn.XLOOKUP(A95,PARAMETROS!A:A,PARAMETROS!D:D)=0,"",_xlfn.XLOOKUP(A95,PARAMETROS!A:A,PARAMETROS!D:D)) | E95: =IF(_xlfn.XLOOKUP('PREENCHIMENTO|LETIVAS'!A95,PARAMETROS!A:A,PARAMETROS!I:I)=0,"",_xlfn.XLOOKUP('PREENCHIMENTO|LETIVAS'!A95,PARAMETROS!A:A,PARAMETROS!I:I)) -> PROFESSOR DE ENSINO SUPERIOR PRESENCIAL | F95: 51|2026 | G95: 2 | H95: 4 - Quarta | I95: 19:00 às 20:30 | J95: NEGÓCIOS INOVADORES E STARTUPS | W95: =IF(I95<>"",2,0) -> 2
A96: GABRIEL COUTINHO CALVI | B96: =IF(_xlfn.XLOOKUP(A96,PARAMETROS!A:A,PARAMETROS!B:B)=0,"",_xlfn.XLOOKUP(A96,PARAMETROS!A:A,PARAMETROS!B:B)) -> 012009005578 | C96: =IF(_xlfn.XLOOKUP(A96,PARAMETROS!A:A,PARAMETROS!C:C)=0,"",_xlfn.XLOOKUP(A96,PARAMETROS!A:A,PARAMETROS!C:C)) -> 20 | D96: =IF(_xlfn.XLOOKUP(A96,PARAMETROS!A:A,PARAMETROS!D:D)=0,"",_xlfn.XLOOKUP(A96,PARAMETROS!A:A,PARAMETROS!D:D)) -> 2 | E96: =IF(_xlfn.XLOOKUP('PREENCHIMENTO|LETIVAS'!A96,PARAMETROS!A:A,PARAMETROS!I:I)=0,"",_xlfn.XLOOKUP('PREENCHIMENTO|LETIVAS'!A96,PARAMETROS!A:A,PARAMETROS!I:I)) -> PROFESSOR DE ENSINO SUPERIOR EAD | F96: 51|2026 | G96: 2 | H96: 5 - Quinta | I96: 19:00 às 20:30 | J96: ARTE, COMUNICAÇÃO E NOVAS MÍDIAS | W96: =IF(I96<>"",2,0) -> 2
A97: MARIANA BARRETO POLTRONIERI | B97: =IF(_xlfn.XLOOKUP(A97,PARAMETROS!A:A,PARAMETROS!B:B)=0,"",_xlfn.XLOOKUP(A97,PARAMETROS!A:A,PARAMETROS!B:B)) -> 012009006212 | C97: =IF(_xlfn.XLOOKUP(A97,PARAMETROS!A:A,PARAMETROS!C:C)=0,"",_xlfn.XLOOKUP(A97,PARAMETROS!A:A,PARAMETROS!C:C)) -> 12 | D97: =IF(_xlfn.XLOOKUP(A97,PARAMETROS!A:A,PARAMETROS!D:D)=0,"",_xlfn.XLOOKUP(A97,PARAMETROS!A:A,PARAMETROS!D:D)) -> 9 | E97: =IF(_xlfn.XLOOKUP('PREENCHIMENTO|LETIVAS'!A97,PARAMETROS!A:A,PARAMETROS!I:I)=0,"",_xlfn.XLOOKUP('PREENCHIMENTO|LETIVAS'!A97,PARAMETROS!A:A,PARAMETROS!I:I)) -> PROFESSOR REGENTE | F97: 51|2026 | G97: 1 | H97: 5 - Quinta | I97: 20:40 às 22:10 | J97: CORPO, DANÇA, EXPRESSÃO E MOVIMENTO | W97: =IF(I97<>"",2,0) -> 2
A98: MARIANA BARRETO POLTRONIERI | B98: =IF(_xlfn.XLOOKUP(A98,PARAMETROS!A:A,PARAMETROS!B:B)=0,"",_xlfn.XLOOKUP(A98,PARAMETROS!A:A,PARAMETROS!B:B)) -> 012009006212 | C98: =IF(_xlfn.XLOOKUP(A98,PARAMETROS!A:A,PARAMETROS!C:C)=0,"",_xlfn.XLOOKUP(A98,PARAMETROS!A:A,PARAMETROS!C:C)) -> 12 | D98: =IF(_xlfn.XLOOKUP(A98,PARAMETROS!A:A,PARAMETROS!D:D)=0,"",_xlfn.XLOOKUP(A98,PARAMETROS!A:A,PARAMETROS!D:D)) -> 9 | E98: =IF(_xlfn.XLOOKUP('PREENCHIMENTO|LETIVAS'!A98,PARAMETROS!A:A,PARAMETROS!I:I)=0,"",_xlfn.XLOOKUP('PREENCHIMENTO|LETIVAS'!A98,PARAMETROS!A:A,PARAMETROS!I:I)) -> PROFESSOR REGENTE | F98: 51|2026 | G98: 2 | H98: 5 - Quinta | I98: 19:00 às 20:30 | J98: DANÇAS FOLCLÓRICAS E AS PROPOSIÇÕES COREOGRÁFICAS | W98: =IF(I98<>"",2,0) -> 2
A99: RENATA MARIANE DE SOUZA PROVENSI | B99: =IF(_xlfn.XLOOKUP(A99,PARAMETROS!A:A,PARAMETROS!B:B)=0,"",_xlfn.XLOOKUP(A99,PARAMETROS!A:A,PARAMETROS!B:B)) -> 012009006282 | C99: =IF(_xlfn.XLOOKUP(A99,PARAMETROS!A:A,PARAMETROS!C:C)=0,"",_xlfn.XLOOKUP(A99,PARAMETROS!A:A,PARAMETROS!C:C)) -> 12 | D99: =IF(_xlfn.XLOOKUP(A99,PARAMETROS!A:A,PARAMETROS!D:D)=0,"",_xlfn.XLOOKUP(A99,PARAMETROS!A:A,PARAMETROS!D:D)) -> 9 | E99: =IF(_xlfn.XLOOKUP('PREENCHIMENTO|LETIVAS'!A99,PARAMETROS!A:A,PARAMETROS!I:I)=0,"",_xlfn.XLOOKUP('PREENCHIMENTO|LETIVAS'!A99,PARAMETROS!A:A,PARAMETROS!I:I)) -> PROFESSOR REGENTE | F99: 51|2026 | G99: ESTENDIDA | H99: 2 - Segunda | I99: 19:00 às 20:30 | J99: ESTATÍSTICA E PROBABILIDADE | W99: =IF(I99<>"",2,0) -> 2
A100: RENATA MARIANE DE SOUZA PROVENSI | B100: =IF(_xlfn.XLOOKUP(A100,PARAMETROS!A:A,PARAMETROS!B:B)=0,"",_xlfn.XLOOKUP(A100,PARAMETROS!A:A,PARAMETROS!B:B)) -> 012009006282 | C100: =IF(_xlfn.XLOOKUP(A100,PARAMETROS!A:A,PARAMETROS!C:C)=0,"",_xlfn.XLOOKUP(A100,PARAMETROS!A:A,PARAMETROS!C:C)) -> 12 | D100: =IF(_xlfn.XLOOKUP(A100,PARAMETROS!A:A,PARAMETROS!D:D)=0,"",_xlfn.XLOOKUP(A100,PARAMETROS!A:A,PARAMETROS!D:D)) -> 9 | E100: =IF(_xlfn.XLOOKUP('PREENCHIMENTO|LETIVAS'!A100,PARAMETROS!A:A,PARAMETROS!I:I)=0,"",_xlfn.XLOOKUP('PREENCHIMENTO|LETIVAS'!A100,PARAMETROS!A:A,PARAMETROS!I:I)) -> PROFESSOR REGENTE | F100: 51|2026 | G100: ESTENDIDA | H100: 2 - Segunda | I100: 20:40 às 22:10 | J100: FUNDAMENTOS DE BOTÂNICA | W100: =IF(I100<>"",2,0) -> 2
A101: ISABELA ANTUNES DE SOUZA LIMA | B101: =IF(_xlfn.XLOOKUP(A101,PARAMETROS!A:A,PARAMETROS!B:B)=0,"",_xlfn.XLOOKUP(A101,PARAMETROS!A:A,PARAMETROS!B:B)) -> 012009006215 | C101: =IF(_xlfn.XLOOKUP(A101,PARAMETROS!A:A,PARAMETROS!C:C)=0,"",_xlfn.XLOOKUP(A101,PARAMETROS!A:A,PARAMETROS!C:C)) -> 12 | D101: =IF(_xlfn.XLOOKUP(A101,PARAMETROS!A:A,PARAMETROS!D:D)=0,"",_xlfn.XLOOKUP(A101,PARAMETROS!A:A,PARAMETROS!D:D)) -> 9 | E101: =IF(_xlfn.XLOOKUP('PREENCHIMENTO|LETIVAS'!A101,PARAMETROS!A:A,PARAMETROS!I:I)=0,"",_xlfn.XLOOKUP('PREENCHIMENTO|LETIVAS'!A101,PARAMETROS!A:A,PARAMETROS!I:I)) -> PROFESSOR REGENTE | F101: 51|2026 | G101: ESTENDIDA | H101: 2 - Segunda | I101: 19:00 às 20:30 | J101: INTRODUÇÃO À ENGENHARIA | W101: =IF(I101<>"",2,0) -> 2
A102: ISABELA ANTUNES DE SOUZA LIMA | B102: =IF(_xlfn.XLOOKUP(A102,PARAMETROS!A:A,PARAMETROS!B:B)=0,"",_xlfn.XLOOKUP(A102,PARAMETROS!A:A,PARAMETROS!B:B)) -> 012009006215 | C102: =IF(_xlfn.XLOOKUP(A102,PARAMETROS!A:A,PARAMETROS!C:C)=0,"",_xlfn.XLOOKUP(A102,PARAMETROS!A:A,PARAMETROS!C:C)) -> 12 | D102: =IF(_xlfn.XLOOKUP(A102,PARAMETROS!A:A,PARAMETROS!D:D)=0,"",_xlfn.XLOOKUP(A102,PARAMETROS!A:A,PARAMETROS!D:D)) -> 9 | E102: =IF(_xlfn.XLOOKUP('PREENCHIMENTO|LETIVAS'!A102,PARAMETROS!A:A,PARAMETROS!I:I)=0,"",_xlfn.XLOOKUP('PREENCHIMENTO|LETIVAS'!A102,PARAMETROS!A:A,PARAMETROS!I:I)) -> PROFESSOR REGENTE | F102: 51|2026 | G102: ESTENDIDA | H102: 2 - Segunda | I102: 20:40 às 22:10 | J102: MAPEAMENTO DE PROCESSOS | W102: =IF(I102<>"",2,0) -> 2
A103: HELOISE BEATRIZ QUESADA | B103: =IF(_xlfn.XLOOKUP(A103,PARAMETROS!A:A,PARAMETROS!B:B)=0,"",_xlfn.XLOOKUP(A103,PARAMETROS!A:A,PARAMETROS!B:B)) -> 012009006191 | C103: =IF(_xlfn.XLOOKUP(A103,PARAMETROS!A:A,PARAMETROS!C:C)=0,"",_xlfn.XLOOKUP(A103,PARAMETROS!A:A,PARAMETROS!C:C)) -> 40 | D103: =IF(_xlfn.XLOOKUP(A103,PARAMETROS!A:A,PARAMETROS!D:D)=0,"",_xlfn.XLOOKUP(A103,PARAMETROS!A:A,PARAMETROS!D:D)) -> 20 | E103: =IF(_xlfn.XLOOKUP('PREENCHIMENTO|LETIVAS'!A103,PARAMETROS!A:A,PARAMETROS!I:I)=0,"",_xlfn.XLOOKUP('PREENCHIMENTO|LETIVAS'!A103,PARAMETROS!A:A,PARAMETROS!I:I)) -> PROFESSOR REGENTE | F103: 51|2026 | G103: ESTENDIDA | H103: 2 - Segunda | I103: 19:00 às 20:30 | J103: QUÍMICA INORGÂNICA E ORGÂNICA | W103: =IF(I103<>"",2,0) -> 2
A104: HELOISE BEATRIZ QUESADA | B104: =IF(_xlfn.XLOOKUP(A104,PARAMETROS!A:A,PARAMETROS!B:B)=0,"",_xlfn.XLOOKUP(A104,PARAMETROS!A:A,PARAMETROS!B:B)) -> 012009006191 | C104: =IF(_xlfn.XLOOKUP(A104,PARAMETROS!A:A,PARAMETROS!C:C)=0,"",_xlfn.XLOOKUP(A104,PARAMETROS!A:A,PARAMETROS!C:C)) -> 40 | D104: =IF(_xlfn.XLOOKUP(A104,PARAMETROS!A:A,PARAMETROS!D:D)=0,"",_xlfn.XLOOKUP(A104,PARAMETROS!A:A,PARAMETROS!D:D)) -> 20 | E104: =IF(_xlfn.XLOOKUP('PREENCHIMENTO|LETIVAS'!A104,PARAMETROS!A:A,PARAMETROS!I:I)=0,"",_xlfn.XLOOKUP('PREENCHIMENTO|LETIVAS'!A104,PARAMETROS!A:A,PARAMETROS!I:I)) -> PROFESSOR REGENTE | F104: 51|2026 | G104: ESTENDIDA | H104: 2 - Segunda | I104: 20:40 às 22:10 | J104: ENERGIA HIDRÁULICA E SISTEMAS DE GERAÇÃO HIDRELÉTRICA | W104: =IF(I104<>"",2,0) -> 2
A105: ALEXANDRE AMADO DE MOURA | B105: =IF(_xlfn.XLOOKUP(A105,PARAMETROS!A:A,PARAMETROS!B:B)=0,"",_xlfn.XLOOKUP(A105,PARAMETROS!A:A,PARAMETROS!B:B)) -> 012009006280 | C105: =IF(_xlfn.XLOOKUP(A105,PARAMETROS!A:A,PARAMETROS!C:C)=0,"",_xlfn.XLOOKUP(A105,PARAMETROS!A:A,PARAMETROS!C:C)) -> 12 | D105: =IF(_xlfn.XLOOKUP(A105,PARAMETROS!A:A,PARAMETROS!D:D)=0,"",_xlfn.XLOOKUP(A105,PARAMETROS!A:A,PARAMETROS!D:D)) -> 9 | E105: =IF(_xlfn.XLOOKUP('PREENCHIMENTO|LETIVAS'!A105,PARAMETROS!A:A,PARAMETROS!I:I)=0,"",_xlfn.XLOOKUP('PREENCHIMENTO|LETIVAS'!A105,PARAMETROS!A:A,PARAMETROS!I:I)) -> PROFESSOR REGENTE | F105: 51|2026 | G105: ESTENDIDA | H105: 2 - Segunda | I105: 20:40 às 22:10 | J105: FUNDAÇÕES E OBRAS DE TERRA | W105: =IF(I105<>"",2,0) -> 2
A106: ALEXANDRE AMADO DE MOURA | B106: =IF(_xlfn.XLOOKUP(A106,PARAMETROS!A:A,PARAMETROS!B:B)=0,"",_xlfn.XLOOKUP(A106,PARAMETROS!A:A,PARAMETROS!B:B)) -> 012009006280 | C106: =IF(_xlfn.XLOOKUP(A106,PARAMETROS!A:A,PARAMETROS!C:C)=0,"",_xlfn.XLOOKUP(A106,PARAMETROS!A:A,PARAMETROS!C:C)) -> 12 | D106: =IF(_xlfn.XLOOKUP(A106,PARAMETROS!A:A,PARAMETROS!D:D)=0,"",_xlfn.XLOOKUP(A106,PARAMETROS!A:A,PARAMETROS!D:D)) -> 9 | E106: =IF(_xlfn.XLOOKUP('PREENCHIMENTO|LETIVAS'!A106,PARAMETROS!A:A,PARAMETROS!I:I)=0,"",_xlfn.XLOOKUP('PREENCHIMENTO|LETIVAS'!A106,PARAMETROS!A:A,PARAMETROS!I:I)) -> PROFESSOR REGENTE | F106: 51|2026 | G106: ESTENDIDA | H106: 2 - Segunda | I106: 19:00 às 20:30 | J106: TEORIA DAS ESTRUTURAS | W106: =IF(I106<>"",2,0) -> 2
A107: MARGARETE CAMPOS VIEIRA | B107: =IF(_xlfn.XLOOKUP(A107,PARAMETROS!A:A,PARAMETROS!B:B)=0,"",_xlfn.XLOOKUP(A107,PARAMETROS!A:A,PARAMETROS!B:B)) -> 012009006203 | C107: =IF(_xlfn.XLOOKUP(A107,PARAMETROS!A:A,PARAMETROS!C:C)=0,"",_xlfn.XLOOKUP(A107,PARAMETROS!A:A,PARAMETROS!C:C)) -> 12 | D107: =IF(_xlfn.XLOOKUP(A107,PARAMETROS!A:A,PARAMETROS!D:D)=0,"",_xlfn.XLOOKUP(A107,PARAMETROS!A:A,PARAMETROS!D:D)) -> 9 | E107: =IF(_xlfn.XLOOKUP('PREENCHIMENTO|LETIVAS'!A107,PARAMETROS!A:A,PARAMETROS!I:I)=0,"",_xlfn.XLOOKUP('PREENCHIMENTO|LETIVAS'!A107,PARAMETROS!A:A,PARAMETROS!I:I)) -> PROFESSOR REGENTE | F107: 51|2026 | G107: 1 | H107: 4 - Quarta | I107: 20:40 às 22:10 | J107: ECONOMIA INDUSTRIAL | W107: =IF(I107<>"",2,0) -> 2
A108: MARGARETE CAMPOS VIEIRA | B108: =IF(_xlfn.XLOOKUP(A108,PARAMETROS!A:A,PARAMETROS!B:B)=0,"",_xlfn.XLOOKUP(A108,PARAMETROS!A:A,PARAMETROS!B:B)) -> 012009006203 | C108: =IF(_xlfn.XLOOKUP(A108,PARAMETROS!A:A,PARAMETROS!C:C)=0,"",_xlfn.XLOOKUP(A108,PARAMETROS!A:A,PARAMETROS!C:C)) -> 12 | D108: =IF(_xlfn.XLOOKUP(A108,PARAMETROS!A:A,PARAMETROS!D:D)=0,"",_xlfn.XLOOKUP(A108,PARAMETROS!A:A,PARAMETROS!D:D)) -> 9 | E108: =IF(_xlfn.XLOOKUP('PREENCHIMENTO|LETIVAS'!A108,PARAMETROS!A:A,PARAMETROS!I:I)=0,"",_xlfn.XLOOKUP('PREENCHIMENTO|LETIVAS'!A108,PARAMETROS!A:A,PARAMETROS!I:I)) -> PROFESSOR REGENTE | F108: 51|2026 | G108: 2 | H108: 4 - Quarta | I108: 20:40 às 22:10 | J108: MICROECONOMIA II | W108: =IF(I108<>"",2,0) -> 2
A109: CARLA FABIANA DE ANDRADE GONCALVES IORI | B109: =IF(_xlfn.XLOOKUP(A109,PARAMETROS!A:A,PARAMETROS!B:B)=0,"",_xlfn.XLOOKUP(A109,PARAMETROS!A:A,PARAMETROS!B:B)) -> 012009003517 | C109: =IF(_xlfn.XLOOKUP(A109,PARAMETROS!A:A,PARAMETROS!C:C)=0,"",_xlfn.XLOOKUP(A109,PARAMETROS!A:A,PARAMETROS!C:C)) -> 40 | D109: =IF(_xlfn.XLOOKUP(A109,PARAMETROS!A:A,PARAMETROS!D:D)=0,"",_xlfn.XLOOKUP(A109,PARAMETROS!A:A,PARAMETROS!D:D)) -> 4 | E109: =IF(_xlfn.XLOOKUP('PREENCHIMENTO|LETIVAS'!A109,PARAMETROS!A:A,PARAMETROS!I:I)=0,"",_xlfn.XLOOKUP('PREENCHIMENTO|LETIVAS'!A109,PARAMETROS!A:A,PARAMETROS!I:I)) -> PROFESSOR DE ENSINO SUPERIOR EAD | F109: 51|2026 | G109: 2 | H109: 4 - Quarta | I109: 19:00 às 20:30 | J109: FORMAÇÃO ECONÔMICA DO BRASIL | W109: =IF(I109<>"",2,0) -> 2
A110: CARLA FABIANA DE ANDRADE GONCALVES IORI | B110: =IF(_xlfn.XLOOKUP(A110,PARAMETROS!A:A,PARAMETROS!B:B)=0,"",_xlfn.XLOOKUP(A110,PARAMETROS!A:A,PARAMETROS!B:B)) -> 012009003517 | C110: =IF(_xlfn.XLOOKUP(A110,PARAMETROS!A:A,PARAMETROS!C:C)=0,"",_xlfn.XLOOKUP(A110,PARAMETROS!A:A,PARAMETROS!C:C)) -> 40 | D110: =IF(_xlfn.XLOOKUP(A110,PARAMETROS!A:A,PARAMETROS!D:D)=0,"",_xlfn.XLOOKUP(A110,PARAMETROS!A:A,PARAMETROS!D:D)) -> 4 | E110: =IF(_xlfn.XLOOKUP('PREENCHIMENTO|LETIVAS'!A110,PARAMETROS!A:A,PARAMETROS!I:I)=0,"",_xlfn.XLOOKUP('PREENCHIMENTO|LETIVAS'!A110,PARAMETROS!A:A,PARAMETROS!I:I)) -> PROFESSOR DE ENSINO SUPERIOR EAD | F110: 51|2026 | G110: 2 | H110: 4 - Quarta | I110: 20:40 às 22:10 | J110: HISTÓRIA ECONÔMICA GERAL | W110: =IF(I110<>"",2,0) -> 2
A111: INDIANARA PAULA PINHEIRO FERMINO | B111: =IF(_xlfn.XLOOKUP(A111,PARAMETROS!A:A,PARAMETROS!B:B)=0,"",_xlfn.XLOOKUP(A111,PARAMETROS!A:A,PARAMETROS!B:B)) -> 012009006257 | C111: =IF(_xlfn.XLOOKUP(A111,PARAMETROS!A:A,PARAMETROS!C:C)=0,"",_xlfn.XLOOKUP(A111,PARAMETROS!A:A,PARAMETROS!C:C)) -> 12 | D111: =IF(_xlfn.XLOOKUP(A111,PARAMETROS!A:A,PARAMETROS!D:D)=0,"",_xlfn.XLOOKUP(A111,PARAMETROS!A:A,PARAMETROS!D:D)) -> 9 | E111: =IF(_xlfn.XLOOKUP('PREENCHIMENTO|LETIVAS'!A111,PARAMETROS!A:A,PARAMETROS!I:I)=0,"",_xlfn.XLOOKUP('PREENCHIMENTO|LETIVAS'!A111,PARAMETROS!A:A,PARAMETROS!I:I)) -> PROFESSOR REGENTE | F111: 51|2026 | G111: 1 | H111: 2 - Segunda | I111: 20:40 às 22:10 | J111: COSMETOLOGIA | W111: =IF(I111<>"",2,0) -> 2
A112: INDIANARA PAULA PINHEIRO FERMINO | B112: =IF(_xlfn.XLOOKUP(A112,PARAMETROS!A:A,PARAMETROS!B:B)=0,"",_xlfn.XLOOKUP(A112,PARAMETROS!A:A,PARAMETROS!B:B)) -> 012009006257 | C112: =IF(_xlfn.XLOOKUP(A112,PARAMETROS!A:A,PARAMETROS!C:C)=0,"",_xlfn.XLOOKUP(A112,PARAMETROS!A:A,PARAMETROS!C:C)) -> 12 | D112: =IF(_xlfn.XLOOKUP(A112,PARAMETROS!A:A,PARAMETROS!D:D)=0,"",_xlfn.XLOOKUP(A112,PARAMETROS!A:A,PARAMETROS!D:D)) -> 9 | E112: =IF(_xlfn.XLOOKUP('PREENCHIMENTO|LETIVAS'!A112,PARAMETROS!A:A,PARAMETROS!I:I)=0,"",_xlfn.XLOOKUP('PREENCHIMENTO|LETIVAS'!A112,PARAMETROS!A:A,PARAMETROS!I:I)) -> PROFESSOR REGENTE | F112: 51|2026 | G112: 2 | H112: 2 - Segunda | I112: 19:00 às 20:30 | J112: TERAPIAS COLETIVAS | W112: =IF(I112<>"",2,0) -> 2
A113: HEVILA MARIA VIEIRA RUY | B113: =IF(_xlfn.XLOOKUP(A113,PARAMETROS!A:A,PARAMETROS!B:B)=0,"",_xlfn.XLOOKUP(A113,PARAMETROS!A:A,PARAMETROS!B:B)) -> 012009006234 | C113: =IF(_xlfn.XLOOKUP(A113,PARAMETROS!A:A,PARAMETROS!C:C)=0,"",_xlfn.XLOOKUP(A113,PARAMETROS!A:A,PARAMETROS!C:C)) -> 12 | D113: =IF(_xlfn.XLOOKUP(A113,PARAMETROS!A:A,PARAMETROS!D:D)=0,"",_xlfn.XLOOKUP(A113,PARAMETROS!A:A,PARAMETROS!D:D)) -> 9 | E113: =IF(_xlfn.XLOOKUP('PREENCHIMENTO|LETIVAS'!A113,PARAMETROS!A:A,PARAMETROS!I:I)=0,"",_xlfn.XLOOKUP('PREENCHIMENTO|LETIVAS'!A113,PARAMETROS!A:A,PARAMETROS!I:I)) -> PROFESSOR REGENTE | F113: 51|2026 | G113: 2 | H113: 2 - Segunda | I113: 19:00 às 20:30 | J113: ELETROTERMOFOTOTERAPIA E INOVAÇÃO TECNOLÓGICA | W113: =IF(I113<>"",2,0) -> 2
A114: HEVILA MARIA VIEIRA RUY | B114: =IF(_xlfn.XLOOKUP(A114,PARAMETROS!A:A,PARAMETROS!B:B)=0,"",_xlfn.XLOOKUP(A114,PARAMETROS!A:A,PARAMETROS!B:B)) -> 012009006234 | C114: =IF(_xlfn.XLOOKUP(A114,PARAMETROS!A:A,PARAMETROS!C:C)=0,"",_xlfn.XLOOKUP(A114,PARAMETROS!A:A,PARAMETROS!C:C)) -> 12 | D114: =IF(_xlfn.XLOOKUP(A114,PARAMETROS!A:A,PARAMETROS!D:D)=0,"",_xlfn.XLOOKUP(A114,PARAMETROS!A:A,PARAMETROS!D:D)) -> 9 | E114: =IF(_xlfn.XLOOKUP('PREENCHIMENTO|LETIVAS'!A114,PARAMETROS!A:A,PARAMETROS!I:I)=0,"",_xlfn.XLOOKUP('PREENCHIMENTO|LETIVAS'!A114,PARAMETROS!A:A,PARAMETROS!I:I)) -> PROFESSOR REGENTE | F114: 51|2026 | G114: 2 | H114: 2 - Segunda | I114: 20:40 às 22:10 | J114: ESTÉTICA FACIAL | W114: =IF(I114<>"",2,0) -> 2
A115: HEVILA MARIA VIEIRA RUY | B115: =IF(_xlfn.XLOOKUP(A115,PARAMETROS!A:A,PARAMETROS!B:B)=0,"",_xlfn.XLOOKUP(A115,PARAMETROS!A:A,PARAMETROS!B:B)) -> 012009006234 | C115: =IF(_xlfn.XLOOKUP(A115,PARAMETROS!A:A,PARAMETROS!C:C)=0,"",_xlfn.XLOOKUP(A115,PARAMETROS!A:A,PARAMETROS!C:C)) -> 12 | D115: =IF(_xlfn.XLOOKUP(A115,PARAMETROS!A:A,PARAMETROS!D:D)=0,"",_xlfn.XLOOKUP(A115,PARAMETROS!A:A,PARAMETROS!D:D)) -> 9 | E115: =IF(_xlfn.XLOOKUP('PREENCHIMENTO|LETIVAS'!A115,PARAMETROS!A:A,PARAMETROS!I:I)=0,"",_xlfn.XLOOKUP('PREENCHIMENTO|LETIVAS'!A115,PARAMETROS!A:A,PARAMETROS!I:I)) -> PROFESSOR REGENTE | F115: 51|2026 | G115: ESTENDIDA | H115: 4 - Quarta | I115: 20:40 às 22:10 | J115: ELETROTERMOFOTOTERAPIA | W115: =IF(I115<>"",2,0) -> 2
A116: HEVILA MARIA VIEIRA RUY | B116: =IF(_xlfn.XLOOKUP(A116,PARAMETROS!A:A,PARAMETROS!B:B)=0,"",_xlfn.XLOOKUP(A116,PARAMETROS!A:A,PARAMETROS!B:B)) -> 012009006234 | C116: =IF(_xlfn.XLOOKUP(A116,PARAMETROS!A:A,PARAMETROS!C:C)=0,"",_xlfn.XLOOKUP(A116,PARAMETROS!A:A,PARAMETROS!C:C)) -> 12 | D116: =IF(_xlfn.XLOOKUP(A116,PARAMETROS!A:A,PARAMETROS!D:D)=0,"",_xlfn.XLOOKUP(A116,PARAMETROS!A:A,PARAMETROS!D:D)) -> 9 | E116: =IF(_xlfn.XLOOKUP('PREENCHIMENTO|LETIVAS'!A116,PARAMETROS!A:A,PARAMETROS!I:I)=0,"",_xlfn.XLOOKUP('PREENCHIMENTO|LETIVAS'!A116,PARAMETROS!A:A,PARAMETROS!I:I)) -> PROFESSOR REGENTE | F116: 51|2026 | G116: ESTENDIDA | H116: 4 - Quarta | I116: 19:00 às 20:30 | J116: FISIOTERAPIA COMO PROFISSÃO | W116: =IF(I116<>"",2,0) -> 2
A117: NATALY DE CARVALHO FUGI | B117: =IF(_xlfn.XLOOKUP(A117,PARAMETROS!A:A,PARAMETROS!B:B)=0,"",_xlfn.XLOOKUP(A117,PARAMETROS!A:A,PARAMETROS!B:B)) -> 012009004311 | C117: =IF(_xlfn.XLOOKUP(A117,PARAMETROS!A:A,PARAMETROS!C:C)=0,"",_xlfn.XLOOKUP(A117,PARAMETROS!A:A,PARAMETROS!C:C)) -> 20 | D117: =IF(_xlfn.XLOOKUP(A117,PARAMETROS!A:A,PARAMETROS!D:D)=0,"",_xlfn.XLOOKUP(A117,PARAMETROS!A:A,PARAMETROS!D:D)) -> 2 | E117: =IF(_xlfn.XLOOKUP('PREENCHIMENTO|LETIVAS'!A117,PARAMETROS!A:A,PARAMETROS!I:I)=0,"",_xlfn.XLOOKUP('PREENCHIMENTO|LETIVAS'!A117,PARAMETROS!A:A,PARAMETROS!I:I)) -> PROFESSOR DE ENSINO SUPERIOR EAD | F117: 51|2026 | G117: 2 | H117: 3 - Terça | I117: 19:00 às 20:30 | J117: DIDÁTICA | W117: =IF(I117<>"",2,0) -> 2
A118: RIZIA FERRELLI LOURES LOYOLA FRANCO | B118: =IF(_xlfn.XLOOKUP(A118,PARAMETROS!A:A,PARAMETROS!B:B)=0,"",_xlfn.XLOOKUP(A118,PARAMETROS!A:A,PARAMETROS!B:B)) -> 012009005535 | C118: =IF(_xlfn.XLOOKUP(A118,PARAMETROS!A:A,PARAMETROS!C:C)=0,"",_xlfn.XLOOKUP(A118,PARAMETROS!A:A,PARAMETROS!C:C)) -> 40 | D118: =IF(_xlfn.XLOOKUP(A118,PARAMETROS!A:A,PARAMETROS!D:D)=0,"",_xlfn.XLOOKUP(A118,PARAMETROS!A:A,PARAMETROS!D:D)) -> 4 | E118: =IF(_xlfn.XLOOKUP('PREENCHIMENTO|LETIVAS'!A118,PARAMETROS!A:A,PARAMETROS!I:I)=0,"",_xlfn.XLOOKUP('PREENCHIMENTO|LETIVAS'!A118,PARAMETROS!A:A,PARAMETROS!I:I)) -> PROFESSOR DE ENSINO SUPERIOR EAD | F118: 51|2026 | G118: 2 | H118: 5 - Quinta | I118: 20:40 às 22:10 | J118: POLÍTICAS EDUCACIONAIS E FUNCIONAMENTO DA EDUCAÇÃO ESPECIAL | W118: =IF(I118<>"",2,0) -> 2
A119: RIZIA FERRELLI LOURES LOYOLA FRANCO | B119: =IF(_xlfn.XLOOKUP(A119,PARAMETROS!A:A,PARAMETROS!B:B)=0,"",_xlfn.XLOOKUP(A119,PARAMETROS!A:A,PARAMETROS!B:B)) -> 012009005535 | C119: =IF(_xlfn.XLOOKUP(A119,PARAMETROS!A:A,PARAMETROS!C:C)=0,"",_xlfn.XLOOKUP(A119,PARAMETROS!A:A,PARAMETROS!C:C)) -> 40 | D119: =IF(_xlfn.XLOOKUP(A119,PARAMETROS!A:A,PARAMETROS!D:D)=0,"",_xlfn.XLOOKUP(A119,PARAMETROS!A:A,PARAMETROS!D:D)) -> 4 | E119: =IF(_xlfn.XLOOKUP('PREENCHIMENTO|LETIVAS'!A119,PARAMETROS!A:A,PARAMETROS!I:I)=0,"",_xlfn.XLOOKUP('PREENCHIMENTO|LETIVAS'!A119,PARAMETROS!A:A,PARAMETROS!I:I)) -> PROFESSOR DE ENSINO SUPERIOR EAD | F119: 51|2026 | G119: 1 | H119: 5 - Quinta | I119: 19:00 às 20:30 | J119: METODOLOGIA DO ENSINO DA ARTE E DA MÚSICA | W119: =IF(I119<>"",2,0) -> 2
A120: TALITA MEIRELES FLORES | B120: =IF(_xlfn.XLOOKUP(A120,PARAMETROS!A:A,PARAMETROS!B:B)=0,"",_xlfn.XLOOKUP(A120,PARAMETROS!A:A,PARAMETROS!B:B)) -> 012009006315 | C120: =IF(_xlfn.XLOOKUP(A120,PARAMETROS!A:A,PARAMETROS!C:C)=0,"",_xlfn.XLOOKUP(A120,PARAMETROS!A:A,PARAMETROS!C:C)) -> 12 | D120: =IF(_xlfn.XLOOKUP(A120,PARAMETROS!A:A,PARAMETROS!D:D)=0,"",_xlfn.XLOOKUP(A120,PARAMETROS!A:A,PARAMETROS!D:D)) -> 9 | E120: =IF(_xlfn.XLOOKUP('PREENCHIMENTO|LETIVAS'!A120,PARAMETROS!A:A,PARAMETROS!I:I)=0,"",_xlfn.XLOOKUP('PREENCHIMENTO|LETIVAS'!A120,PARAMETROS!A:A,PARAMETROS!I:I)) -> PROFESSOR REGENTE | F120: 51|2026 | G120: 2 | H120: 5 - Quinta | I120: 20:40 às 22:10 | J120: TEORIA E PRÁTICA: DEFICIÊNCIA VISUAL | W120: =IF(I120<>"",2,0) -> 2
A121: TALITA MEIRELES FLORES | B121: =IF(_xlfn.XLOOKUP(A121,PARAMETROS!A:A,PARAMETROS!B:B)=0,"",_xlfn.XLOOKUP(A121,PARAMETROS!A:A,PARAMETROS!B:B)) -> 012009006315 | C121: =IF(_xlfn.XLOOKUP(A121,PARAMETROS!A:A,PARAMETROS!C:C)=0,"",_xlfn.XLOOKUP(A121,PARAMETROS!A:A,PARAMETROS!C:C)) -> 12 | D121: =IF(_xlfn.XLOOKUP(A121,PARAMETROS!A:A,PARAMETROS!D:D)=0,"",_xlfn.XLOOKUP(A121,PARAMETROS!A:A,PARAMETROS!D:D)) -> 9 | E121: =IF(_xlfn.XLOOKUP('PREENCHIMENTO|LETIVAS'!A121,PARAMETROS!A:A,PARAMETROS!I:I)=0,"",_xlfn.XLOOKUP('PREENCHIMENTO|LETIVAS'!A121,PARAMETROS!A:A,PARAMETROS!I:I)) -> PROFESSOR REGENTE | F121: 51|2026 | G121: 1 | H121: 3 - Terça | I121: 19:00 às 20:30 | J121: NEUROCIÊNCIA E APRENDIZAGEM | W121: =IF(I197<>"",2,0) -> 2
A122: MARIA CAROLINA MIESSE | B122: =IF(_xlfn.XLOOKUP(A122,PARAMETROS!A:A,PARAMETROS!B:B)=0,"",_xlfn.XLOOKUP(A122,PARAMETROS!A:A,PARAMETROS!B:B)) -> 012009004461 | C122: =IF(_xlfn.XLOOKUP(A122,PARAMETROS!A:A,PARAMETROS!C:C)=0,"",_xlfn.XLOOKUP(A122,PARAMETROS!A:A,PARAMETROS!C:C)) -> 20 | D122: =IF(_xlfn.XLOOKUP(A122,PARAMETROS!A:A,PARAMETROS!D:D)=0,"",_xlfn.XLOOKUP(A122,PARAMETROS!A:A,PARAMETROS!D:D)) -> 2 | E122: =IF(_xlfn.XLOOKUP('PREENCHIMENTO|LETIVAS'!A122,PARAMETROS!A:A,PARAMETROS!I:I)=0,"",_xlfn.XLOOKUP('PREENCHIMENTO|LETIVAS'!A122,PARAMETROS!A:A,PARAMETROS!I:I)) -> PROFESSOR DE ENSINO SUPERIOR EAD | F122: 51|2026 | G122: 2 | H122: 5 - Quinta | I122: 19:00 às 20:30 | J122: TEORIAS PEDAGÓGICAS APLICADAS À EDUCAÇÃO ESPECIAL | W122: =IF(I122<>"",2,0) -> 2
A123: ANDERSON DOUGLAS DA SILVA | B123: =IF(_xlfn.XLOOKUP(A123,PARAMETROS!A:A,PARAMETROS!B:B)=0,"",_xlfn.XLOOKUP(A123,PARAMETROS!A:A,PARAMETROS!B:B)) -> 012009006177 | C123: =IF(_xlfn.XLOOKUP(A123,PARAMETROS!A:A,PARAMETROS!C:C)=0,"",_xlfn.XLOOKUP(A123,PARAMETROS!A:A,PARAMETROS!C:C)) -> 12 | D123: =IF(_xlfn.XLOOKUP(A123,PARAMETROS!A:A,PARAMETROS!D:D)=0,"",_xlfn.XLOOKUP(A123,PARAMETROS!A:A,PARAMETROS!D:D)) -> 9 | E123: =IF(_xlfn.XLOOKUP('PREENCHIMENTO|LETIVAS'!A123,PARAMETROS!A:A,PARAMETROS!I:I)=0,"",_xlfn.XLOOKUP('PREENCHIMENTO|LETIVAS'!A123,PARAMETROS!A:A,PARAMETROS!I:I)) -> PROFESSOR REGENTE | F123: 51|2026 | G123: 1 | H123: 5 - Quinta | I123: 20:40 às 22:10 | J123: TRANSTORNO GLOBAL DO DESENVOLVIMENTO: ENSINO E APRENDIZAGEM NO CONTEXTO INCLUSIVO | W123: =IF(I123<>"",2,0) -> 2
A124: ANDERSON DOUGLAS DA SILVA | B124: =IF(_xlfn.XLOOKUP(A124,PARAMETROS!A:A,PARAMETROS!B:B)=0,"",_xlfn.XLOOKUP(A124,PARAMETROS!A:A,PARAMETROS!B:B)) -> 012009006177 | C124: =IF(_xlfn.XLOOKUP(A124,PARAMETROS!A:A,PARAMETROS!C:C)=0,"",_xlfn.XLOOKUP(A124,PARAMETROS!A:A,PARAMETROS!C:C)) -> 12 | D124: =IF(_xlfn.XLOOKUP(A124,PARAMETROS!A:A,PARAMETROS!D:D)=0,"",_xlfn.XLOOKUP(A124,PARAMETROS!A:A,PARAMETROS!D:D)) -> 9 | E124: =IF(_xlfn.XLOOKUP('PREENCHIMENTO|LETIVAS'!A124,PARAMETROS!A:A,PARAMETROS!I:I)=0,"",_xlfn.XLOOKUP('PREENCHIMENTO|LETIVAS'!A124,PARAMETROS!A:A,PARAMETROS!I:I)) -> PROFESSOR REGENTE | F124: 51|2026 | G124: 1 | H124: 5 - Quinta | I124: 19:00 às 20:30 | J124: NEUROCIÊNCIA E APRENDIZAGEM | W124: =IF(I124<>"",2,0) -> 2
...

Sheet PREENCHIMENTO|NÃO-LETIVAS
A1: - Considerar as atividades presentes na lista da coluna G; - Caso o total de horas dedicadas seja superior ao limite semanal de um professor, as linhas correspondentes ao nome dele ficarão vermelhas.
A8: LISTAS SUSPENSAS (Apenas Seleção)
A9: PROFESSOR(A) | B9: CHAPA | C9: CH SEMANAL | D9: CH NÃO-LETIVA | E9: CARGO | F9: MÓDULO | G9: ATIVIDADE | H9: CH DEDICADA | I9: OBSERVAÇÃO
B10: =IF(_xlfn.XLOOKUP(A10,PARAMETROS!A:A,PARAMETROS!B:B)=0,"",_xlfn.XLOOKUP(A10,PARAMETROS!A:A,PARAMETROS!B:B)) | C10: =IF(_xlfn.XLOOKUP(A10,PARAMETROS!A:A,PARAMETROS!C:C)=0,"",_xlfn.XLOOKUP(A10,PARAMETROS!A:A,PARAMETROS!C:C)) | D10: =IF(_xlfn.XLOOKUP(A10,PARAMETROS!A:A,PARAMETROS!E:E)=0,"",_xlfn.XLOOKUP(A10,PARAMETROS!A:A,PARAMETROS!E:E)) | E10: =IF(_xlfn.XLOOKUP('PREENCHIMENTO|NÃO-LETIVAS'!A10,PARAMETROS!A:A,PARAMETROS!I:I)=0,"",_xlfn.XLOOKUP('PREENCHIMENTO|NÃO-LETIVAS'!A10,PARAMETROS!A:A,PARAMETROS!I:I)) | Y10: =_xlfn.XLOOKUP(G:G,PARAMETROS!Y:Y,PARAMETROS!AD:AD) -> 0
B11: =IF(_xlfn.XLOOKUP(A11,PARAMETROS!A:A,PARAMETROS!B:B)=0,"",_xlfn.XLOOKUP(A11,PARAMETROS!A:A,PARAMETROS!B:B)) | C11: =IF(_xlfn.XLOOKUP(A11,PARAMETROS!A:A,PARAMETROS!C:C)=0,"",_xlfn.XLOOKUP(A11,PARAMETROS!A:A,PARAMETROS!C:C)) | D11: =IF(_xlfn.XLOOKUP(A11,PARAMETROS!A:A,PARAMETROS!E:E)=0,"",_xlfn.XLOOKUP(A11,PARAMETROS!A:A,PARAMETROS!E:E)) | E11: =IF(_xlfn.XLOOKUP('PREENCHIMENTO|NÃO-LETIVAS'!A11,PARAMETROS!A:A,PARAMETROS!I:I)=0,"",_xlfn.XLOOKUP('PREENCHIMENTO|NÃO-LETIVAS'!A11,PARAMETROS!A:A,PARAMETROS!I:I)) | Y11: =_xlfn.XLOOKUP(G:G,PARAMETROS!Y:Y,PARAMETROS!AD:AD) -> 0
B12: =IF(_xlfn.XLOOKUP(A12,PARAMETROS!A:A,PARAMETROS!B:B)=0,"",_xlfn.XLOOKUP(A12,PARAMETROS!A:A,PARAMETROS!B:B)) | C12: =IF(_xlfn.XLOOKUP(A12,PARAMETROS!A:A,PARAMETROS!C:C)=0,"",_xlfn.XLOOKUP(A12,PARAMETROS!A:A,PARAMETROS!C:C)) | D12: =IF(_xlfn.XLOOKUP(A12,PARAMETROS!A:A,PARAMETROS!E:E)=0,"",_xlfn.XLOOKUP(A12,PARAMETROS!A:A,PARAMETROS!E:E)) | E12: =IF(_xlfn.XLOOKUP('PREENCHIMENTO|NÃO-LETIVAS'!A12,PARAMETROS!A:A,PARAMETROS!I:I)=0,"",_xlfn.XLOOKUP('PREENCHIMENTO|NÃO-LETIVAS'!A12,PARAMETROS!A:A,PARAMETROS!I:I)) | Y12: =_xlfn.XLOOKUP(G:G,PARAMETROS!Y:Y,PARAMETROS!AD:AD) -> 0
B13: =IF(_xlfn.XLOOKUP(A13,PARAMETROS!A:A,PARAMETROS!B:B)=0,"",_xlfn.XLOOKUP(A13,PARAMETROS!A:A,PARAMETROS!B:B)) | C13: =IF(_xlfn.XLOOKUP(A13,PARAMETROS!A:A,PARAMETROS!C:C)=0,"",_xlfn.XLOOKUP(A13,PARAMETROS!A:A,PARAMETROS!C:C)) | D13: =IF(_xlfn.XLOOKUP(A13,PARAMETROS!A:A,PARAMETROS!E:E)=0,"",_xlfn.XLOOKUP(A13,PARAMETROS!A:A,PARAMETROS!E:E)) | E13: =IF(_xlfn.XLOOKUP('PREENCHIMENTO|NÃO-LETIVAS'!A13,PARAMETROS!A:A,PARAMETROS!I:I)=0,"",_xlfn.XLOOKUP('PREENCHIMENTO|NÃO-LETIVAS'!A13,PARAMETROS!A:A,PARAMETROS!I:I)) | Y13: =_xlfn.XLOOKUP(G:G,PARAMETROS!Y:Y,PARAMETROS!AD:AD) -> 0
B14: =IF(_xlfn.XLOOKUP(A14,PARAMETROS!A:A,PARAMETROS!B:B)=0,"",_xlfn.XLOOKUP(A14,PARAMETROS!A:A,PARAMETROS!B:B)) | C14: =IF(_xlfn.XLOOKUP(A14,PARAMETROS!A:A,PARAMETROS!C:C)=0,"",_xlfn.XLOOKUP(A14,PARAMETROS!A:A,PARAMETROS!C:C)) | D14: =IF(_xlfn.XLOOKUP(A14,PARAMETROS!A:A,PARAMETROS!E:E)=0,"",_xlfn.XLOOKUP(A14,PARAMETROS!A:A,PARAMETROS!E:E)) | E14: =IF(_xlfn.XLOOKUP('PREENCHIMENTO|NÃO-LETIVAS'!A14,PARAMETROS!A:A,PARAMETROS!I:I)=0,"",_xlfn.XLOOKUP('PREENCHIMENTO|NÃO-LETIVAS'!A14,PARAMETROS!A:A,PARAMETROS!I:I)) | Y14: =_xlfn.XLOOKUP(G:G,PARAMETROS!Y:Y,PARAMETROS!AD:AD) -> 0
B15: =IF(_xlfn.XLOOKUP(A15,PARAMETROS!A:A,PARAMETROS!B:B)=0,"",_xlfn.XLOOKUP(A15,PARAMETROS!A:A,PARAMETROS!B:B)) | C15: =IF(_xlfn.XLOOKUP(A15,PARAMETROS!A:A,PARAMETROS!C:C)=0,"",_xlfn.XLOOKUP(A15,PARAMETROS!A:A,PARAMETROS!C:C)) | D15: =IF(_xlfn.XLOOKUP(A15,PARAMETROS!A:A,PARAMETROS!E:E)=0,"",_xlfn.XLOOKUP(A15,PARAMETROS!A:A,PARAMETROS!E:E)) | E15: =IF(_xlfn.XLOOKUP('PREENCHIMENTO|NÃO-LETIVAS'!A15,PARAMETROS!A:A,PARAMETROS!I:I)=0,"",_xlfn.XLOOKUP('PREENCHIMENTO|NÃO-LETIVAS'!A15,PARAMETROS!A:A,PARAMETROS!I:I)) | Y15: =_xlfn.XLOOKUP(G:G,PARAMETROS!Y:Y,PARAMETROS!AD:AD) -> 0
B16: =IF(_xlfn.XLOOKUP(A16,PARAMETROS!A:A,PARAMETROS!B:B)=0,"",_xlfn.XLOOKUP(A16,PARAMETROS!A:A,PARAMETROS!B:B)) | C16: =IF(_xlfn.XLOOKUP(A16,PARAMETROS!A:A,PARAMETROS!C:C)=0,"",_xlfn.XLOOKUP(A16,PARAMETROS!A:A,PARAMETROS!C:C)) | D16: =IF(_xlfn.XLOOKUP(A16,PARAMETROS!A:A,PARAMETROS!E:E)=0,"",_xlfn.XLOOKUP(A16,PARAMETROS!A:A,PARAMETROS!E:E)) | E16: =IF(_xlfn.XLOOKUP('PREENCHIMENTO|NÃO-LETIVAS'!A16,PARAMETROS!A:A,PARAMETROS!I:I)=0,"",_xlfn.XLOOKUP('PREENCHIMENTO|NÃO-LETIVAS'!A16,PARAMETROS!A:A,PARAMETROS!I:I)) | Y16: =_xlfn.XLOOKUP(G:G,PARAMETROS!Y:Y,PARAMETROS!AD:AD) -> 0
B17: =IF(_xlfn.XLOOKUP(A17,PARAMETROS!A:A,PARAMETROS!B:B)=0,"",_xlfn.XLOOKUP(A17,PARAMETROS!A:A,PARAMETROS!B:B)) | C17: =IF(_xlfn.XLOOKUP(A17,PARAMETROS!A:A,PARAMETROS!C:C)=0,"",_xlfn.XLOOKUP(A17,PARAMETROS!A:A,PARAMETROS!C:C)) | D17: =IF(_xlfn.XLOOKUP(A17,PARAMETROS!A:A,PARAMETROS!E:E)=0,"",_xlfn.XLOOKUP(A17,PARAMETROS!A:A,PARAMETROS!E:E)) | E17: =IF(_xlfn.XLOOKUP('PREENCHIMENTO|NÃO-LETIVAS'!A17,PARAMETROS!A:A,PARAMETROS!I:I)=0,"",_xlfn.XLOOKUP('PREENCHIMENTO|NÃO-LETIVAS'!A17,PARAMETROS!A:A,PARAMETROS!I:I)) | Y17: =_xlfn.XLOOKUP(G:G,PARAMETROS!Y:Y,PARAMETROS!AD:AD) -> 0
B18: =IF(_xlfn.XLOOKUP(A18,PARAMETROS!A:A,PARAMETROS!B:B)=0,"",_xlfn.XLOOKUP(A18,PARAMETROS!A:A,PARAMETROS!B:B)) | C18: =IF(_xlfn.XLOOKUP(A18,PARAMETROS!A:A,PARAMETROS!C:C)=0,"",_xlfn.XLOOKUP(A18,PARAMETROS!A:A,PARAMETROS!C:C)) | D18: =IF(_xlfn.XLOOKUP(A18,PARAMETROS!A:A,PARAMETROS!E:E)=0,"",_xlfn.XLOOKUP(A18,PARAMETROS!A:A,PARAMETROS!E:E)) | E18: =IF(_xlfn.XLOOKUP('PREENCHIMENTO|NÃO-LETIVAS'!A18,PARAMETROS!A:A,PARAMETROS!I:I)=0,"",_xlfn.XLOOKUP('PREENCHIMENTO|NÃO-LETIVAS'!A18,PARAMETROS!A:A,PARAMETROS!I:I)) | Y18: =_xlfn.XLOOKUP(G:G,PARAMETROS!Y:Y,PARAMETROS!AD:AD) -> 0
B19: =IF(_xlfn.XLOOKUP(A19,PARAMETROS!A:A,PARAMETROS!B:B)=0,"",_xlfn.XLOOKUP(A19,PARAMETROS!A:A,PARAMETROS!B:B)) | C19: =IF(_xlfn.XLOOKUP(A19,PARAMETROS!A:A,PARAMETROS!C:C)=0,"",_xlfn.XLOOKUP(A19,PARAMETROS!A:A,PARAMETROS!C:C)) | D19: =IF(_xlfn.XLOOKUP(A19,PARAMETROS!A:A,PARAMETROS!E:E)=0,"",_xlfn.XLOOKUP(A19,PARAMETROS!A:A,PARAMETROS!E:E)) | E19: =IF(_xlfn.XLOOKUP('PREENCHIMENTO|NÃO-LETIVAS'!A19,PARAMETROS!A:A,PARAMETROS!I:I)=0,"",_xlfn.XLOOKUP('PREENCHIMENTO|NÃO-LETIVAS'!A19,PARAMETROS!A:A,PARAMETROS!I:I)) | Y19: =_xlfn.XLOOKUP(G:G,PARAMETROS!Y:Y,PARAMETROS!AD:AD) -> 0
B20: =IF(_xlfn.XLOOKUP(A20,PARAMETROS!A:A,PARAMETROS!B:B)=0,"",_xlfn.XLOOKUP(A20,PARAMETROS!A:A,PARAMETROS!B:B)) | C20: =IF(_xlfn.XLOOKUP(A20,PARAMETROS!A:A,PARAMETROS!C:C)=0,"",_xlfn.XLOOKUP(A20,PARAMETROS!A:A,PARAMETROS!C:C)) | D20: =IF(_xlfn.XLOOKUP(A20,PARAMETROS!A:A,PARAMETROS!E:E)=0,"",_xlfn.XLOOKUP(A20,PARAMETROS!A:A,PARAMETROS!E:E)) | E20: =IF(_xlfn.XLOOKUP('PREENCHIMENTO|NÃO-LETIVAS'!A20,PARAMETROS!A:A,PARAMETROS!I:I)=0,"",_xlfn.XLOOKUP('PREENCHIMENTO|NÃO-LETIVAS'!A20,PARAMETROS!A:A,PARAMETROS!I:I)) | Y20: =_xlfn.XLOOKUP(G:G,PARAMETROS!Y:Y,PARAMETROS!AD:AD) -> 0
B21: =IF(_xlfn.XLOOKUP(A21,PARAMETROS!A:A,PARAMETROS!B:B)=0,"",_xlfn.XLOOKUP(A21,PARAMETROS!A:A,PARAMETROS!B:B)) | C21: =IF(_xlfn.XLOOKUP(A21,PARAMETROS!A:A,PARAMETROS!C:C)=0,"",_xlfn.XLOOKUP(A21,PARAMETROS!A:A,PARAMETROS!C:C)) | D21: =IF(_xlfn.XLOOKUP(A21,PARAMETROS!A:A,PARAMETROS!E:E)=0,"",_xlfn.XLOOKUP(A21,PARAMETROS!A:A,PARAMETROS!E:E)) | E21: =IF(_xlfn.XLOOKUP('PREENCHIMENTO|NÃO-LETIVAS'!A21,PARAMETROS!A:A,PARAMETROS!I:I)=0,"",_xlfn.XLOOKUP('PREENCHIMENTO|NÃO-LETIVAS'!A21,PARAMETROS!A:A,PARAMETROS!I:I)) | Y21: =_xlfn.XLOOKUP(G:G,PARAMETROS!Y:Y,PARAMETROS!AD:AD) -> 0
... B500: =IF(_xlfn.XLOOKUP(A500,PARAMETROS!A:A,PARAMETROS!B:B)=0,"",_xlfn.XLOOKUP(A500,PARAMETROS!A:A,PARAMETROS!B:B)) | C500: =IF(_xlfn.XLOOKUP(A500,PARAMETROS!A:A,PARAMETROS!C:C)=0,"",_xlfn.XLOOKUP(A500,PARAMETROS!A:A,PARAMETROS!C:C)) | D500: =IF(_xlfn.XLOOKUP(A500,PARAMETROS!A:A,PARAMETROS!E:E)=0,"",_xlfn.XLOOKUP(A500,PARAMETROS!A:A,PARAMETROS!E:E)) | E500: =IF(_xlfn.XLOOKUP('PREENCHIMENTO|NÃO-LETIVAS'!A500,PARAMETROS!A:A,PARAMETROS!I:I)=0,"",_xlfn.XLOOKUP('PREENCHIMENTO|NÃO-LETIVAS'!A500,PARAMETROS!A:A,PARAMETROS!I:I)) | Y500: =_xlfn.XLOOKUP(G:G,PARAMETROS!Y:Y,PARAMETROS!AD:AD) -> 0
